Workbook

Sheet Driver Data
A1: Driver ID | B1: Full Name | C1: Full Address | D1: Phone | E1: SSN (Masked) | F1: Bank Name | G1: Routing Number | H1: Account Number | I1: Document Type | J1: Status | K1: Document Number | L1: CDL Expiration | M1: Med Card Expiration | N1: MVR Expiration | O1: Incident Details | P1: Hair Color | Q1: Eye Color | R1: Height | S1: Weight | T1: Gender | U1: DOB | V1: Driver Photo | W1: Ethnicity | X1: Email | Y1: Street Address | Z1: City | AA1: State | AB1: ZIP | AC1: State of Residence | AD1: License Class | AE1: CDL Issue Date | AF1: CDL Endorsements | AG1: CDL Restrictions | AH1: Medical Issue Date | AI1: Medical Certificate Number | AJ1: Medical Examiner Name | AK1: Medical Examiner Registry Number | AL1: Medical Restrictions | AM1: Medical Status | AN1: MVR Review Date | AO1: Violation Points | AP1: Accidents on Record | AQ1: MVR Restrictions | AR1: MVR Status | AS1: Hire Date | AT1: Work Authorization Status | AU1: I9 Document 1 | AV1: I9 Document 2 | AW1: I9 Document 3 | AX1: I9 Completion Date | AY1: Employer Representative | AZ1: I9 Status | BA1: Business Name | BB1: Tax Classification | BC1: TIN Type | BD1: TIN | BE1: Exemption Codes | BF1: W9 Submission Date | BG1: W9 Status | BH1: Account Type | BI1: Payment Preference | BJ1: Bank Info Submission Date | BK1: Bank Info Status | BL1: Road Test Date | BM1: Examiner Name | BN1: Vehicle Type | BO1: Trailer Type | BP1: Road Test Location | BQ1: Pre-Trip Inspection Score | BR1: Vehicle Control Score | BS1: Backing Score | BT1: Turning Score | BU1: Braking Score | BV1: Mirror Use Score | BW1: Coupling Score | BX1: Defensive Driving Score | BY1: Overall Safety Score | BZ1: Road Test Result | CA1: Restrictions or Recommendations | CB1: Road Test Status | CC1: Drug and Alcohol Status | CD1: Clearinghouse Status | CE1: Compliance Review Date | CF1: Next Review Date | CG1: Open Deficiencies | CH1: Compliance Status | CI1: Notes | CJ1: First Name | CK1: Last Name | CL1: 5876 Driver License Number | CM1: 5876 License Issuing State | CN1: 5876 CLP/CDL Applicant/Holder | CO1: 5876 Driver Signature Name | CP1: 5876 Driver Signature Date | CQ1: 5876 Certificate Expiration Date | CR1: 5876 Medical Examiner Telephone | CS1: 5876 Medical Examiner Signature Name | CT1: 5876 Date Certificate Signed | CU1: 5876 Medical Examiner License Number | CV1: 5876 National Registry Number | CW1: 5876 Practitioner Type | CX1: 5876 Issuing State/Province | CY1: 5876 Certification Basis | CZ1: 5876 State Variance Details | DA1: 5876 Waiver/Exemption | DB1: 5876 SPE Certificate | DC1: 5876 Exempt Intracity Zone | DD1: 5876 Grandfathered from State Requirements | DE1: 5876 Wearing Corrective Lenses | DF1: 5876 Wearing Hearing Aid | DG1: Emergency Contact Name | DH1: Emergency Contact Relation | DI1: Emergency Contact Phone | DJ1: 5875 High Blood Pressure | DK1: 5875 Diabetes | DL1: 5875 Sleep Apnea | DM1: 5875 Heart Disease | DN1: 5875 Surgeries | DO1: 5875 Vision Score Right | DP1: 5875 Vision Score Left | DQ1: 5875 Hearing Score | DR1: 5875 Blood Pressure Sys | DS1: 5875 Blood Pressure Dia | DT1: 5875 Pulse | DU1: 5875 Urinalysis | DV1: Clearinghouse Consent Date | DW1: Drug Test Result Date | DX1: Drug Test Result | DY1: Safety Policy Ack Date | DZ1: Safety Policy Name | EA1: DQF Status | EB1: DQF Audit Date
A2: DRV-001 | B2: John Carter | C2: 220 Demo Street, Cleveland, OH 44113 | D2: 206-555-0102 | E2: ***-**-0123 | F2: Huntington | G2: 104 | H2: 999900202 | I2: CDL Summary | J2: VALID | K2: OH0000075 | L2: 46621 | M2: 46272 | N2: 46310 | P2: Black | Q2: Green | R2: 5'-10" | S2: 180 | T2: M | U2: 25934 | V2: DRV-001.png | W2: Caucasian | X2: jcarter@example.com | Y2: 220 Demo Street | Z2: Cleveland | AA2: OH | AB2: 44113 | AC2: OH | AD2: Class A | AE2: 44799 | AF2: N,T | AH2: 45364 | AI2: MC-0010108 | AJ2: Dr. Patricia Owens | AK2: ME100001 | AM2: Qualified | AN2: 46050 | AO2: 0 | AP2: 0 | AR2: Clear | AS2: 45392 | AT2: Authorized to Work | AU2: U.S. Passport | AX2: 45392 | AY2: BOF Onboarding Team | AZ2: Complete | BB2: Individual/Sole Proprietor | BC2: SSN | BD2: ***-**-0123 | BF2: 45392 | BG2: Received | BH2: Checking | BI2: Direct Deposit | BJ2: 45392 | BK2: Verified | BL2: 45385 | BM2: A. Reynolds | BN2: Sleeper tractor | BO2: 53 ft dry van | BP2: Cleveland, OH | BQ2: 5 | BR2: 5 | BS2: 4 | BT2: 5 | BU2: 5 | BV2: 5 | BW2: 4 | BX2: 5 | BY2: 5 | BZ2: Pass | CB2: Passed | CC2: Enrolled | CD2: Query Completed | CE2: 46037 | CF2: 46218 | CH2: Compliant | CJ2: John | CK2: Carter | CL2: OH0000075 | CM2: OH | CN2: CDL Holder | CO2: John Carter | CP2: 45364 | CQ2: 46094 | CR2: (614) 555-0107 | CS2: Dr. Patricia Owens | CT2: 45364 | CU2: OH-ME-970443 | CV2: ME100001 | CW2: Chiropractor | CX2: OH | CY2: Federal Motor Carrier Safety Regulations | DA2: No | DB2: No | DC2: No | DD2: No | DE2: No | DF2: No | DG2: Sarah Carter | DH2: Spouse | DI2: 206-555-0199 | DJ2: No | DK2: No | DL2: No | DM2: No | DN2: Yes - Appendectomy (2005) | DO2: 20/20 | DP2: 20/20 | DQ2: Pass | DR2: 118 | DS2: 78 | DT2: 72 | DU2: Normal | DV2: 45392 | DW2: 45394 | DX2: Negative | DY2: 45397 | DZ2: BOF Fleet Safety & Compliance Policy 2024 | EA2: Complete | EB2: 45413
A3: DRV-001 | B3: John Carter | C3: 220 Demo Street, Cleveland, OH 44113 | D3: 206-555-0102 | E3: ***-**-0123 | F3: Huntington | G3: 104 | H3: 999900202 | I3: Medical Certification | J3: VALID | K3: OH0000092 | L3: 46621 | M3: 46273 | N3: 46311 | P3: Black | Q3: Green | R3: 5'-10" | S3: 180 | T3: M | U3: 25934 | V3: DRV-001.png | W3: Caucasian | X3: jcarter@example.com | Y3: 220 Demo Street | Z3: Cleveland | AA3: OH | AB3: 44113 | AC3: OH | AD3: Class A | AE3: 44799 | AF3: N,T | AH3: 45364 | AI3: MC-0010108 | AJ3: Dr. Patricia Owens | AK3: ME100001 | AM3: Qualified | AN3: 46050 | AO3: 0 | AP3: 0 | AR3: Clear | AS3: 45392 | AT3: Authorized to Work | AU3: U.S. Passport | AX3: 45392 | AY3: BOF Onboarding Team | AZ3: Complete | BB3: Individual/Sole Proprietor | BC3: SSN | BD3: ***-**-0123 | BF3: 45392 | BG3: Received | BH3: Checking | BI3: Direct Deposit | BJ3: 45392 | BK3: Verified | BL3: 45385 | BM3: A. Reynolds | BN3: Sleeper tractor | BO3: 53 ft dry van | BP3: Cleveland, OH | BQ3: 5 | BR3: 5 | BS3: 4 | BT3: 5 | BU3: 5 | BV3: 5 | BW3: 4 | BX3: 5 | BY3: 5 | BZ3: Pass | CB3: Passed | CC3: Enrolled | CD3: Query Completed | CE3: 46037 | CF3: 46218 | CH3: Compliant | CJ3: John | CK3: Carter | CL3: OH0000076 | CM3: OH | CN3: CDL Holder | CO3: John Carter | CP3: 45364 | CQ3: 46094 | CR3: (614) 555-0107 | CS3: Dr. Patricia Owens | CT3: 45364 | CU3: OH-ME-970443 | CV3: ME100001 | CW3: Chiropractor | CX3: OH | CY3: Federal Motor Carrier Safety Regulations | DA3: No | DB3: No | DC3: No | DD3: No | DE3: No | DF3: No | DG3: Sarah Carter | DH3: Spouse | DI3: 206-555-0199 | DJ3: No | DK3: No | DL3: No | DM3: No | DN3: Yes - Appendectomy (2005) | DO3: 20/20 | DP3: 20/20 | DQ3: Pass | DR3: 118 | DS3: 78 | DT3: 72 | DU3: Normal | DV3: 45392 | DW3: 45394 | DX3: Negative | DY3: 45397 | DZ3: BOF Fleet Safety & Compliance Policy 2024 | EA3: Complete | EB3: 45413
A4: DRV-001 | B4: John Carter | C4: 220 Demo Street, Cleveland, OH 44113 | D4: 206-555-0102 | E4: ***-**-0123 | F4: Huntington | G4: 104 | H4: 999900202 | I4: MVR Background Report | J4: VALID | K4: OH0000111 | L4: 46621 | M4: 46274 | N4: 46312 | P4: Black | Q4: Green | R4: 5'-10" | S4: 180 | T4: M | U4: 25934 | V4: DRV-001.png | W4: Caucasian | X4: jcarter@example.com | Y4: 220 Demo Street | Z4: Cleveland | AA4: OH | AB4: 44113 | AC4: OH | AD4: Class A | AE4: 44799 | AF4: N,T | AH4: 45364 | AI4: MC-0010108 | AJ4: Dr. Patricia Owens | AK4: ME100001 | AM4: Qualified | AN4: 46050 | AO4: 0 | AP4: 0 | AR4: Clear | AS4: 45392 | AT4: Authorized to Work | AU4: U.S. Passport | AX4: 45392 | AY4: BOF Onboarding Team | AZ4: Complete | BB4: Individual/Sole Proprietor | BC4: SSN | BD4: ***-**-0123 | BF4: 45392 | BG4: Received | BH4: Checking | BI4: Direct Deposit | BJ4: 45392 | BK4: Verified | BL4: 45385 | BM4: A. Reynolds | BN4: Sleeper tractor | BO4: 53 ft dry van | BP4: Cleveland, OH | BQ4: 5 | BR4: 5 | BS4: 4 | BT4: 5 | BU4: 5 | BV4: 5 | BW4: 4 | BX4: 5 | BY4: 5 | BZ4: Pass | CB4: Passed | CC4: Enrolled | CD4: Query Completed | CE4: 46037 | CF4: 46218 | CH4: Compliant | CJ4: John | CK4: Carter | CL4: OH0000077 | CM4: OH | CN4: CDL Holder | CO4: John Carter | CP4: 45364 | CQ4: 46094 | CR4: (614) 555-0107 | CS4: Dr. Patricia Owens | CT4: 45364 | CU4: OH-ME-970443 | CV4: ME100001 | CW4: Chiropractor | CX4: OH | CY4: Federal Motor Carrier Safety Regulations | DA4: No | DB4: No | DC4: No | DD4: No | DE4: No | DF4: No | DG4: Sarah Carter | DH4: Spouse | DI4: 206-555-0199 | DJ4: No | DK4: No | DL4: No | DM4: No | DN4: Yes - Appendectomy (2005) | DO4: 20/20 | DP4: 20/20 | DQ4: Pass | DR4: 118 | DS4: 78 | DT4: 72 | DU4: Normal | DV4: 45392 | DW4: 45394 | DX4: Negative | DY4: 45397 | DZ4: BOF Fleet Safety & Compliance Policy 2024 | EA4: Complete | EB4: 45413
A5: DRV-001 | B5: John Carter | C5: 220 Demo Street, Cleveland, OH 44113 | D5: 206-555-0102 | E5: ***-**-0123 | F5: Huntington | G5: 104 | H5: 999900202 | I5: Driver Application | J5: VALID | K5: OH0000127 | L5: 46621 | M5: 46275 | N5: 46313 | P5: Black | Q5: Green | R5: 5'-10" | S5: 180 | T5: M | U5: 25934 | V5: DRV-001.png | W5: Caucasian | X5: jcarter@example.com | Y5: 220 Demo Street | Z5: Cleveland | AA5: OH | AB5: 44113 | AC5: OH | AD5: Class A | AE5: 44799 | AF5: N,T | AH5: 45364 | AI5: MC-0010108 | AJ5: Dr. Patricia Owens | AK5: ME100001 | AM5: Qualified | AN5: 46050 | AO5: 0 | AP5: 0 | AR5: Clear | AS5: 45392 | AT5: Authorized to Work | AU5: U.S. Passport | AX5: 45392 | AY5: BOF Onboarding Team | AZ5: Complete | BB5: Individual/Sole Proprietor | BC5: SSN | BD5: ***-**-0123 | BF5: 45392 | BG5: Received | BH5: Checking | BI5: Direct Deposit | BJ5: 45392 | BK5: Verified | BL5: 45385 | BM5: A. Reynolds | BN5: Sleeper tractor | BO5: 53 ft dry van | BP5: Cleveland, OH | BQ5: 5 | BR5: 5 | BS5: 4 | BT5: 5 | BU5: 5 | BV5: 5 | BW5: 4 | BX5: 5 | BY5: 5 | BZ5: Pass | CB5: Passed | CC5: Enrolled | CD5: Query Completed | CE5: 46037 | CF5: 46218 | CH5: Compliant | CJ5: John | CK5: Carter | CL5: OH0000078 | CM5: OH | CN5: CDL Holder | CO5: John Carter | CP5: 45364 | CQ5: 46094 | CR5: (614) 555-0107 | CS5: Dr. Patricia Owens | CT5: 45364 | CU5: OH-ME-970443 | CV5: ME100001 | CW5: Chiropractor | CX5: OH | CY5: Federal Motor Carrier Safety Regulations | DA5: No | DB5: No | DC5: No | DD5: No | DE5: No | DF5: No | DG5: Sarah Carter | DH5: Spouse | DI5: 206-555-0199 | DJ5: No | DK5: No | DL5: No | DM5: No | DN5: Yes - Appendectomy (2005) | DO5: 20/20 | DP5: 20/20 | DQ5: Pass | DR5: 118 | DS5: 78 | DT5: 72 | DU5: Normal | DV5: 45392 | DW5: 45394 | DX5: Negative | DY5: 45397 | DZ5: BOF Fleet Safety & Compliance Policy 2024 | EA5: Complete | EB5: 45413
A6: DRV-001 | B6: John Carter | C6: 220 Demo Street, Cleveland, OH 44113 | D6: 206-555-0102 | E6: ***-**-0123 | F6: Huntington | G6: 104 | H6: 999900202 | I6: Road Test Certificate | J6: VALID | K6: OH0000137 | L6: 46621 | M6: 46276 | N6: 46314 | P6: Black | Q6: Green | R6: 5'-10" | S6: 180 | T6: M | U6: 25934 | V6: DRV-001.png | W6: Caucasian | X6: jcarter@example.com | Y6: 220 Demo Street | Z6: Cleveland | AA6: OH | AB6: 44113 | AC6: OH | AD6: Class A | AE6: 44799 | AF6: N,T | AH6: 45364 | AI6: MC-0010108 | AJ6: Dr. Patricia Owens | AK6: ME100001 | AM6: Qualified | AN6: 46050 | AO6: 0 | AP6: 0 | AR6: Clear | AS6: 45392 | AT6: Authorized to Work | AU6: U.S. Passport | AX6: 45392 | AY6: BOF Onboarding Team | AZ6: Complete | BB6: Individual/Sole Proprietor | BC6: SSN | BD6: ***-**-0123 | BF6: 45392 | BG6: Received | BH6: Checking | BI6: Direct Deposit | BJ6: 45392 | BK6: Verified | BL6: 45385 | BM6: A. Reynolds | BN6: Sleeper tractor | BO6: 53 ft dry van | BP6: Cleveland, OH | BQ6: 5 | BR6: 5 | BS6: 4 | BT6: 5 | BU6: 5 | BV6: 5 | BW6: 4 | BX6: 5 | BY6: 5 | BZ6: Pass | CB6: Passed | CC6: Enrolled | CD6: Query Completed | CE6: 46037 | CF6: 46218 | CH6: Compliant | CJ6: John | CK6: Carter | CL6: OH0000079 | CM6: OH | CN6: CDL Holder | CO6: John Carter | CP6: 45364 | CQ6: 46094 | CR6: (614) 555-0107 | CS6: Dr. Patricia Owens | CT6: 45364 | CU6: OH-ME-970443 | CV6: ME100001 | CW6: Chiropractor | CX6: OH | CY6: Federal Motor Carrier Safety Regulations | DA6: No | DB6: No | DC6: No | DD6: No | DE6: No | DF6: No | DG6: Sarah Carter | DH6: Spouse | DI6: 206-555-0199 | DJ6: No | DK6: No | DL6: No | DM6: No | DN6: Yes - Appendectomy (2005) | DO6: 20/20 | DP6: 20/20 | DQ6: Pass | DR6: 118 | DS6: 78 | DT6: 72 | DU6: Normal | DV6: 45392 | DW6: 45394 | DX6: Negative | DY6: 45397 | DZ6: BOF Fleet Safety & Compliance Policy 2024 | EA6: Complete | EB6: 45413
A7: DRV-001 | B7: John Carter | C7: 220 Demo Street, Cleveland, OH 44113 | D7: 206-555-0102 | E7: ***-**-0123 | F7: Huntington | G7: 104 | H7: 999900202 | I7: Incident/Accident Report | J7: VALID | K7: OH0000138 | L7: 46621 | M7: 46277 | N7: 46315 | O7: Load L-501: Seal mismatch detected. Pickup: SEAL-83921 Delivery: SEAL-83920. | P7: Black | Q7: Green | R7: 5'-10" | S7: 180 | T7: M | U7: 25934 | V7: DRV-001.png | W7: Caucasian | X7: jcarter@example.com | Y7: 220 Demo Street | Z7: Cleveland | AA7: OH | AB7: 44113 | AC7: OH | AD7: Class A | AE7: 44799 | AF7: N,T | AH7: 45364 | AI7: MC-0010108 | AJ7: Dr. Patricia Owens | AK7: ME100001 | AM7: Qualified | AN7: 46050 | AO7: 0 | AP7: 0 | AR7: Clear | AS7: 45392 | AT7: Authorized to Work | AU7: U.S. Passport | AX7: 45392 | AY7: BOF Onboarding Team | AZ7: Complete | BB7: Individual/Sole Proprietor | BC7: SSN | BD7: ***-**-0123 | BF7: 45392 | BG7: Received | BH7: Checking | BI7: Direct Deposit | BJ7: 45392 | BK7: Verified | BL7: 45385 | BM7: A. Reynolds | BN7: Sleeper tractor | BO7: 53 ft dry van | BP7: Cleveland, OH | BQ7: 5 | BR7: 5 | BS7: 4 | BT7: 5 | BU7: 5 | BV7: 5 | BW7: 4 | BX7: 5 | BY7: 5 | BZ7: Pass | CB7: Passed | CC7: Enrolled | CD7: Query Completed | CE7: 46037 | CF7: 46218 | CH7: Compliant | CJ7: John | CK7: Carter | CL7: OH0000080 | CM7: OH | CN7: CDL Holder | CO7: John Carter | CP7: 45364 | CQ7: 46094 | CR7: (614) 555-0107 | CS7: Dr. Patricia Owens | CT7: 45364 | CU7: OH-ME-970443 | CV7: ME100001 | CW7: Chiropractor | CX7: OH | CY7: Federal Motor Carrier Safety Regulations | DA7: No | DB7: No | DC7: No | DD7: No | DE7: No | DF7: No | DG7: Sarah Carter | DH7: Spouse | DI7: 206-555-0199 | DJ7: No | DK7: No | DL7: No | DM7: No | DN7: Yes - Appendectomy (2005) | DO7: 20/20 | DP7: 20/20 | DQ7: Pass | DR7: 118 | DS7: 78 | DT7: 72 | DU7: Normal | DV7: 45392 | DW7: 45394 | DX7: Negative | DY7: 45397 | DZ7: BOF Fleet Safety & Compliance Policy 2024 | EA7: Complete | EB7: 45413
A8: DRV-001 | B8: John Carter | C8: 220 Demo Street, Cleveland, OH 44113 | D8: 206-555-0102 | E8: ***-**-0123 | F8: Huntington | G8: 104 | H8: 999900202 | I8: Direct Deposit Form | J8: VALID | K8: OH0000124 | L8: 46621 | M8: 46278 | N8: 46316 | P8: Black | Q8: Green | R8: 5'-10" | S8: 180 | T8: M | U8: 25934 | V8: DRV-001.png | W8: Caucasian | X8: jcarter@example.com | Y8: 220 Demo Street | Z8: Cleveland | AA8: OH | AB8: 44113 | AC8: OH | AD8: Class A | AE8: 44799 | AF8: N,T | AH8: 45364 | AI8: MC-0010108 | AJ8: Dr. Patricia Owens | AK8: ME100001 | AM8: Qualified | AN8: 46050 | AO8: 0 | AP8: 0 | AR8: Clear | AS8: 45392 | AT8: Authorized to Work | AU8: U.S. Passport | AX8: 45392 | AY8: BOF Onboarding Team | AZ8: Complete | BB8: Individual/Sole Proprietor | BC8: SSN | BD8: ***-**-0123 | BF8: 45392 | BG8: Received | BH8: Checking | BI8: Direct Deposit | BJ8: 45392 | BK8: Verified | BL8: 45385 | BM8: A. Reynolds | BN8: Sleeper tractor | BO8: 53 ft dry van | BP8: Cleveland, OH | BQ8: 5 | BR8: 5 | BS8: 4 | BT8: 5 | BU8: 5 | BV8: 5 | BW8: 4 | BX8: 5 | BY8: 5 | BZ8: Pass | CB8: Passed | CC8: Enrolled | CD8: Query Completed | CE8: 46037 | CF8: 46218 | CH8: Compliant | CJ8: John | CK8: Carter | CL8: OH0000081 | CM8: OH | CN8: CDL Holder | CO8: John Carter | CP8: 45364 | CQ8: 46094 | CR8: (614) 555-0107 | CS8: Dr. Patricia Owens | CT8: 45364 | CU8: OH-ME-970443 | CV8: ME100001 | CW8: Chiropractor | CX8: OH | CY8: Federal Motor Carrier Safety Regulations | DA8: No | DB8: No | DC8: No | DD8: No | DE8: No | DF8: No | DG8: Sarah Carter | DH8: Spouse | DI8: 206-555-0199 | DJ8: No | DK8: No | DL8: No | DM8: No | DN8: Yes - Appendectomy (2005) | DO8: 20/20 | DP8: 20/20 | DQ8: Pass | DR8: 118 | DS8: 78 | DT8: 72 | DU8: Normal | DV8: 45392 | DW8: 45394 | DX8: Negative | DY8: 45397 | DZ8: BOF Fleet Safety & Compliance Policy 2024 | EA8: Complete | EB8: 45413
A9: DRV-002 | B9: Maria Lopez | C9: 770 Demo Street, Chicago, IL 60611 | D9: 707-555-0100 | E9: ***-**-0105 | F9: Chase | G9: 107 | H9: 999900201 | I9: CDL Summary | J9: VALID | K9: IL0000041 | L9: 46518 | M9: 46596 | N9: 46455 | P9: Brown | Q9: Hazel | R9: 5'-3" | S9: 134 | T9: F | U9: 30317 | V9: DRV-002.png | W9: Hispanic | X9: marialopez@example.com | Y9: 770 Demo Street | Z9: Chicago | AA9: IL | AB9: 60611 | AC9: IL | AD9: Class A | AE9: 44696 | AF9: N | AG9: Corrective lenses | AH9: 45866 | AI9: MC-0020104 | AJ9: Dr. Kevin Marshall | AK9: ME100002 | AL9: Corrective lenses | AM9: Qualified | AN9: 46425 | AO9: 1 | AP9: 0 | AQ9: Corrective lenses | AR9: Clear | AS9: 45446 | AT9: Authorized to Work | AU9: U.S. Passport | AX9: 45446 | AY9: BOF Onboarding Team | AZ9: Complete | BB9: Individual/Sole Proprietor | BC9: SSN | BD9: ***-**-0105 | BF9: 45446 | BG9: Received | BH9: Checking | BI9: Direct Deposit | BJ9: 45446 | BK9: Verified | BL9: 45439 | BM9: D. Foster | BN9: Day cab tractor | BO9: 53 ft reefer | BP9: Chicago, IL | BQ9: 4 | BR9: 5 | BS9: 4 | BT9: 4 | BU9: 5 | BV9: 5 | BW9: 4 | BX9: 5 | BY9: 4 | BZ9: Pass | CA9: Corrective lenses | CB9: Passed | CC9: Enrolled | CD9: Query Completed | CE9: 46037 | CF9: 46218 | CH9: Compliant | CJ9: Maria | CK9: Lopez | CL9: IL0000041 | CM9: IL | CN9: CDL Holder | CO9: Maria Lopez | CP9: 45866 | CQ9: 46596 | CR9: (312) 555-0101 | CS9: Dr. Kevin Marshall | CT9: 45866 | CU9: IL-ME-425674 | CV9: ME100002 | CW9: MD | CX9: IL | CY9: Federal Motor Carrier Safety Regulations | DA9: Yes | DB9: No | DC9: No | DD9: No | DE9: Yes | DF9: No | DG9: Jane Doe | DH9: Sister | DI9: 555-555-5555 | DJ9: No | DK9: No | DL9: No | DM9: No | DN9: Yes - Appendectomy (2005) | DO9: 20/20 | DP9: 20/20 | DQ9: Pass | DR9: 118 | DS9: 78 | DT9: 72 | DU9: Normal | DV9: 45392 | DW9: 45394 | DX9: Negative | DY9: 45397 | DZ9: BOF Fleet Safety & Compliance Policy 2024 | EA9: Complete | EB9: 45413
A10: DRV-002 | B10: Maria Lopez | C10: 770 Demo Street, Chicago, IL 60611 | D10: 707-555-0100 | E10: ***-**-0105 | F10: Chase | G10: 107 | H10: 999900201 | I10: Medical Certification | J10: VALID | K10: IL0000068 | L10: 46518 | M10: 46596 | N10: 46455 | P10: Brown | Q10: Hazel | R10: 5'-3" | S10: 134 | T10: F | U10: 30317 | V10: DRV-002.png | W10: Hispanic | X10: marialopez@example.com | Y10: 770 Demo Street | Z10: Chicago | AA10: IL | AB10: 60611 | AC10: IL | AD10: Class A | AE10: 44696 | AF10: N | AG10: Corrective lenses | AH10: 45866 | AI10: MC-0020104 | AJ10: Dr. Kevin Marshall | AK10: ME100002 | AL10: Corrective lenses | AM10: Qualified | AN10: 46425 | AO10: 1 | AP10: 0 | AQ10: Corrective lenses | AR10: Clear | AS10: 45446 | AT10: Authorized to Work | AU10: U.S. Passport | AX10: 45446 | AY10: BOF Onboarding Team | AZ10: Complete | BB10: Individual/Sole Proprietor | BC10: SSN | BD10: ***-**-0105 | BF10: 45446 | BG10: Received | BH10: Checking | BI10: Direct Deposit | BJ10: 45446 | BK10: Verified | BL10: 45439 | BM10: D. Foster | BN10: Day cab tractor | BO10: 53 ft reefer | BP10: Chicago, IL | BQ10: 4 | BR10: 5 | BS10: 4 | BT10: 4 | BU10: 5 | BV10: 5 | BW10: 4 | BX10: 5 | BY10: 4 | BZ10: Pass | CA10: Corrective lenses | CB10: Passed | CC10: Enrolled | CD10: Query Completed | CE10: 46037 | CF10: 46218 | CH10: Compliant | CJ10: Maria | CK10: Lopez | CL10: IL0000042 | CM10: IL | CN10: CDL Holder | CO10: Maria Lopez | CP10: 45866 | CQ10: 46596 | CR10: (312) 555-0101 | CS10: Dr. Kevin Marshall | CT10: 45866 | CU10: IL-ME-425674 | CV10: ME100002 | CW10: MD | CX10: IL | CY10: Federal Motor Carrier Safety Regulations | DA10: Yes | DB10: No | DC10: No | DD10: No | DE10: Yes | DF10: No | DG10: Jane Doe | DH10: Sister | DI10: 555-555-5555 | DJ10: No | DK10: No | DL10: No | DM10: No | DN10: Yes - Appendectomy (2005) | DO10: 20/20 | DP10: 20/20 | DQ10: Pass | DR10: 118 | DS10: 78 | DT10: 72 | DU10: Normal | DV10: 45392 | DW10: 45394 | DX10: Negative | DY10: 45397 | DZ10: BOF Fleet Safety & Compliance Policy 2024 | EA10: Complete | EB10: 45413
A11: DRV-002 | B11: Maria Lopez | C11: 770 Demo Street, Chicago, IL 60611 | D11: 707-555-0100 | E11: ***-**-0105 | F11: Chase | G11: 107 | H11: 999900201 | I11: MVR Background Report | J11: VALID | K11: IL0000056 | L11: 46518 | M11: 46596 | N11: 46455 | P11: Brown | Q11: Hazel | R11: 5'-3" | S11: 134 | T11: F | U11: 30317 | V11: DRV-002.png | W11: Hispanic | X11: marialopez@example.com | Y11: 770 Demo Street | Z11: Chicago | AA11: IL | AB11: 60611 | AC11: IL | AD11: Class A | AE11: 44696 | AF11: N | AG11: Corrective lenses | AH11: 45866 | AI11: MC-0020104 | AJ11: Dr. Kevin Marshall | AK11: ME100002 | AL11: Corrective lenses | AM11: Qualified | AN11: 46425 | AO11: 1 | AP11: 0 | AQ11: Corrective lenses | AR11: Clear | AS11: 45446 | AT11: Authorized to Work | AU11: U.S. Passport | AX11: 45446 | AY11: BOF Onboarding Team | AZ11: Complete | BB11: Individual/Sole Proprietor | BC11: SSN | BD11: ***-**-0105 | BF11: 45446 | BG11: Received | BH11: Checking | BI11: Direct Deposit | BJ11: 45446 | BK11: Verified | BL11: 45439 | BM11: D. Foster | BN11: Day cab tractor | BO11: 53 ft reefer | BP11: Chicago, IL | BQ11: 4 | BR11: 5 | BS11: 4 | BT11: 4 | BU11: 5 | BV11: 5 | BW11: 4 | BX11: 5 | BY11: 4 | BZ11: Pass | CA11: Corrective lenses | CB11: Passed | CC11: Enrolled | CD11: Query Completed | CE11: 46037 | CF11: 46218 | CH11: Compliant | CJ11: Maria | CK11: Lopez | CL11: IL0000043 | CM11: IL | CN11: CDL Holder | CO11: Maria Lopez | CP11: 45866 | CQ11: 46596 | CR11: (312) 555-0101 | CS11: Dr. Kevin Marshall | CT11: 45866 | CU11: IL-ME-425674 | CV11: ME100002 | CW11: MD | CX11: IL | CY11: Federal Motor Carrier Safety Regulations | DA11: Yes | DB11: No | DC11: No | DD11: No | DE11: Yes | DF11: No | DG11: Jane Doe | DH11: Sister | DI11: 555-555-5555 | DJ11: No | DK11: No | DL11: No | DM11: No | DN11: Yes - Appendectomy (2005) | DO11: 20/20 | DP11: 20/20 | DQ11: Pass | DR11: 118 | DS11: 78 | DT11: 72 | DU11: Normal | DV11: 45392 | DW11: 45394 | DX11: Negative | DY11: 45397 | DZ11: BOF Fleet Safety & Compliance Policy 2024 | EA11: Complete | EB11: 45413
A12: DRV-002 | B12: Maria Lopez | C12: 770 Demo Street, Chicago, IL 60611 | D12: 707-555-0100 | E12: ***-**-0105 | F12: Chase | G12: 107 | H12: 999900201 | I12: Driver Application | J12: VALID | K12: IL0000065 | L12: 46518 | M12: 46596 | N12: 46455 | P12: Brown | Q12: Hazel | R12: 5'-3" | S12: 134 | T12: F | U12: 30317 | V12: DRV-002.png | W12: Hispanic | X12: marialopez@example.com | Y12: 770 Demo Street | Z12: Chicago | AA12: IL | AB12: 60611 | AC12: IL | AD12: Class A | AE12: 44696 | AF12: N | AG12: Corrective lenses | AH12: 45866 | AI12: MC-0020104 | AJ12: Dr. Kevin Marshall | AK12: ME100002 | AL12: Corrective lenses | AM12: Qualified | AN12: 46425 | AO12: 1 | AP12: 0 | AQ12: Corrective lenses | AR12: Clear | AS12: 45446 | AT12: Authorized to Work | AU12: U.S. Passport | AX12: 45446 | AY12: BOF Onboarding Team | AZ12: Complete | BB12: Individual/Sole Proprietor | BC12: SSN | BD12: ***-**-0105 | BF12: 45446 | BG12: Received | BH12: Checking | BI12: Direct Deposit | BJ12: 45446 | BK12: Verified | BL12: 45439 | BM12: D. Foster | BN12: Day cab tractor | BO12: 53 ft reefer | BP12: Chicago, IL | BQ12: 4 | BR12: 5 | BS12: 4 | BT12: 4 | BU12: 5 | BV12: 5 | BW12: 4 | BX12: 5 | BY12: 4 | BZ12: Pass | CA12: Corrective lenses | CB12: Passed | CC12: Enrolled | CD12: Query Completed | CE12: 46037 | CF12: 46218 | CH12: Compliant | CJ12: Maria | CK12: Lopez | CL12: IL0000044 | CM12: IL | CN12: CDL Holder | CO12: Maria Lopez | CP12: 45866 | CQ12: 46596 | CR12: (312) 555-0101 | CS12: Dr. Kevin Marshall | CT12: 45866 | CU12: IL-ME-425674 | CV12: ME100002 | CW12: MD | CX12: IL | CY12: Federal Motor Carrier Safety Regulations | DA12: Yes | DB12: No | DC12: No | DD12: No | DE12: Yes | DF12: No | DG12: Jane Doe | DH12: Sister | DI12: 555-555-5555 | DJ12: No | DK12: No | DL12: No | DM12: No | DN12: Yes - Appendectomy (2005) | DO12: 20/20 | DP12: 20/20 | DQ12: Pass | DR12: 118 | DS12: 78 | DT12: 72 | DU12: Normal | DV12: 45392 | DW12: 45394 | DX12: Negative | DY12: 45397 | DZ12: BOF Fleet Safety & Compliance Policy 2024 | EA12: Complete | EB12: 45413
A13: DRV-002 | B13: Maria Lopez | C13: 770 Demo Street, Chicago, IL 60611 | D13: 707-555-0100 | E13: ***-**-0105 | F13: Chase | G13: 107 | H13: 999900201 | I13: Road Test Certificate | J13: VALID | K13: IL0000067 | L13: 46518 | M13: 46596 | N13: 46455 | P13: Brown | Q13: Hazel | R13: 5'-3" | S13: 134 | T13: F | U13: 30317 | V13: DRV-002.png | W13: Hispanic | X13: marialopez@example.com | Y13: 770 Demo Street | Z13: Chicago | AA13: IL | AB13: 60611 | AC13: IL | AD13: Class A | AE13: 44696 | AF13: N | AG13: Corrective lenses | AH13: 45866 | AI13: MC-0020104 | AJ13: Dr. Kevin Marshall | AK13: ME100002 | AL13: Corrective lenses | AM13: Qualified | AN13: 46425 | AO13: 1 | AP13: 0 | AQ13: Corrective lenses | AR13: Clear | AS13: 45446 | AT13: Authorized to Work | AU13: U.S. Passport | AX13: 45446 | AY13: BOF Onboarding Team | AZ13: Complete | BB13: Individual/Sole Proprietor | BC13: SSN | BD13: ***-**-0105 | BF13: 45446 | BG13: Received | BH13: Checking | BI13: Direct Deposit | BJ13: 45446 | BK13: Verified | BL13: 45439 | BM13: D. Foster | BN13: Day cab tractor | BO13: 53 ft reefer | BP13: Chicago, IL | BQ13: 4 | BR13: 5 | BS13: 4 | BT13: 4 | BU13: 5 | BV13: 5 | BW13: 4 | BX13: 5 | BY13: 4 | BZ13: Pass | CA13: Corrective lenses | CB13: Passed | CC13: Enrolled | CD13: Query Completed | CE13: 46037 | CF13: 46218 | CH13: Compliant | CJ13: Maria | CK13: Lopez | CL13: IL0000045 | CM13: IL | CN13: CDL Holder | CO13: Maria Lopez | CP13: 45866 | CQ13: 46596 | CR13: (312) 555-0101 | CS13: Dr. Kevin Marshall | CT13: 45866 | CU13: IL-ME-425674 | CV13: ME100002 | CW13: MD | CX13: IL | CY13: Federal Motor Carrier Safety Regulations | DA13: Yes | DB13: No | DC13: No | DD13: No | DE13: Yes | DF13: No | DG13: Jane Doe | DH13: Sister | DI13: 555-555-5555 | DJ13: No | DK13: No | DL13: No | DM13: No | DN13: Yes - Appendectomy (2005) | DO13: 20/20 | DP13: 20/20 | DQ13: Pass | DR13: 118 | DS13: 78 | DT13: 72 | DU13: Normal | DV13: 45392 | DW13: 45394 | DX13: Negative | DY13: 45397 | DZ13: BOF Fleet Safety & Compliance Policy 2024 | EA13: Complete | EB13: 45413
A14: DRV-002 | B14: Maria Lopez | C14: 770 Demo Street, Chicago, IL 60611 | D14: 707-555-0100 | E14: ***-**-0105 | F14: Chase | G14: 107 | H14: 999900201 | I14: Incident/Accident Report | J14: VALID | K14: IL0000058 | L14: 46518 | M14: 46596 | N14: 46455 | O14: No major incidents recorded in last 90 days. | P14: Brown | Q14: Hazel | R14: 5'-3" | S14: 134 | T14: F | U14: 30317 | V14: DRV-002.png | W14: Hispanic | X14: marialopez@example.com | Y14: 770 Demo Street | Z14: Chicago | AA14: IL | AB14: 60611 | AC14: IL | AD14: Class A | AE14: 44696 | AF14: N | AG14: Corrective lenses | AH14: 45866 | AI14: MC-0020104 | AJ14: Dr. Kevin Marshall | AK14: ME100002 | AL14: Corrective lenses | AM14: Qualified | AN14: 46425 | AO14: 1 | AP14: 0 | AQ14: Corrective lenses | AR14: Clear | AS14: 45446 | AT14: Authorized to Work | AU14: U.S. Passport | AX14: 45446 | AY14: BOF Onboarding Team | AZ14: Complete | BB14: Individual/Sole Proprietor | BC14: SSN | BD14: ***-**-0105 | BF14: 45446 | BG14: Received | BH14: Checking | BI14: Direct Deposit | BJ14: 45446 | BK14: Verified | BL14: 45439 | BM14: D. Foster | BN14: Day cab tractor | BO14: 53 ft reefer | BP14: Chicago, IL | BQ14: 4 | BR14: 5 | BS14: 4 | BT14: 4 | BU14: 5 | BV14: 5 | BW14: 4 | BX14: 5 | BY14: 4 | BZ14: Pass | CA14: Corrective lenses | CB14: Passed | CC14: Enrolled | CD14: Query Completed | CE14: 46037 | CF14: 46218 | CH14: Compliant | CJ14: Maria | CK14: Lopez | CL14: IL0000046 | CM14: IL | CN14: CDL Holder | CO14: Maria Lopez | CP14: 45866 | CQ14: 46596 | CR14: (312) 555-0101 | CS14: Dr. Kevin Marshall | CT14: 45866 | CU14: IL-ME-425674 | CV14: ME100002 | CW14: MD | CX14: IL | CY14: Federal Motor Carrier Safety Regulations | DA14: Yes | DB14: No | DC14: No | DD14: No | DE14: Yes | DF14: No | DG14: Jane Doe | DH14: Sister | DI14: 555-555-5555 | DJ14: No | DK14: No | DL14: No | DM14: No | DN14: Yes - Appendectomy (2005) | DO14: 20/20 | DP14: 20/20 | DQ14: Pass | DR14: 118 | DS14: 78 | DT14: 72 | DU14: Normal | DV14: 45392 | DW14: 45394 | DX14: Negative | DY14: 45397 | DZ14: BOF Fleet Safety & Compliance Policy 2024 | EA14: Complete | EB14: 45413
A15: DRV-002 | B15: Maria Lopez | C15: 770 Demo Street, Chicago, IL 60611 | D15: 707-555-0100 | E15: ***-**-0105 | F15: Chase | G15: 107 | H15: 999900201 | I15: Direct Deposit Form | J15: VALID | K15: IL0000061 | L15: 46518 | M15: 46596 | N15: 46455 | P15: Brown | Q15: Hazel | R15: 5'-3" | S15: 134 | T15: F | U15: 30317 | V15: DRV-002.png | W15: Hispanic | X15: marialopez@example.com | Y15: 770 Demo Street | Z15: Chicago | AA15: IL | AB15: 60611 | AC15: IL | AD15: Class A | AE15: 44696 | AF15: N | AG15: Corrective lenses | AH15: 45866 | AI15: MC-0020104 | AJ15: Dr. Kevin Marshall | AK15: ME100002 | AL15: Corrective lenses | AM15: Qualified | AN15: 46425 | AO15: 1 | AP15: 0 | AQ15: Corrective lenses | AR15: Clear | AS15: 45446 | AT15: Authorized to Work | AU15: U.S. Passport | AX15: 45446 | AY15: BOF Onboarding Team | AZ15: Complete | BB15: Individual/Sole Proprietor | BC15: SSN | BD15: ***-**-0105 | BF15: 45446 | BG15: Received | BH15: Checking | BI15: Direct Deposit | BJ15: 45446 | BK15: Verified | BL15: 45439 | BM15: D. Foster | BN15: Day cab tractor | BO15: 53 ft reefer | BP15: Chicago, IL | BQ15: 4 | BR15: 5 | BS15: 4 | BT15: 4 | BU15: 5 | BV15: 5 | BW15: 4 | BX15: 5 | BY15: 4 | BZ15: Pass | CA15: Corrective lenses | CB15: Passed | CC15: Enrolled | CD15: Query Completed | CE15: 46037 | CF15: 46218 | CH15: Compliant | CJ15: Maria | CK15: Lopez | CL15: IL0000047 | CM15: IL | CN15: CDL Holder | CO15: Maria Lopez | CP15: 45866 | CQ15: 46596 | CR15: (312) 555-0101 | CS15: Dr. Kevin Marshall | CT15: 45866 | CU15: IL-ME-425674 | CV15: ME100002 | CW15: MD | CX15: IL | CY15: Federal Motor Carrier Safety Regulations | DA15: Yes | DB15: No | DC15: No | DD15: No | DE15: Yes | DF15: No | DG15: Jane Doe | DH15: Sister | DI15: 555-555-5555 | DJ15: No | DK15: No | DL15: No | DM15: No | DN15: Yes - Appendectomy (2005) | DO15: 20/20 | DP15: 20/20 | DQ15: Pass | DR15: 118 | DS15: 78 | DT15: 72 | DU15: Normal | DV15: 45392 | DW15: 45394 | DX15: Negative | DY15: 45397 | DZ15: BOF Fleet Safety & Compliance Policy 2024 | EA15: Complete | EB15: 45413
A16: DRV-003 | B16: Alex Kim | C16: 960 Demo Street, Atlanta, GA 30308 | D16: 675-555-0100 | E16: ***-**-0116 | F16: Chase | G16: 111 | H16: 999900211 | I16: CDL Summary | J16: VALID | K16: GA0000013 | L16: 46420 | M16: 46659 | N16: 46449 | P16: Brown | Q16: Blue | R16: 6'-2" | S16: 214 | T16: M | U16: 25934 | V16: DRV-003.png | W16: Asian | X16: alexkim@example.com | Y16: 960 Demo Street | Z16: Atlanta | AA16: GA | AB16: 30308 | AC16: GA | AD16: Class A | AE16: 44598 | AF16: H,N | AH16: 45929 | AI16: MC-0030104 | AJ16: Dr. Lisa Bennett | AK16: ME100003 | AM16: Qualified | AN16: 46419 | AO16: 0 | AP16: 0 | AR16: Clear | AS16: 45488 | AT16: Authorized to Work | AU16: U.S. Passport | AX16: 45488 | AY16: BOF Onboarding Team | AZ16: Complete | BB16: Individual/Sole Proprietor | BC16: SSN | BD16: ***-**-0116 | BF16: 45488 | BG16: Received | BH16: Checking | BI16: Direct Deposit | BJ16: 45488 | BK16: Verified | BL16: 45481 | BM16: M. Chen | BN16: Sleeper tractor | BO16: Tanker | BP16: Atlanta, GA | BQ16: 5 | BR16: 5 | BS16: 5 | BT16: 5 | BU16: 4 | BV16: 5 | BW16: 5 | BX16: 5 | BY16: 5 | BZ16: Pass | CA16: HazMat loads only after refresher every 12 months | CB16: Passed | CC16: Enrolled | CD16: Query Completed | CE16: 46037 | CF16: 46218 | CH16: Compliant | CJ16: Alex | CK16: Kim | CL16: GA0000013 | CM16: GA | CN16: CDL Holder | CO16: Alex Kim | CP16: 45929 | CQ16: 46659 | CR16: (404) 555-0107 | CS16: Dr. Lisa Bennett | CT16: 45929 | CU16: GA-ME-142937 | CV16: ME100003 | CW16: Advanced Practice Nurse | CX16: GA | CY16: Federal Motor Carrier Safety Regulations | DA16: No | DB16: No | DC16: No | DD16: No | DE16: No | DF16: No | DG16: Jane Doe | DH16: Sister | DI16: 555-555-5555 | DJ16: No | DK16: No | DL16: No | DM16: No | DN16: Yes - Appendectomy (2005) | DO16: 20/20 | DP16: 20/20 | DQ16: Pass | DR16: 118 | DS16: 78 | DT16: 72 | DU16: Normal | DV16: 45392 | DW16: 45394 | DX16: Negative | DY16: 45397 | DZ16: BOF Fleet Safety & Compliance Policy 2024 | EA16: Complete | EB16: 45413
A17: DRV-003 | B17: Alex Kim | C17: 960 Demo Street, Atlanta, GA 30308 | D17: 675-555-0100 | E17: ***-**-0116 | F17: Chase | G17: 111 | H17: 999900211 | I17: Medical Certification | J17: VALID | K17: GA0000006 | L17: 46420 | M17: 46659 | N17: 46449 | P17: Brown | Q17: Blue | R17: 6'-2" | S17: 214 | T17: M | U17: 25934 | V17: DRV-003.png | W17: Asian | X17: alexkim@example.com | Y17: 960 Demo Street | Z17: Atlanta | AA17: GA | AB17: 30308 | AC17: GA | AD17: Class A | AE17: 44598 | AF17: H,N | AH17: 45929 | AI17: MC-0030104 | AJ17: Dr. Lisa Bennett | AK17: ME100003 | AM17: Qualified | AN17: 46419 | AO17: 0 | AP17: 0 | AR17: Clear | AS17: 45488 | AT17: Authorized to Work | AU17: U.S. Passport | AX17: 45488 | AY17: BOF Onboarding Team | AZ17: Complete | BB17: Individual/Sole Proprietor | BC17: SSN | BD17: ***-**-0116 | BF17: 45488 | BG17: Received | BH17: Checking | BI17: Direct Deposit | BJ17: 45488 | BK17: Verified | BL17: 45481 | BM17: M. Chen | BN17: Sleeper tractor | BO17: Tanker | BP17: Atlanta, GA | BQ17: 5 | BR17: 5 | BS17: 5 | BT17: 5 | BU17: 4 | BV17: 5 | BW17: 5 | BX17: 5 | BY17: 5 | BZ17: Pass | CA17: HazMat loads only after refresher every 12 months | CB17: Passed | CC17: Enrolled | CD17: Query Completed | CE17: 46037 | CF17: 46218 | CH17: Compliant | CJ17: Alex | CK17: Kim | CL17: GA0000014 | CM17: GA | CN17: CDL Holder | CO17: Alex Kim | CP17: 45929 | CQ17: 46659 | CR17: (404) 555-0107 | CS17: Dr. Lisa Bennett | CT17: 45929 | CU17: GA-ME-142937 | CV17: ME100003 | CW17: Advanced Practice Nurse | CX17: GA | CY17: Federal Motor Carrier Safety Regulations | DA17: No | DB17: No | DC17: No | DD17: No | DE17: No | DF17: No | DG17: Jane Doe | DH17: Sister | DI17: 555-555-5555 | DJ17: No | DK17: No | DL17: No | DM17: No | DN17: Yes - Appendectomy (2005) | DO17: 20/20 | DP17: 20/20 | DQ17: Pass | DR17: 118 | DS17: 78 | DT17: 72 | DU17: Normal | DV17: 45392 | DW17: 45394 | DX17: Negative | DY17: 45397 | DZ17: BOF Fleet Safety & Compliance Policy 2024 | EA17: Complete | EB17: 45413
A18: DRV-003 | B18: Alex Kim | C18: 960 Demo Street, Atlanta, GA 30308 | D18: 675-555-0100 | E18: ***-**-0116 | F18: Chase | G18: 111 | H18: 999900211 | I18: MVR Background Report | J18: VALID | K18: GA0000011 | L18: 46420 | M18: 46659 | N18: 46449 | P18: Brown | Q18: Blue | R18: 6'-2" | S18: 214 | T18: M | U18: 25934 | V18: DRV-003.png | W18: Asian | X18: alexkim@example.com | Y18: 960 Demo Street | Z18: Atlanta | AA18: GA | AB18: 30308 | AC18: GA | AD18: Class A | AE18: 44598 | AF18: H,N | AH18: 45929 | AI18: MC-0030104 | AJ18: Dr. Lisa Bennett | AK18: ME100003 | AM18: Qualified | AN18: 46419 | AO18: 0 | AP18: 0 | AR18: Clear | AS18: 45488 | AT18: Authorized to Work | AU18: U.S. Passport | AX18: 45488 | AY18: BOF Onboarding Team | AZ18: Complete | BB18: Individual/Sole Proprietor | BC18: SSN | BD18: ***-**-0116 | BF18: 45488 | BG18: Received | BH18: Checking | BI18: Direct Deposit | BJ18: 45488 | BK18: Verified | BL18: 45481 | BM18: M. Chen | BN18: Sleeper tractor | BO18: Tanker | BP18: Atlanta, GA | BQ18: 5 | BR18: 5 | BS18: 5 | BT18: 5 | BU18: 4 | BV18: 5 | BW18: 5 | BX18: 5 | BY18: 5 | BZ18: Pass | CA18: HazMat loads only after refresher every 12 months | CB18: Passed | CC18: Enrolled | CD18: Query Completed | CE18: 46037 | CF18: 46218 | CH18: Compliant | CJ18: Alex | CK18: Kim | CL18: GA0000015 | CM18: GA | CN18: CDL Holder | CO18: Alex Kim | CP18: 45929 | CQ18: 46659 | CR18: (404) 555-0107 | CS18: Dr. Lisa Bennett | CT18: 45929 | CU18: GA-ME-142937 | CV18: ME100003 | CW18: Advanced Practice Nurse | CX18: GA | CY18: Federal Motor Carrier Safety Regulations | DA18: No | DB18: No | DC18: No | DD18: No | DE18: No | DF18: No | DG18: Jane Doe | DH18: Sister | DI18: 555-555-5555 | DJ18: No | DK18: No | DL18: No | DM18: No | DN18: Yes - Appendectomy (2005) | DO18: 20/20 | DP18: 20/20 | DQ18: Pass | DR18: 118 | DS18: 78 | DT18: 72 | DU18: Normal | DV18: 45392 | DW18: 45394 | DX18: Negative | DY18: 45397 | DZ18: BOF Fleet Safety & Compliance Policy 2024 | EA18: Complete | EB18: 45413
A19: DRV-003 | B19: Alex Kim | C19: 960 Demo Street, Atlanta, GA 30308 | D19: 675-555-0100 | E19: ***-**-0116 | F19: Chase | G19: 111 | H19: 999900211 | I19: Driver Application | J19: VALID | K19: GA0000005 | L19: 46420 | M19: 46659 | N19: 46449 | P19: Brown | Q19: Blue | R19: 6'-2" | S19: 214 | T19: M | U19: 25934 | V19: DRV-003.png | W19: Asian | X19: alexkim@example.com | Y19: 960 Demo Street | Z19: Atlanta | AA19: GA | AB19: 30308 | AC19: GA | AD19: Class A | AE19: 44598 | AF19: H,N | AH19: 45929 | AI19: MC-0030104 | AJ19: Dr. Lisa Bennett | AK19: ME100003 | AM19: Qualified | AN19: 46419 | AO19: 0 | AP19: 0 | AR19: Clear | AS19: 45488 | AT19: Authorized to Work | AU19: U.S. Passport | AX19: 45488 | AY19: BOF Onboarding Team | AZ19: Complete | BB19: Individual/Sole Proprietor | BC19: SSN | BD19: ***-**-0116 | BF19: 45488 | BG19: Received | BH19: Checking | BI19: Direct Deposit | BJ19: 45488 | BK19: Verified | BL19: 45481 | BM19: M. Chen | BN19: Sleeper tractor | BO19: Tanker | BP19: Atlanta, GA | BQ19: 5 | BR19: 5 | BS19: 5 | BT19: 5 | BU19: 4 | BV19: 5 | BW19: 5 | BX19: 5 | BY19: 5 | BZ19: Pass | CA19: HazMat loads only after refresher every 12 months | CB19: Passed | CC19: Enrolled | CD19: Query Completed | CE19: 46037 | CF19: 46218 | CH19: Compliant | CJ19: Alex | CK19: Kim | CL19: GA0000016 | CM19: GA | CN19: CDL Holder | CO19: Alex Kim | CP19: 45929 | CQ19: 46659 | CR19: (404) 555-0107 | CS19: Dr. Lisa Bennett | CT19: 45929 | CU19: GA-ME-142937 | CV19: ME100003 | CW19: Advanced Practice Nurse | CX19: GA | CY19: Federal Motor Carrier Safety Regulations | DA19: No | DB19: No | DC19: No | DD19: No | DE19: No | DF19: No | DG19: Jane Doe | DH19: Sister | DI19: 555-555-5555 | DJ19: No | DK19: No | DL19: No | DM19: No | DN19: Yes - Appendectomy (2005) | DO19: 20/20 | DP19: 20/20 | DQ19: Pass | DR19: 118 | DS19: 78 | DT19: 72 | DU19: Normal | DV19: 45392 | DW19: 45394 | DX19: Negative | DY19: 45397 | DZ19: BOF Fleet Safety & Compliance Policy 2024 | EA19: Complete | EB19: 45413
A20: DRV-003 | B20: Alex Kim | C20: 960 Demo Street, Atlanta, GA 30308 | D20: 675-555-0100 | E20: ***-**-0116 | F20: Chase | G20: 111 | H20: 999900211 | I20: Road Test Certificate | J20: VALID | K20: GA0000004 | L20: 46420 | M20: 46659 | N20: 46449 | P20: Brown | Q20: Blue | R20: 6'-2" | S20: 214 | T20: M | U20: 25934 | V20: DRV-003.png | W20: Asian | X20: alexkim@example.com | Y20: 960 Demo Street | Z20: Atlanta | AA20: GA | AB20: 30308 | AC20: GA | AD20: Class A | AE20: 44598 | AF20: H,N | AH20: 45929 | AI20: MC-0030104 | AJ20: Dr. Lisa Bennett | AK20: ME100003 | AM20: Qualified | AN20: 46419 | AO20: 0 | AP20: 0 | AR20: Clear | AS20: 45488 | AT20: Authorized to Work | AU20: U.S. Passport | AX20: 45488 | AY20: BOF Onboarding Team | AZ20: Complete | BB20: Individual/Sole Proprietor | BC20: SSN | BD20: ***-**-0116 | BF20: 45488 | BG20: Received | BH20: Checking | BI20: Direct Deposit | BJ20: 45488 | BK20: Verified | BL20: 45481 | BM20: M. Chen | BN20: Sleeper tractor | BO20: Tanker | BP20: Atlanta, GA | BQ20: 5 | BR20: 5 | BS20: 5 | BT20: 5 | BU20: 4 | BV20: 5 | BW20: 5 | BX20: 5 | BY20: 5 | BZ20: Pass | CA20: HazMat loads only after refresher every 12 months | CB20: Passed | CC20: Enrolled | CD20: Query Completed | CE20: 46037 | CF20: 46218 | CH20: Compliant | CJ20: Alex | CK20: Kim | CL20: GA0000017 | CM20: GA | CN20: CDL Holder | CO20: Alex Kim | CP20: 45929 | CQ20: 46659 | CR20: (404) 555-0107 | CS20: Dr. Lisa Bennett | CT20: 45929 | CU20: GA-ME-142937 | CV20: ME100003 | CW20: Advanced Practice Nurse | CX20: GA | CY20: Federal Motor Carrier Safety Regulations | DA20: No | DB20: No | DC20: No | DD20: No | DE20: No | DF20: No | DG20: Jane Doe | DH20: Sister | DI20: 555-555-5555 | DJ20: No | DK20: No | DL20: No | DM20: No | DN20: Yes - Appendectomy (2005) | DO20: 20/20 | DP20: 20/20 | DQ20: Pass | DR20: 118 | DS20: 78 | DT20: 72 | DU20: Normal | DV20: 45392 | DW20: 45394 | DX20: Negative | DY20: 45397 | DZ20: BOF Fleet Safety & Compliance Policy 2024 | EA20: Complete | EB20: 45413
A21: DRV-003 | B21: Alex Kim | C21: 960 Demo Street, Atlanta, GA 30308 | D21: 675-555-0100 | E21: ***-**-0116 | F21: Chase | G21: 111 | H21: 999900211 | I21: Incident/Accident Report | J21: VALID | K21: GA0000027 | L21: 46420 | M21: 46659 | N21: 46449 | O21: No major incidents recorded in last 90 days. | P21: Brown | Q21: Blue | R21: 6'-2" | S21: 214 | T21: M | U21: 25934 | V21: DRV-003.png | W21: Asian | X21: alexkim@example.com | Y21: 960 Demo Street | Z21: Atlanta | AA21: GA | AB21: 30308 | AC21: GA | AD21: Class A | AE21: 44598 | AF21: H,N | AH21: 45929 | AI21: MC-0030104 | AJ21: Dr. Lisa Bennett | AK21: ME100003 | AM21: Qualified | AN21: 46419 | AO21: 0 | AP21: 0 | AR21: Clear | AS21: 45488 | AT21: Authorized to Work | AU21: U.S. Passport | AX21: 45488 | AY21: BOF Onboarding Team | AZ21: Complete | BB21: Individual/Sole Proprietor | BC21: SSN | BD21: ***-**-0116 | BF21: 45488 | BG21: Received | BH21: Checking | BI21: Direct Deposit | BJ21: 45488 | BK21: Verified | BL21: 45481 | BM21: M. Chen | BN21: Sleeper tractor | BO21: Tanker | BP21: Atlanta, GA | BQ21: 5 | BR21: 5 | BS21: 5 | BT21: 5 | BU21: 4 | BV21: 5 | BW21: 5 | BX21: 5 | BY21: 5 | BZ21: Pass | CA21: HazMat loads only after refresher every 12 months | CB21: Passed | CC21: Enrolled | CD21: Query Completed | CE21: 46037 | CF21: 46218 | CH21: Compliant | CJ21: Alex | CK21: Kim | CL21: GA0000018 | CM21: GA | CN21: CDL Holder | CO21: Alex Kim | CP21: 45929 | CQ21: 46659 | CR21: (404) 555-0107 | CS21: Dr. Lisa Bennett | CT21: 45929 | CU21: GA-ME-142937 | CV21: ME100003 | CW21: Advanced Practice Nurse | CX21: GA | CY21: Federal Motor Carrier Safety Regulations | DA21: No | DB21: No | DC21: No | DD21: No | DE21: No | DF21: No | DG21: Jane Doe | DH21: Sister | DI21: 555-555-5555 | DJ21: No | DK21: No | DL21: No | DM21: No | DN21: Yes - Appendectomy (2005) | DO21: 20/20 | DP21: 20/20 | DQ21: Pass | DR21: 118 | DS21: 78 | DT21: 72 | DU21: Normal | DV21: 45392 | DW21: 45394 | DX21: Negative | DY21: 45397 | DZ21: BOF Fleet Safety & Compliance Policy 2024 | EA21: Complete | EB21: 45413
A22: DRV-003 | B22: Alex Kim | C22: 960 Demo Street, Atlanta, GA 30308 | D22: 675-555-0100 | E22: ***-**-0116 | F22: Chase | G22: 111 | H22: 999900211 | I22: Direct Deposit Form | J22: VALID | K22: GA0000002 | L22: 46420 | M22: 46659 | N22: 46449 | P22: Brown | Q22: Blue | R22: 6'-2" | S22: 214 | T22: M | U22: 25934 | V22: DRV-003.png | W22: Asian | X22: alexkim@example.com | Y22: 960 Demo Street | Z22: Atlanta | AA22: GA | AB22: 30308 | AC22: GA | AD22: Class A | AE22: 44598 | AF22: H,N | AH22: 45929 | AI22: MC-0030104 | AJ22: Dr. Lisa Bennett | AK22: ME100003 | AM22: Qualified | AN22: 46419 | AO22: 0 | AP22: 0 | AR22: Clear | AS22: 45488 | AT22: Authorized to Work | AU22: U.S. Passport | AX22: 45488 | AY22: BOF Onboarding Team | AZ22: Complete | BB22: Individual/Sole Proprietor | BC22: SSN | BD22: ***-**-0116 | BF22: 45488 | BG22: Received | BH22: Checking | BI22: Direct Deposit | BJ22: 45488 | BK22: Verified | BL22: 45481 | BM22: M. Chen | BN22: Sleeper tractor | BO22: Tanker | BP22: Atlanta, GA | BQ22: 5 | BR22: 5 | BS22: 5 | BT22: 5 | BU22: 4 | BV22: 5 | BW22: 5 | BX22: 5 | BY22: 5 | BZ22: Pass | CA22: HazMat loads only after refresher every 12 months | CB22: Passed | CC22: Enrolled | CD22: Query Completed | CE22: 46037 | CF22: 46218 | CH22: Compliant | CJ22: Alex | CK22: Kim | CL22: GA0000019 | CM22: GA | CN22: CDL Holder | CO22: Alex Kim | CP22: 45929 | CQ22: 46659 | CR22: (404) 555-0107 | CS22: Dr. Lisa Bennett | CT22: 45929 | CU22: GA-ME-142937 | CV22: ME100003 | CW22: Advanced Practice Nurse | CX22: GA | CY22: Federal Motor Carrier Safety Regulations | DA22: No | DB22: No | DC22: No | DD22: No | DE22: No | DF22: No | DG22: Jane Doe | DH22: Sister | DI22: 555-555-5555 | DJ22: No | DK22: No | DL22: No | DM22: No | DN22: Yes - Appendectomy (2005) | DO22: 20/20 | DP22: 20/20 | DQ22: Pass | DR22: 118 | DS22: 78 | DT22: 72 | DU22: Normal | DV22: 45392 | DW22: 45394 | DX22: Negative | DY22: 45397 | DZ22: BOF Fleet Safety & Compliance Policy 2024 | EA22: Complete | EB22: 45413
A23: DRV-004 | B23: Priya Patel | C23: 520 Demo Street, Cleveland, OH 44114 | D23: 359-555-0100 | E23: ***-**-0119 | F23: Chase | G23: 101 | H23: 999900203 | I23: CDL Summary | J23: VALID | K23: OH0000130 | L23: 46739 | M23: 46486 | N23: 46452 | P23: Brown | Q23: Blue | R23: 5'-7" | S23: 148 | T23: F | U23: 33970 | V23: DRV-004.png | W23: South Asian | X23: priyapatel@example.com | Y23: 520 Demo Street | Z23: Cleveland | AA23: OH | AB23: 44114 | AC23: OH | AD23: Class A | AE23: 44917 | AF23: N,T | AG23: Automatic transmission only | AH23: 45756 | AI23: MC-0040812 | AJ23: Dr. Ramon Ortiz | AK23: ME100004 | AM23: Qualified | AN23: 46422 | AO23: 0 | AP23: 0 | AQ23: Automatic transmission only | AR23: Clear | AS23: 45432 | AT23: Authorized to Work | AU23: U.S. Passport | AX23: 45432 | AY23: BOF Onboarding Team | AZ23: Complete | BB23: Individual/Sole Proprietor | BC23: SSN | BD23: ***-**-0119 | BF23: 45432 | BG23: Received | BH23: Savings | BI23: Direct Deposit | BJ23: 45432 | BK23: Verified | BL23: 45425 | BM23: S. Howard | BN23: Day cab tractor | BO23: 53 ft dry van | BP23: Cleveland, OH | BQ23: 4 | BR23: 4 | BS23: 4 | BT23: 5 | BU23: 4 | BV23: 4 | BW23: 4 | BX23: 5 | BY23: 4 | BZ23: Pass | CA23: Automatic transmission assigned | CB23: Passed | CC23: Enrolled | CD23: Query Completed | CE23: 46037 | CF23: 46218 | CH23: Compliant | CJ23: Priya | CK23: Patel | CL23: OH0000130 | CM23: OH | CN23: CDL Holder | CO23: Priya Patel | CP23: 45756 | CQ23: 46486 | CR23: (614) 555-0111 | CS23: Dr. Ramon Ortiz | CT23: 45756 | CU23: OH-ME-293591 | CV23: ME100004 | CW23: MD | CX23: OH | CY23: Federal Motor Carrier Safety Regulations | DA23: No | DB23: No | DC23: No | DD23: No | DE23: No | DF23: No | DG23: Jane Doe | DH23: Sister | DI23: 555-555-5555 | DJ23: No | DK23: No | DL23: No | DM23: No | DN23: Yes - Appendectomy (2005) | DO23: 20/20 | DP23: 20/20 | DQ23: Pass | DR23: 118 | DS23: 78 | DT23: 72 | DU23: Normal | DV23: 45392 | DW23: 45394 | DX23: Negative | DY23: 45397 | DZ23: BOF Fleet Safety & Compliance Policy 2024 | EA23: Complete | EB23: 45413
A24: DRV-004 | B24: Priya Patel | C24: 520 Demo Street, Cleveland, OH 44114 | D24: 359-555-0100 | E24: ***-**-0119 | F24: Chase | G24: 101 | H24: 999900203 | I24: Medical Certification | J24: VALID | K24: OH0000099 | L24: 46739 | M24: 46486 | N24: 46452 | P24: Brown | Q24: Blue | R24: 5'-7" | S24: 148 | T24: F | U24: 33970 | V24: DRV-004.png | W24: South Asian | X24: priyapatel@example.com | Y24: 520 Demo Street | Z24: Cleveland | AA24: OH | AB24: 44114 | AC24: OH | AD24: Class A | AE24: 44917 | AF24: N,T | AG24: Automatic transmission only | AH24: 45756 | AI24: MC-0040812 | AJ24: Dr. Ramon Ortiz | AK24: ME100004 | AM24: Qualified | AN24: 46422 | AO24: 0 | AP24: 0 | AQ24: Automatic transmission only | AR24: Clear | AS24: 45432 | AT24: Authorized to Work | AU24: U.S. Passport | AX24: 45432 | AY24: BOF Onboarding Team | AZ24: Complete | BB24: Individual/Sole Proprietor | BC24: SSN | BD24: ***-**-0119 | BF24: 45432 | BG24: Received | BH24: Savings | BI24: Direct Deposit | BJ24: 45432 | BK24: Verified | BL24: 45425 | BM24: S. Howard | BN24: Day cab tractor | BO24: 53 ft dry van | BP24: Cleveland, OH | BQ24: 4 | BR24: 4 | BS24: 4 | BT24: 5 | BU24: 4 | BV24: 4 | BW24: 4 | BX24: 5 | BY24: 4 | BZ24: Pass | CA24: Automatic transmission assigned | CB24: Passed | CC24: Enrolled | CD24: Query Completed | CE24: 46037 | CF24: 46218 | CH24: Compliant | CJ24: Priya | CK24: Patel | CL24: OH0000131 | CM24: OH | CN24: CDL Holder | CO24: Priya Patel | CP24: 45756 | CQ24: 46486 | CR24: (614) 555-0111 | CS24: Dr. Ramon Ortiz | CT24: 45756 | CU24: OH-ME-293591 | CV24: ME100004 | CW24: MD | CX24: OH | CY24: Federal Motor Carrier Safety Regulations | DA24: No | DB24: No | DC24: No | DD24: No | DE24: No | DF24: No | DG24: Jane Doe | DH24: Sister | DI24: 555-555-5555 | DJ24: No | DK24: No | DL24: No | DM24: No | DN24: Yes - Appendectomy (2005) | DO24: 20/20 | DP24: 20/20 | DQ24: Pass | DR24: 118 | DS24: 78 | DT24: 72 | DU24: Normal | DV24: 45392 | DW24: 45394 | DX24: Negative | DY24: 45397 | DZ24: BOF Fleet Safety & Compliance Policy 2024 | EA24: Complete | EB24: 45413
A25: DRV-004 | B25: Priya Patel | C25: 520 Demo Street, Cleveland, OH 44114 | D25: 359-555-0100 | E25: ***-**-0119 | F25: Chase | G25: 101 | H25: 999900203 | I25: MVR Background Report | J25: VALID | K25: OH0000123 | L25: 46739 | M25: 46486 | N25: 46452 | P25: Brown | Q25: Blue | R25: 5'-7" | S25: 148 | T25: F | U25: 33970 | V25: DRV-004.png | W25: South Asian | X25: priyapatel@example.com | Y25: 520 Demo Street | Z25: Cleveland | AA25: OH | AB25: 44114 | AC25: OH | AD25: Class A | AE25: 44917 | AF25: N,T | AG25: Automatic transmission only | AH25: 45756 | AI25: MC-0040812 | AJ25: Dr. Ramon Ortiz | AK25: ME100004 | AM25: Qualified | AN25: 46422 | AO25: 0 | AP25: 0 | AQ25: Automatic transmission only | AR25: Clear | AS25: 45432 | AT25: Authorized to Work | AU25: U.S. Passport | AX25: 45432 | AY25: BOF Onboarding Team | AZ25: Complete | BB25: Individual/Sole Proprietor | BC25: SSN | BD25: ***-**-0119 | BF25: 45432 | BG25: Received | BH25: Savings | BI25: Direct Deposit | BJ25: 45432 | BK25: Verified | BL25: 45425 | BM25: S. Howard | BN25: Day cab tractor | BO25: 53 ft dry van | BP25: Cleveland, OH | BQ25: 4 | BR25: 4 | BS25: 4 | BT25: 5 | BU25: 4 | BV25: 4 | BW25: 4 | BX25: 5 | BY25: 4 | BZ25: Pass | CA25: Automatic transmission assigned | CB25: Passed | CC25: Enrolled | CD25: Query Completed | CE25: 46037 | CF25: 46218 | CH25: Compliant | CJ25: Priya | CK25: Patel | CL25: OH0000132 | CM25: OH | CN25: CDL Holder | CO25: Priya Patel | CP25: 45756 | CQ25: 46486 | CR25: (614) 555-0111 | CS25: Dr. Ramon Ortiz | CT25: 45756 | CU25: OH-ME-293591 | CV25: ME100004 | CW25: MD | CX25: OH | CY25: Federal Motor Carrier Safety Regulations | DA25: No | DB25: No | DC25: No | DD25: No | DE25: No | DF25: No | DG25: Jane Doe | DH25: Sister | DI25: 555-555-5555 | DJ25: No | DK25: No | DL25: No | DM25: No | DN25: Yes - Appendectomy (2005) | DO25: 20/20 | DP25: 20/20 | DQ25: Pass | DR25: 118 | DS25: 78 | DT25: 72 | DU25: Normal | DV25: 45392 | DW25: 45394 | DX25: Negative | DY25: 45397 | DZ25: BOF Fleet Safety & Compliance Policy 2024 | EA25: Complete | EB25: 45413
A26: DRV-004 | B26: Priya Patel | C26: 520 Demo Street, Cleveland, OH 44114 | D26: 359-555-0100 | E26: ***-**-0119 | F26: Chase | G26: 101 | H26: 999900203 | I26: summary | J26: VALID | K26: OH0000149 | L26: 46739 | M26: 46486 | N26: 46452 | P26: Brown | Q26: Blue | R26: 5'-7" | S26: 148 | T26: F | U26: 33970 | V26: DRV-004.png | W26: South Asian | X26: priyapatel@example.com | Y26: 520 Demo Street | Z26: Cleveland | AA26: OH | AB26: 44114 | AC26: OH | AD26: Class A | AE26: 44917 | AF26: N,T | AG26: Automatic transmission only | AH26: 45756 | AI26: MC-0040812 | AJ26: Dr. Ramon Ortiz | AK26: ME100004 | AM26: Qualified | AN26: 46422 | AO26: 0 | AP26: 0 | AQ26: Automatic transmission only | AR26: Clear | AS26: 45432 | AT26: Authorized to Work | AU26: U.S. Passport | AX26: 45432 | AY26: BOF Onboarding Team | AZ26: Complete | BB26: Individual/Sole Proprietor | BC26: SSN | BD26: ***-**-0119 | BF26: 45432 | BG26: Received | BH26: Savings | BI26: Direct Deposit | BJ26: 45432 | BK26: Verified | BL26: 45425 | BM26: S. Howard | BN26: Day cab tractor | BO26: 53 ft dry van | BP26: Cleveland, OH | BQ26: 4 | BR26: 4 | BS26: 4 | BT26: 5 | BU26: 4 | BV26: 4 | BW26: 4 | BX26: 5 | BY26: 4 | BZ26: Pass | CA26: Automatic transmission assigned | CB26: Passed | CC26: Enrolled | CD26: Query Completed | CE26: 46037 | CF26: 46218 | CH26: Compliant | CJ26: Priya | CK26: Patel | CL26: OH0000133 | CM26: OH | CN26: CDL Holder | CO26: Priya Patel | CP26: 45756 | CQ26: 46486 | CR26: (614) 555-0111 | CS26: Dr. Ramon Ortiz | CT26: 45756 | CU26: OH-ME-293591 | CV26: ME100004 | CW26: MD | CX26: OH | CY26: Federal Motor Carrier Safety Regulations | DA26: No | DB26: No | DC26: No | DD26: No | DE26: No | DF26: No | DG26: Jane Doe | DH26: Sister | DI26: 555-555-5555 | DJ26: No | DK26: No | DL26: No | DM26: No | DN26: Yes - Appendectomy (2005) | DO26: 20/20 | DP26: 20/20 | DQ26: Pass | DR26: 118 | DS26: 78 | DT26: 72 | DU26: Normal | DV26: 45392 | DW26: 45394 | DX26: Negative | DY26: 45397 | DZ26: BOF Fleet Safety & Compliance Policy 2024 | EA26: Complete | EB26: 45413
A27: DRV-004 | B27: Priya Patel | C27: 520 Demo Street, Cleveland, OH 44114 | D27: 359-555-0100 | E27: ***-**-0119 | F27: Chase | G27: 101 | H27: 999900203 | I27: Road Test Certificate | J27: VALID | K27: OH0000072 | L27: 46739 | M27: 46486 | N27: 46452 | P27: Brown | Q27: Blue | R27: 5'-7" | S27: 148 | T27: F | U27: 33970 | V27: DRV-004.png | W27: South Asian | X27: priyapatel@example.com | Y27: 520 Demo Street | Z27: Cleveland | AA27: OH | AB27: 44114 | AC27: OH | AD27: Class A | AE27: 44917 | AF27: N,T | AG27: Automatic transmission only | AH27: 45756 | AI27: MC-0040812 | AJ27: Dr. Ramon Ortiz | AK27: ME100004 | AM27: Qualified | AN27: 46422 | AO27: 0 | AP27: 0 | AQ27: Automatic transmission only | AR27: Clear | AS27: 45432 | AT27: Authorized to Work | AU27: U.S. Passport | AX27: 45432 | AY27: BOF Onboarding Team | AZ27: Complete | BB27: Individual/Sole Proprietor | BC27: SSN | BD27: ***-**-0119 | BF27: 45432 | BG27: Received | BH27: Savings | BI27: Direct Deposit | BJ27: 45432 | BK27: Verified | BL27: 45425 | BM27: S. Howard | BN27: Day cab tractor | BO27: 53 ft dry van | BP27: Cleveland, OH | BQ27: 4 | BR27: 4 | BS27: 4 | BT27: 5 | BU27: 4 | BV27: 4 | BW27: 4 | BX27: 5 | BY27: 4 | BZ27: Pass | CA27: Automatic transmission assigned | CB27: Passed | CC27: Enrolled | CD27: Query Completed | CE27: 46037 | CF27: 46218 | CH27: Compliant | CJ27: Priya | CK27: Patel | CL27: OH0000134 | CM27: OH | CN27: CDL Holder | CO27: Priya Patel | CP27: 45756 | CQ27: 46486 | CR27: (614) 555-0111 | CS27: Dr. Ramon Ortiz | CT27: 45756 | CU27: OH-ME-293591 | CV27: ME100004 | CW27: MD | CX27: OH | CY27: Federal Motor Carrier Safety Regulations | DA27: No | DB27: No | DC27: No | DD27: No | DE27: No | DF27: No | DG27: Jane Doe | DH27: Sister | DI27: 555-555-5555 | DJ27: No | DK27: No | DL27: No | DM27: No | DN27: Yes - Appendectomy (2005) | DO27: 20/20 | DP27: 20/20 | DQ27: Pass | DR27: 118 | DS27: 78 | DT27: 72 | DU27: Normal | DV27: 45392 | DW27: 45394 | DX27: Negative | DY27: 45397 | DZ27: BOF Fleet Safety & Compliance Policy 2024 | EA27: Complete | EB27: 45413
A28: DRV-004 | B28: Priya Patel | C28: 520 Demo Street, Cleveland, OH 44114 | D28: 359-555-0100 | E28: ***-**-0119 | F28: Chase | G28: 101 | H28: 999900203 | I28: Incident/Accident Report | J28: VALID | K28: OH0000074 | L28: 46739 | M28: 46486 | N28: 46452 | O28: Load L-504: Seal mismatch detected. Pickup: SEAL-61044 Delivery: SEAL-61043. | P28: Brown | Q28: Blue | R28: 5'-7" | S28: 148 | T28: F | U28: 33970 | V28: DRV-004.png | W28: South Asian | X28: priyapatel@example.com | Y28: 520 Demo Street | Z28: Cleveland | AA28: OH | AB28: 44114 | AC28: OH | AD28: Class A | AE28: 44917 | AF28: N,T | AG28: Automatic transmission only | AH28: 45756 | AI28: MC-0040812 | AJ28: Dr. Ramon Ortiz | AK28: ME100004 | AM28: Qualified | AN28: 46422 | AO28: 0 | AP28: 0 | AQ28: Automatic transmission only | AR28: Clear | AS28: 45432 | AT28: Authorized to Work | AU28: U.S. Passport | AX28: 45432 | AY28: BOF Onboarding Team | AZ28: Complete | BB28: Individual/Sole Proprietor | BC28: SSN | BD28: ***-**-0119 | BF28: 45432 | BG28: Received | BH28: Savings | BI28: Direct Deposit | BJ28: 45432 | BK28: Verified | BL28: 45425 | BM28: S. Howard | BN28: Day cab tractor | BO28: 53 ft dry van | BP28: Cleveland, OH | BQ28: 4 | BR28: 4 | BS28: 4 | BT28: 5 | BU28: 4 | BV28: 4 | BW28: 4 | BX28: 5 | BY28: 4 | BZ28: Pass | CA28: Automatic transmission assigned | CB28: Passed | CC28: Enrolled | CD28: Query Completed | CE28: 46037 | CF28: 46218 | CH28: Compliant | CJ28: Priya | CK28: Patel | CL28: OH0000135 | CM28: OH | CN28: CDL Holder | CO28: Priya Patel | CP28: 45756 | CQ28: 46486 | CR28: (614) 555-0111 | CS28: Dr. Ramon Ortiz | CT28: 45756 | CU28: OH-ME-293591 | CV28: ME100004 | CW28: MD | CX28: OH | CY28: Federal Motor Carrier Safety Regulations | DA28: No | DB28: No | DC28: No | DD28: No | DE28: No | DF28: No | DG28: Jane Doe | DH28: Sister | DI28: 555-555-5555 | DJ28: No | DK28: No | DL28: No | DM28: No | DN28: Yes - Appendectomy (2005) | DO28: 20/20 | DP28: 20/20 | DQ28: Pass | DR28: 118 | DS28: 78 | DT28: 72 | DU28: Normal | DV28: 45392 | DW28: 45394 | DX28: Negative | DY28: 45397 | DZ28: BOF Fleet Safety & Compliance Policy 2024 | EA28: Complete | EB28: 45413
A29: DRV-004 | B29: Priya Patel | C29: 520 Demo Street, Cleveland, OH 44114 | D29: 359-555-0100 | E29: ***-**-0119 | F29: Chase | G29: 101 | H29: 999900203 | I29: Direct Deposit Form | J29: VALID | K29: OH0000095 | L29: 46739 | M29: 46486 | N29: 46452 | P29: Brown | Q29: Blue | R29: 5'-7" | S29: 148 | T29: F | U29: 33970 | V29: DRV-004.png | W29: South Asian | X29: priyapatel@example.com | Y29: 520 Demo Street | Z29: Cleveland | AA29: OH | AB29: 44114 | AC29: OH | AD29: Class A | AE29: 44917 | AF29: N,T | AG29: Automatic transmission only | AH29: 45756 | AI29: MC-0040812 | AJ29: Dr. Ramon Ortiz | AK29: ME100004 | AM29: Qualified | AN29: 46422 | AO29: 0 | AP29: 0 | AQ29: Automatic transmission only | AR29: Clear | AS29: 45432 | AT29: Authorized to Work | AU29: U.S. Passport | AX29: 45432 | AY29: BOF Onboarding Team | AZ29: Complete | BB29: Individual/Sole Proprietor | BC29: SSN | BD29: ***-**-0119 | BF29: 45432 | BG29: Received | BH29: Savings | BI29: Direct Deposit | BJ29: 45432 | BK29: Verified | BL29: 45425 | BM29: S. Howard | BN29: Day cab tractor | BO29: 53 ft dry van | BP29: Cleveland, OH | BQ29: 4 | BR29: 4 | BS29: 4 | BT29: 5 | BU29: 4 | BV29: 4 | BW29: 4 | BX29: 5 | BY29: 4 | BZ29: Pass | CA29: Automatic transmission assigned | CB29: Passed | CC29: Enrolled | CD29: Query Completed | CE29: 46037 | CF29: 46218 | CH29: Compliant | CJ29: Priya | CK29: Patel | CL29: OH0000136 | CM29: OH | CN29: CDL Holder | CO29: Priya Patel | CP29: 45756 | CQ29: 46486 | CR29: (614) 555-0111 | CS29: Dr. Ramon Ortiz | CT29: 45756 | CU29: OH-ME-293591 | CV29: ME100004 | CW29: MD | CX29: OH | CY29: Federal Motor Carrier Safety Regulations | DA29: No | DB29: No | DC29: No | DD29: No | DE29: No | DF29: No | DG29: Jane Doe | DH29: Sister | DI29: 555-555-5555 | DJ29: No | DK29: No | DL29: No | DM29: No | DN29: Yes - Appendectomy (2005) | DO29: 20/20 | DP29: 20/20 | DQ29: Pass | DR29: 118 | DS29: 78 | DT29: 72 | DU29: Normal | DV29: 45392 | DW29: 45394 | DX29: Negative | DY29: 45397 | DZ29: BOF Fleet Safety & Compliance Policy 2024 | EA29: Complete | EB29: 45413
A30: DRV-005 | B30: Kenji Tanaka | C30: 150 Demo Street, Columbus, OH 43215 | D30: 871-555-0100 | E30: ***-**-0102 | F30: Chase | G30: 105 | H30: 999900206 | I30: CDL Summary | J30: VALID | K30: OH0000084 | L30: 46577 | M30: 46496 | N30: 46478 | P30: Black | Q30: Green | R30: 5'-10" | S30: 193 | T30: M | U30: 24108 | V30: DRV-005.png | W30: Asian | X30: ktanaka@example.com | Y30: 150 Demo Street | Z30: Columbus | AA30: OH | AB30: 43215 | AC30: OH | AD30: Class A | AE30: 44755 | AF30: T | AG30: Corrective lenses | AH30: 45766 | AI30: MC-0051018 | AJ30: Dr. Helen Price | AK30: ME100005 | AL30: Corrective lenses | AM30: Qualified | AN30: 46448 | AO30: 1 | AP30: 0 | AQ30: Corrective lenses | AR30: Clear | AS30: 45509 | AT30: Authorized to Work | AU30: U.S. Passport | AX30: 45509 | AY30: BOF Onboarding Team | AZ30: Complete | BB30: Individual/Sole Proprietor | BC30: SSN | BD30: ***-**-0102 | BF30: 45509 | BG30: Received | BH30: Checking | BI30: Direct Deposit | BJ30: 45509 | BK30: Verified | BL30: 45502 | BM30: T. Warren | BN30: Day cab tractor | BO30: 53 ft dry van | BP30: Columbus, OH | BQ30: 5 | BR30: 4 | BS30: 4 | BT30: 4 | BU30: 4 | BV30: 5 | BW30: 4 | BX30: 4 | BY30: 4 | BZ30: Pass | CA30: Corrective lenses | CB30: Passed | CC30: Enrolled | CD30: Query Completed | CE30: 46037 | CF30: 46218 | CH30: Compliant | CJ30: Kenji | CK30: Tanaka | CL30: OH0000084 | CM30: OH | CN30: CDL Holder | CO30: Kenji Tanaka | CP30: 45766 | CQ30: 46496 | CR30: (614) 555-0106 | CS30: Dr. Helen Price | CT30: 45766 | CU30: OH-ME-401933 | CV30: ME100005 | CW30: Advanced Practice Nurse | CX30: OH | CY30: Federal Motor Carrier Safety Regulations | DA30: Yes | DB30: No | DC30: No | DD30: No | DE30: Yes | DF30: No | DG30: Jane Doe | DH30: Sister | DI30: 555-555-5555 | DJ30: No | DK30: No | DL30: No | DM30: No | DN30: Yes - Appendectomy (2005) | DO30: 20/20 | DP30: 20/20 | DQ30: Pass | DR30: 118 | DS30: 78 | DT30: 72 | DU30: Normal | DV30: 45392 | DW30: 45394 | DX30: Negative | DY30: 45397 | DZ30: BOF Fleet Safety & Compliance Policy 2024 | EA30: Complete | EB30: 45413
A31: DRV-005 | B31: Kenji Tanaka | C31: 150 Demo Street, Columbus, OH 43215 | D31: 871-555-0100 | E31: ***-**-0102 | F31: Chase | G31: 105 | H31: 999900206 | I31: Medical Certification | J31: VALID | K31: OH0000093 | L31: 46577 | M31: 46496 | N31: 46478 | P31: Black | Q31: Green | R31: 5'-10" | S31: 193 | T31: M | U31: 24108 | V31: DRV-005.png | W31: Asian | X31: ktanaka@example.com | Y31: 150 Demo Street | Z31: Columbus | AA31: OH | AB31: 43215 | AC31: OH | AD31: Class A | AE31: 44755 | AF31: T | AG31: Corrective lenses | AH31: 45766 | AI31: MC-0051018 | AJ31: Dr. Helen Price | AK31: ME100005 | AL31: Corrective lenses | AM31: Qualified | AN31: 46448 | AO31: 1 | AP31: 0 | AQ31: Corrective lenses | AR31: Clear | AS31: 45509 | AT31: Authorized to Work | AU31: U.S. Passport | AX31: 45509 | AY31: BOF Onboarding Team | AZ31: Complete | BB31: Individual/Sole Proprietor | BC31: SSN | BD31: ***-**-0102 | BF31: 45509 | BG31: Received | BH31: Checking | BI31: Direct Deposit | BJ31: 45509 | BK31: Verified | BL31: 45502 | BM31: T. Warren | BN31: Day cab tractor | BO31: 53 ft dry van | BP31: Columbus, OH | BQ31: 5 | BR31: 4 | BS31: 4 | BT31: 4 | BU31: 4 | BV31: 5 | BW31: 4 | BX31: 4 | BY31: 4 | BZ31: Pass | CA31: Corrective lenses | CB31: Passed | CC31: Enrolled | CD31: Query Completed | CE31: 46037 | CF31: 46218 | CH31: Compliant | CJ31: Kenji | CK31: Tanaka | CL31: OH0000085 | CM31: OH | CN31: CDL Holder | CO31: Kenji Tanaka | CP31: 45766 | CQ31: 46496 | CR31: (614) 555-0106 | CS31: Dr. Helen Price | CT31: 45766 | CU31: OH-ME-401933 | CV31: ME100005 | CW31: Advanced Practice Nurse | CX31: OH | CY31: Federal Motor Carrier Safety Regulations | DA31: Yes | DB31: No | DC31: No | DD31: No | DE31: Yes | DF31: No | DG31: Jane Doe | DH31: Sister | DI31: 555-555-5555 | DJ31: No | DK31: No | DL31: No | DM31: No | DN31: Yes - Appendectomy (2005) | DO31: 20/20 | DP31: 20/20 | DQ31: Pass | DR31: 118 | DS31: 78 | DT31: 72 | DU31: Normal | DV31: 45392 | DW31: 45394 | DX31: Negative | DY31: 45397 | DZ31: BOF Fleet Safety & Compliance Policy 2024 | EA31: Complete | EB31: 45413
A32: DRV-005 | B32: Kenji Tanaka | C32: 150 Demo Street, Columbus, OH 43215 | D32: 871-555-0100 | E32: ***-**-0102 | F32: Chase | G32: 105 | H32: 999900206 | I32: MVR Background Report | J32: VALID | K32: OH0000119 | L32: 46577 | M32: 46496 | N32: 46478 | P32: Black | Q32: Green | R32: 5'-10" | S32: 193 | T32: M | U32: 24108 | V32: DRV-005.png | W32: Asian | X32: ktanaka@example.com | Y32: 150 Demo Street | Z32: Columbus | AA32: OH | AB32: 43215 | AC32: OH | AD32: Class A | AE32: 44755 | AF32: T | AG32: Corrective lenses | AH32: 45766 | AI32: MC-0051018 | AJ32: Dr. Helen Price | AK32: ME100005 | AL32: Corrective lenses | AM32: Qualified | AN32: 46448 | AO32: 1 | AP32: 0 | AQ32: Corrective lenses | AR32: Clear | AS32: 45509 | AT32: Authorized to Work | AU32: U.S. Passport | AX32: 45509 | AY32: BOF Onboarding Team | AZ32: Complete | BB32: Individual/Sole Proprietor | BC32: SSN | BD32: ***-**-0102 | BF32: 45509 | BG32: Received | BH32: Checking | BI32: Direct Deposit | BJ32: 45509 | BK32: Verified | BL32: 45502 | BM32: T. Warren | BN32: Day cab tractor | BO32: 53 ft dry van | BP32: Columbus, OH | BQ32: 5 | BR32: 4 | BS32: 4 | BT32: 4 | BU32: 4 | BV32: 5 | BW32: 4 | BX32: 4 | BY32: 4 | BZ32: Pass | CA32: Corrective lenses | CB32: Passed | CC32: Enrolled | CD32: Query Completed | CE32: 46037 | CF32: 46218 | CH32: Compliant | CJ32: Kenji | CK32: Tanaka | CL32: OH0000086 | CM32: OH | CN32: CDL Holder | CO32: Kenji Tanaka | CP32: 45766 | CQ32: 46496 | CR32: (614) 555-0106 | CS32: Dr. Helen Price | CT32: 45766 | CU32: OH-ME-401933 | CV32: ME100005 | CW32: Advanced Practice Nurse | CX32: OH | CY32: Federal Motor Carrier Safety Regulations | DA32: Yes | DB32: No | DC32: No | DD32: No | DE32: Yes | DF32: No | DG32: Jane Doe | DH32: Sister | DI32: 555-555-5555 | DJ32: No | DK32: No | DL32: No | DM32: No | DN32: Yes - Appendectomy (2005) | DO32: 20/20 | DP32: 20/20 | DQ32: Pass | DR32: 118 | DS32: 78 | DT32: 72 | DU32: Normal | DV32: 45392 | DW32: 45394 | DX32: Negative | DY32: 45397 | DZ32: BOF Fleet Safety & Compliance Policy 2024 | EA32: Complete | EB32: 45413
A33: DRV-005 | B33: Kenji Tanaka | C33: 150 Demo Street, Columbus, OH 43215 | D33: 871-555-0100 | E33: ***-**-0102 | F33: Chase | G33: 105 | H33: 999900206 | I33: Driver Application | J33: VALID | K33: OH0000102 | L33: 46577 | M33: 46496 | N33: 46478 | P33: Black | Q33: Green | R33: 5'-10" | S33: 193 | T33: M | U33: 24108 | V33: DRV-005.png | W33: Asian | X33: ktanaka@example.com | Y33: 150 Demo Street | Z33: Columbus | AA33: OH | AB33: 43215 | AC33: OH | AD33: Class A | AE33: 44755 | AF33: T | AG33: Corrective lenses | AH33: 45766 | AI33: MC-0051018 | AJ33: Dr. Helen Price | AK33: ME100005 | AL33: Corrective lenses | AM33: Qualified | AN33: 46448 | AO33: 1 | AP33: 0 | AQ33: Corrective lenses | AR33: Clear | AS33: 45509 | AT33: Authorized to Work | AU33: U.S. Passport | AX33: 45509 | AY33: BOF Onboarding Team | AZ33: Complete | BB33: Individual/Sole Proprietor | BC33: SSN | BD33: ***-**-0102 | BF33: 45509 | BG33: Received | BH33: Checking | BI33: Direct Deposit | BJ33: 45509 | BK33: Verified | BL33: 45502 | BM33: T. Warren | BN33: Day cab tractor | BO33: 53 ft dry van | BP33: Columbus, OH | BQ33: 5 | BR33: 4 | BS33: 4 | BT33: 4 | BU33: 4 | BV33: 5 | BW33: 4 | BX33: 4 | BY33: 4 | BZ33: Pass | CA33: Corrective lenses | CB33: Passed | CC33: Enrolled | CD33: Query Completed | CE33: 46037 | CF33: 46218 | CH33: Compliant | CJ33: Kenji | CK33: Tanaka | CL33: OH0000087 | CM33: OH | CN33: CDL Holder | CO33: Kenji Tanaka | CP33: 45766 | CQ33: 46496 | CR33: (614) 555-0106 | CS33: Dr. Helen Price | CT33: 45766 | CU33: OH-ME-401933 | CV33: ME100005 | CW33: Advanced Practice Nurse | CX33: OH | CY33: Federal Motor Carrier Safety Regulations | DA33: Yes | DB33: No | DC33: No | DD33: No | DE33: Yes | DF33: No | DG33: Jane Doe | DH33: Sister | DI33: 555-555-5555 | DJ33: No | DK33: No | DL33: No | DM33: No | DN33: Yes - Appendectomy (2005) | DO33: 20/20 | DP33: 20/20 | DQ33: Pass | DR33: 118 | DS33: 78 | DT33: 72 | DU33: Normal | DV33: 45392 | DW33: 45394 | DX33: Negative | DY33: 45397 | DZ33: BOF Fleet Safety & Compliance Policy 2024 | EA33: Complete | EB33: 45413
A34: DRV-005 | B34: Kenji Tanaka | C34: 150 Demo Street, Columbus, OH 43215 | D34: 871-555-0100 | E34: ***-**-0102 | F34: Chase | G34: 105 | H34: 999900206 | I34: Road Test Certificate | J34: VALID | K34: OH0000125 | L34: 46577 | M34: 46496 | N34: 46478 | P34: Black | Q34: Green | R34: 5'-10" | S34: 193 | T34: M | U34: 24108 | V34: DRV-005.png | W34: Asian | X34: ktanaka@example.com | Y34: 150 Demo Street | Z34: Columbus | AA34: OH | AB34: 43215 | AC34: OH | AD34: Class A | AE34: 44755 | AF34: T | AG34: Corrective lenses | AH34: 45766 | AI34: MC-0051018 | AJ34: Dr. Helen Price | AK34: ME100005 | AL34: Corrective lenses | AM34: Qualified | AN34: 46448 | AO34: 1 | AP34: 0 | AQ34: Corrective lenses | AR34: Clear | AS34: 45509 | AT34: Authorized to Work | AU34: U.S. Passport | AX34: 45509 | AY34: BOF Onboarding Team | AZ34: Complete | BB34: Individual/Sole Proprietor | BC34: SSN | BD34: ***-**-0102 | BF34: 45509 | BG34: Received | BH34: Checking | BI34: Direct Deposit | BJ34: 45509 | BK34: Verified | BL34: 45502 | BM34: T. Warren | BN34: Day cab tractor | BO34: 53 ft dry van | BP34: Columbus, OH | BQ34: 5 | BR34: 4 | BS34: 4 | BT34: 4 | BU34: 4 | BV34: 5 | BW34: 4 | BX34: 4 | BY34: 4 | BZ34: Pass | CA34: Corrective lenses | CB34: Passed | CC34: Enrolled | CD34: Query Completed | CE34: 46037 | CF34: 46218 | CH34: Compliant | CJ34: Kenji | CK34: Tanaka | CL34: OH0000088 | CM34: OH | CN34: CDL Holder | CO34: Kenji Tanaka | CP34: 45766 | CQ34: 46496 | CR34: (614) 555-0106 | CS34: Dr. Helen Price | CT34: 45766 | CU34: OH-ME-401933 | CV34: ME100005 | CW34: Advanced Practice Nurse | CX34: OH | CY34: Federal Motor Carrier Safety Regulations | DA34: Yes | DB34: No | DC34: No | DD34: No | DE34: Yes | DF34: No | DG34: Jane Doe | DH34: Sister | DI34: 555-555-5555 | DJ34: No | DK34: No | DL34: No | DM34: No | DN34: Yes - Appendectomy (2005) | DO34: 20/20 | DP34: 20/20 | DQ34: Pass | DR34: 118 | DS34: 78 | DT34: 72 | DU34: Normal | DV34: 45392 | DW34: 45394 | DX34: Negative | DY34: 45397 | DZ34: BOF Fleet Safety & Compliance Policy 2024 | EA34: Complete | EB34: 45413
A35: DRV-005 | B35: Kenji Tanaka | C35: 150 Demo Street, Columbus, OH 43215 | D35: 871-555-0100 | E35: ***-**-0102 | F35: Chase | G35: 105 | H35: 999900206 | I35: Incident/Accident Report | J35: VALID | K35: OH0000082 | L35: 46577 | M35: 46496 | N35: 46478 | O35: No major incidents recorded in last 90 days. | P35: Black | Q35: Green | R35: 5'-10" | S35: 193 | T35: M | U35: 24108 | V35: DRV-005.png | W35: Asian | X35: ktanaka@example.com | Y35: 150 Demo Street | Z35: Columbus | AA35: OH | AB35: 43215 | AC35: OH | AD35: Class A | AE35: 44755 | AF35: T | AG35: Corrective lenses | AH35: 45766 | AI35: MC-0051018 | AJ35: Dr. Helen Price | AK35: ME100005 | AL35: Corrective lenses | AM35: Qualified | AN35: 46448 | AO35: 1 | AP35: 0 | AQ35: Corrective lenses | AR35: Clear | AS35: 45509 | AT35: Authorized to Work | AU35: U.S. Passport | AX35: 45509 | AY35: BOF Onboarding Team | AZ35: Complete | BB35: Individual/Sole Proprietor | BC35: SSN | BD35: ***-**-0102 | BF35: 45509 | BG35: Received | BH35: Checking | BI35: Direct Deposit | BJ35: 45509 | BK35: Verified | BL35: 45502 | BM35: T. Warren | BN35: Day cab tractor | BO35: 53 ft dry van | BP35: Columbus, OH | BQ35: 5 | BR35: 4 | BS35: 4 | BT35: 4 | BU35: 4 | BV35: 5 | BW35: 4 | BX35: 4 | BY35: 4 | BZ35: Pass | CA35: Corrective lenses | CB35: Passed | CC35: Enrolled | CD35: Query Completed | CE35: 46037 | CF35: 46218 | CH35: Compliant | CJ35: Kenji | CK35: Tanaka | CL35: OH0000089 | CM35: OH | CN35: CDL Holder | CO35: Kenji Tanaka | CP35: 45766 | CQ35: 46496 | CR35: (614) 555-0106 | CS35: Dr. Helen Price | CT35: 45766 | CU35: OH-ME-401933 | CV35: ME100005 | CW35: Advanced Practice Nurse | CX35: OH | CY35: Federal Motor Carrier Safety Regulations | DA35: Yes | DB35: No | DC35: No | DD35: No | DE35: Yes | DF35: No | DG35: Jane Doe | DH35: Sister | DI35: 555-555-5555 | DJ35: No | DK35: No | DL35: No | DM35: No | DN35: Yes - Appendectomy (2005) | DO35: 20/20 | DP35: 20/20 | DQ35: Pass | DR35: 118 | DS35: 78 | DT35: 72 | DU35: Normal | DV35: 45392 | DW35: 45394 | DX35: Negative | DY35: 45397 | DZ35: BOF Fleet Safety & Compliance Policy 2024 | EA35: Complete | EB35: 45413
A36: DRV-005 | B36: Kenji Tanaka | C36: 150 Demo Street, Columbus, OH 43215 | D36: 871-555-0100 | E36: ***-**-0102 | F36: Chase | G36: 105 | H36: 999900206 | I36: Direct Deposit Form | J36: VALID | K36: OH0000126 | L36: 46577 | M36: 46496 | N36: 46478 | P36: Black | Q36: Green | R36: 5'-10" | S36: 193 | T36: M | U36: 24108 | V36: DRV-005.png | W36: Asian | X36: ktanaka@example.com | Y36: 150 Demo Street | Z36: Columbus | AA36: OH | AB36: 43215 | AC36: OH | AD36: Class A | AE36: 44755 | AF36: T | AG36: Corrective lenses | AH36: 45766 | AI36: MC-0051018 | AJ36: Dr. Helen Price | AK36: ME100005 | AL36: Corrective lenses | AM36: Qualified | AN36: 46448 | AO36: 1 | AP36: 0 | AQ36: Corrective lenses | AR36: Clear | AS36: 45509 | AT36: Authorized to Work | AU36: U.S. Passport | AX36: 45509 | AY36: BOF Onboarding Team | AZ36: Complete | BB36: Individual/Sole Proprietor | BC36: SSN | BD36: ***-**-0102 | BF36: 45509 | BG36: Received | BH36: Checking | BI36: Direct Deposit | BJ36: 45509 | BK36: Verified | BL36: 45502 | BM36: T. Warren | BN36: Day cab tractor | BO36: 53 ft dry van | BP36: Columbus, OH | BQ36: 5 | BR36: 4 | BS36: 4 | BT36: 4 | BU36: 4 | BV36: 5 | BW36: 4 | BX36: 4 | BY36: 4 | BZ36: Pass | CA36: Corrective lenses | CB36: Passed | CC36: Enrolled | CD36: Query Completed | CE36: 46037 | CF36: 46218 | CH36: Compliant | CJ36: Kenji | CK36: Tanaka | CL36: OH0000090 | CM36: OH | CN36: CDL Holder | CO36: Kenji Tanaka | CP36: 45766 | CQ36: 46496 | CR36: (614) 555-0106 | CS36: Dr. Helen Price | CT36: 45766 | CU36: OH-ME-401933 | CV36: ME100005 | CW36: Advanced Practice Nurse | CX36: OH | CY36: Federal Motor Carrier Safety Regulations | DA36: Yes | DB36: No | DC36: No | DD36: No | DE36: Yes | DF36: No | DG36: Jane Doe | DH36: Sister | DI36: 555-555-5555 | DJ36: No | DK36: No | DL36: No | DM36: No | DN36: Yes - Appendectomy (2005) | DO36: 20/20 | DP36: 20/20 | DQ36: Pass | DR36: 118 | DS36: 78 | DT36: 72 | DU36: Normal | DV36: 45392 | DW36: 45394 | DX36: Negative | DY36: 45397 | DZ36: BOF Fleet Safety & Compliance Policy 2024 | EA36: Complete | EB36: 45413
A37: DRV-006 | B37: Marcus Chen | C37: 810 Demo Street, Dallas, TX 75202 | D37: 283-555-0100 | E37: ***-**-0101 | F37: Chase | G37: 112 | H37: 999900207 | I37: CDL Summary | J37: VALID | K37: TX0000158 | L37: 45826 | M37: 46394 | N37: 46455 | P37: Bald | Q37: Brown | R37: 6'-1" | S37: 238 | T37: M | U37: 25569 | V37: DRV-006.png | W37: Asian | X37: mchen@example.com | Y37: 810 Demo Street | Z37: Dallas | AA37: TX | AB37: 75202 | AC37: TX | AD37: Class A | AE37: 44004 | AF37: H,N,T | AH37: 45664 | AI37: MC-0060208 | AJ37: Dr. Monica Steele | AK37: ME100006 | AM37: Qualified | AN37: 46425 | AO37: 2 | AP37: 1 | AR37: Reviewed - Clear to Drive | AS37: 45544 | AT37: Authorized to Work | AU37: U.S. Passport | AX37: 45544 | AY37: BOF Onboarding Team | AZ37: Complete | BB37: Individual/Sole Proprietor | BC37: SSN | BD37: ***-**-0101 | BF37: 45544 | BG37: Received | BH37: Checking | BI37: Direct Deposit | BJ37: 45544 | BK37: Verified | BL37: 45537 | BM37: R. Delgado | BN37: Sleeper tractor | BO37: 53 ft reefer | BP37: Dallas, TX | BQ37: 4 | BR37: 4 | BS37: 3 | BT37: 4 | BU37: 4 | BV37: 4 | BW37: 4 | BX37: 4 | BY37: 4 | BZ37: Pass | CA37: Maintain following distance | CB37: Passed | CC37: Enrolled | CD37: Query Completed | CE37: 46037 | CF37: 46218 | CH37: Compliant | CJ37: Marcus | CK37: Chen | CL37: TX0000158 | CM37: TX | CN37: CDL Holder | CO37: Marcus Chen | CP37: 45664 | CQ37: 46394 | CR37: (512) 555-0100 | CS37: Dr. Monica Steele | CT37: 45664 | CU37: TX-ME-991196 | CV37: ME100006 | CW37: Physician Assistant | CX37: TX | CY37: Federal Motor Carrier Safety Regulations | DA37: No | DB37: No | DC37: No | DD37: No | DE37: No | DF37: No | DG37: Jane Doe | DH37: Sister | DI37: 555-555-5555 | DJ37: No | DK37: No | DL37: No | DM37: No | DN37: Yes - Appendectomy (2005) | DO37: 20/20 | DP37: 20/20 | DQ37: Pass | DR37: 118 | DS37: 78 | DT37: 72 | DU37: Normal | DV37: 45392 | DW37: 45394 | DX37: Negative | DY37: 45397 | DZ37: BOF Fleet Safety & Compliance Policy 2024 | EA37: Complete | EB37: 45413
A38: DRV-006 | B38: Marcus Chen | C38: 810 Demo Street, Dallas, TX 75202 | D38: 283-555-0100 | E38: ***-**-0101 | F38: Chase | G38: 112 | H38: 999900207 | I38: Medical Certification | J38: VALID | K38: TX0000165 | L38: 45826 | M38: 46394 | N38: 46455 | P38: Bald | Q38: Brown | R38: 6'-1" | S38: 238 | T38: M | U38: 25569 | V38: DRV-006.png | W38: Asian | X38: mchen@example.com | Y38: 810 Demo Street | Z38: Dallas | AA38: TX | AB38: 75202 | AC38: TX | AD38: Class A | AE38: 44004 | AF38: H,N,T | AH38: 45664 | AI38: MC-0060208 | AJ38: Dr. Monica Steele | AK38: ME100006 | AM38: Qualified | AN38: 46425 | AO38: 2 | AP38: 1 | AR38: Reviewed - Clear to Drive | AS38: 45544 | AT38: Authorized to Work | AU38: U.S. Passport | AX38: 45544 | AY38: BOF Onboarding Team | AZ38: Complete | BB38: Individual/Sole Proprietor | BC38: SSN | BD38: ***-**-0101 | BF38: 45544 | BG38: Received | BH38: Checking | BI38: Direct Deposit | BJ38: 45544 | BK38: Verified | BL38: 45537 | BM38: R. Delgado | BN38: Sleeper tractor | BO38: 53 ft reefer | BP38: Dallas, TX | BQ38: 4 | BR38: 4 | BS38: 3 | BT38: 4 | BU38: 4 | BV38: 4 | BW38: 4 | BX38: 4 | BY38: 4 | BZ38: Pass | CA38: Maintain following distance | CB38: Passed | CC38: Enrolled | CD38: Query Completed | CE38: 46037 | CF38: 46218 | CH38: Compliant | CJ38: Marcus | CK38: Chen | CL38: TX0000159 | CM38: TX | CN38: CDL Holder | CO38: Marcus Chen | CP38: 45664 | CQ38: 46394 | CR38: (512) 555-0100 | CS38: Dr. Monica Steele | CT38: 45664 | CU38: TX-ME-991196 | CV38: ME100006 | CW38: Physician Assistant | CX38: TX | CY38: Federal Motor Carrier Safety Regulations | DA38: No | DB38: No | DC38: No | DD38: No | DE38: No | DF38: No | DG38: Jane Doe | DH38: Sister | DI38: 555-555-5555 | DJ38: No | DK38: No | DL38: No | DM38: No | DN38: Yes - Appendectomy (2005) | DO38: 20/20 | DP38: 20/20 | DQ38: Pass | DR38: 118 | DS38: 78 | DT38: 72 | DU38: Normal | DV38: 45392 | DW38: 45394 | DX38: Negative | DY38: 45397 | DZ38: BOF Fleet Safety & Compliance Policy 2024 | EA38: Complete | EB38: 45413
A39: DRV-006 | B39: Marcus Chen | C39: 810 Demo Street, Dallas, TX 75202 | D39: 283-555-0100 | E39: ***-**-0101 | F39: Chase | G39: 112 | H39: 999900207 | I39: MVR Background Report | J39: VALID | K39: TX0000155 | L39: 45826 | M39: 46394 | N39: 46455 | P39: Bald | Q39: Brown | R39: 6'-1" | S39: 238 | T39: M | U39: 25569 | V39: DRV-006.png | W39: Asian | X39: mchen@example.com | Y39: 810 Demo Street | Z39: Dallas | AA39: TX | AB39: 75202 | AC39: TX | AD39: Class A | AE39: 44004 | AF39: H,N,T | AH39: 45664 | AI39: MC-0060208 | AJ39: Dr. Monica Steele | AK39: ME100006 | AM39: Qualified | AN39: 46425 | AO39: 2 | AP39: 1 | AR39: Reviewed - Clear to Drive | AS39: 45544 | AT39: Authorized to Work | AU39: U.S. Passport | AX39: 45544 | AY39: BOF Onboarding Team | AZ39: Complete | BB39: Individual/Sole Proprietor | BC39: SSN | BD39: ***-**-0101 | BF39: 45544 | BG39: Received | BH39: Checking | BI39: Direct Deposit | BJ39: 45544 | BK39: Verified | BL39: 45537 | BM39: R. Delgado | BN39: Sleeper tractor | BO39: 53 ft reefer | BP39: Dallas, TX | BQ39: 4 | BR39: 4 | BS39: 3 | BT39: 4 | BU39: 4 | BV39: 4 | BW39: 4 | BX39: 4 | BY39: 4 | BZ39: Pass | CA39: Maintain following distance | CB39: Passed | CC39: Enrolled | CD39: Query Completed | CE39: 46037 | CF39: 46218 | CH39: Compliant | CJ39: Marcus | CK39: Chen | CL39: TX0000160 | CM39: TX | CN39: CDL Holder | CO39: Marcus Chen | CP39: 45664 | CQ39: 46394 | CR39: (512) 555-0100 | CS39: Dr. Monica Steele | CT39: 45664 | CU39: TX-ME-991196 | CV39: ME100006 | CW39: Physician Assistant | CX39: TX | CY39: Federal Motor Carrier Safety Regulations | DA39: No | DB39: No | DC39: No | DD39: No | DE39: No | DF39: No | DG39: Jane Doe | DH39: Sister | DI39: 555-555-5555 | DJ39: No | DK39: No | DL39: No | DM39: No | DN39: Yes - Appendectomy (2005) | DO39: 20/20 | DP39: 20/20 | DQ39: Pass | DR39: 118 | DS39: 78 | DT39: 72 | DU39: Normal | DV39: 45392 | DW39: 45394 | DX39: Negative | DY39: 45397 | DZ39: BOF Fleet Safety & Compliance Policy 2024 | EA39: Complete | EB39: 45413
A40: DRV-006 | B40: Marcus Chen | C40: 810 Demo Street, Dallas, TX 75202 | D40: 283-555-0100 | E40: ***-**-0101 | F40: Chase | G40: 112 | H40: 999900207 | I40: Driver Application | J40: VALID | K40: TX0000166 | L40: 45826 | M40: 46394 | N40: 46455 | P40: Bald | Q40: Brown | R40: 6'-1" | S40: 238 | T40: M | U40: 25569 | V40: DRV-006.png | W40: Asian | X40: mchen@example.com | Y40: 810 Demo Street | Z40: Dallas | AA40: TX | AB40: 75202 | AC40: TX | AD40: Class A | AE40: 44004 | AF40: H,N,T | AH40: 45664 | AI40: MC-0060208 | AJ40: Dr. Monica Steele | AK40: ME100006 | AM40: Qualified | AN40: 46425 | AO40: 2 | AP40: 1 | AR40: Reviewed - Clear to Drive | AS40: 45544 | AT40: Authorized to Work | AU40: U.S. Passport | AX40: 45544 | AY40: BOF Onboarding Team | AZ40: Complete | BB40: Individual/Sole Proprietor | BC40: SSN | BD40: ***-**-0101 | BF40: 45544 | BG40: Received | BH40: Checking | BI40: Direct Deposit | BJ40: 45544 | BK40: Verified | BL40: 45537 | BM40: R. Delgado | BN40: Sleeper tractor | BO40: 53 ft reefer | BP40: Dallas, TX | BQ40: 4 | BR40: 4 | BS40: 3 | BT40: 4 | BU40: 4 | BV40: 4 | BW40: 4 | BX40: 4 | BY40: 4 | BZ40: Pass | CA40: Maintain following distance | CB40: Passed | CC40: Enrolled | CD40: Query Completed | CE40: 46037 | CF40: 46218 | CH40: Compliant | CJ40: Marcus | CK40: Chen | CL40: TX0000161 | CM40: TX | CN40: CDL Holder | CO40: Marcus Chen | CP40: 45664 | CQ40: 46394 | CR40: (512) 555-0100 | CS40: Dr. Monica Steele | CT40: 45664 | CU40: TX-ME-991196 | CV40: ME100006 | CW40: Physician Assistant | CX40: TX | CY40: Federal Motor Carrier Safety Regulations | DA40: No | DB40: No | DC40: No | DD40: No | DE40: No | DF40: No | DG40: Jane Doe | DH40: Sister | DI40: 555-555-5555 | DJ40: No | DK40: No | DL40: No | DM40: No | DN40: Yes - Appendectomy (2005) | DO40: 20/20 | DP40: 20/20 | DQ40: Pass | DR40: 118 | DS40: 78 | DT40: 72 | DU40: Normal | DV40: 45392 | DW40: 45394 | DX40: Negative | DY40: 45397 | DZ40: BOF Fleet Safety & Compliance Policy 2024 | EA40: Complete | EB40: 45413
A41: DRV-006 | B41: Marcus Chen | C41: 810 Demo Street, Dallas, TX 75202 | D41: 283-555-0100 | E41: ***-**-0101 | F41: Chase | G41: 112 | H41: 999900207 | I41: Road Test Certificate | J41: VALID | K41: TX0000156 | L41: 45826 | M41: 46394 | N41: 46455 | P41: Bald | Q41: Brown | R41: 6'-1" | S41: 238 | T41: M | U41: 25569 | V41: DRV-006.png | W41: Asian | X41: mchen@example.com | Y41: 810 Demo Street | Z41: Dallas | AA41: TX | AB41: 75202 | AC41: TX | AD41: Class A | AE41: 44004 | AF41: H,N,T | AH41: 45664 | AI41: MC-0060208 | AJ41: Dr. Monica Steele | AK41: ME100006 | AM41: Qualified | AN41: 46425 | AO41: 2 | AP41: 1 | AR41: Reviewed - Clear to Drive | AS41: 45544 | AT41: Authorized to Work | AU41: U.S. Passport | AX41: 45544 | AY41: BOF Onboarding Team | AZ41: Complete | BB41: Individual/Sole Proprietor | BC41: SSN | BD41: ***-**-0101 | BF41: 45544 | BG41: Received | BH41: Checking | BI41: Direct Deposit | BJ41: 45544 | BK41: Verified | BL41: 45537 | BM41: R. Delgado | BN41: Sleeper tractor | BO41: 53 ft reefer | BP41: Dallas, TX | BQ41: 4 | BR41: 4 | BS41: 3 | BT41: 4 | BU41: 4 | BV41: 4 | BW41: 4 | BX41: 4 | BY41: 4 | BZ41: Pass | CA41: Maintain following distance | CB41: Passed | CC41: Enrolled | CD41: Query Completed | CE41: 46037 | CF41: 46218 | CH41: Compliant | CJ41: Marcus | CK41: Chen | CL41: TX0000162 | CM41: TX | CN41: CDL Holder | CO41: Marcus Chen | CP41: 45664 | CQ41: 46394 | CR41: (512) 555-0100 | CS41: Dr. Monica Steele | CT41: 45664 | CU41: TX-ME-991196 | CV41: ME100006 | CW41: Physician Assistant | CX41: TX | CY41: Federal Motor Carrier Safety Regulations | DA41: No | DB41: No | DC41: No | DD41: No | DE41: No | DF41: No | DG41: Jane Doe | DH41: Sister | DI41: 555-555-5555 | DJ41: No | DK41: No | DL41: No | DM41: No | DN41: Yes - Appendectomy (2005) | DO41: 20/20 | DP41: 20/20 | DQ41: Pass | DR41: 118 | DS41: 78 | DT41: 72 | DU41: Normal | DV41: 45392 | DW41: 45394 | DX41: Negative | DY41: 45397 | DZ41: BOF Fleet Safety & Compliance Policy 2024 | EA41: Complete | EB41: 45413
A42: DRV-006 | B42: Marcus Chen | C42: 810 Demo Street, Dallas, TX 75202 | D42: 283-555-0100 | E42: ***-**-0101 | F42: Chase | G42: 112 | H42: 999900207 | I42: Incident/Accident Report | J42: VALID | K42: TX0000167 | L42: 45826 | M42: 46394 | N42: 46455 | O42: No major incidents recorded in last 90 days. | P42: Bald | Q42: Brown | R42: 6'-1" | S42: 238 | T42: M | U42: 25569 | V42: DRV-006.png | W42: Asian | X42: mchen@example.com | Y42: 810 Demo Street | Z42: Dallas | AA42: TX | AB42: 75202 | AC42: TX | AD42: Class A | AE42: 44004 | AF42: H,N,T | AH42: 45664 | AI42: MC-0060208 | AJ42: Dr. Monica Steele | AK42: ME100006 | AM42: Qualified | AN42: 46425 | AO42: 2 | AP42: 1 | AR42: Reviewed - Clear to Drive | AS42: 45544 | AT42: Authorized to Work | AU42: U.S. Passport | AX42: 45544 | AY42: BOF Onboarding Team | AZ42: Complete | BB42: Individual/Sole Proprietor | BC42: SSN | BD42: ***-**-0101 | BF42: 45544 | BG42: Received | BH42: Checking | BI42: Direct Deposit | BJ42: 45544 | BK42: Verified | BL42: 45537 | BM42: R. Delgado | BN42: Sleeper tractor | BO42: 53 ft reefer | BP42: Dallas, TX | BQ42: 4 | BR42: 4 | BS42: 3 | BT42: 4 | BU42: 4 | BV42: 4 | BW42: 4 | BX42: 4 | BY42: 4 | BZ42: Pass | CA42: Maintain following distance | CB42: Passed | CC42: Enrolled | CD42: Query Completed | CE42: 46037 | CF42: 46218 | CH42: Compliant | CJ42: Marcus | CK42: Chen | CL42: TX0000163 | CM42: TX | CN42: CDL Holder | CO42: Marcus Chen | CP42: 45664 | CQ42: 46394 | CR42: (512) 555-0100 | CS42: Dr. Monica Steele | CT42: 45664 | CU42: TX-ME-991196 | CV42: ME100006 | CW42: Physician Assistant | CX42: TX | CY42: Federal Motor Carrier Safety Regulations | DA42: No | DB42: No | DC42: No | DD42: No | DE42: No | DF42: No | DG42: Jane Doe | DH42: Sister | DI42: 555-555-5555 | DJ42: No | DK42: No | DL42: No | DM42: No | DN42: Yes - Appendectomy (2005) | DO42: 20/20 | DP42: 20/20 | DQ42: Pass | DR42: 118 | DS42: 78 | DT42: 72 | DU42: Normal | DV42: 45392 | DW42: 45394 | DX42: Negative | DY42: 45397 | DZ42: BOF Fleet Safety & Compliance Policy 2024 | EA42: Complete | EB42: 45413
A43: DRV-006 | B43: Marcus Chen | C43: 810 Demo Street, Dallas, TX 75202 | D43: 283-555-0100 | E43: ***-**-0101 | F43: Chase | G43: 112 | H43: 999900207 | I43: Direct Deposit Form | J43: VALID | K43: TX0000157 | L43: 45826 | M43: 46394 | N43: 46455 | P43: Bald | Q43: Brown | R43: 6'-1" | S43: 238 | T43: M | U43: 25569 | V43: DRV-006.png | W43: Asian | X43: mchen@example.com | Y43: 810 Demo Street | Z43: Dallas | AA43: TX | AB43: 75202 | AC43: TX | AD43: Class A | AE43: 44004 | AF43: H,N,T | AH43: 45664 | AI43: MC-0060208 | AJ43: Dr. Monica Steele | AK43: ME100006 | AM43: Qualified | AN43: 46425 | AO43: 2 | AP43: 1 | AR43: Reviewed - Clear to Drive | AS43: 45544 | AT43: Authorized to Work | AU43: U.S. Passport | AX43: 45544 | AY43: BOF Onboarding Team | AZ43: Complete | BB43: Individual/Sole Proprietor | BC43: SSN | BD43: ***-**-0101 | BF43: 45544 | BG43: Received | BH43: Checking | BI43: Direct Deposit | BJ43: 45544 | BK43: Verified | BL43: 45537 | BM43: R. Delgado | BN43: Sleeper tractor | BO43: 53 ft reefer | BP43: Dallas, TX | BQ43: 4 | BR43: 4 | BS43: 3 | BT43: 4 | BU43: 4 | BV43: 4 | BW43: 4 | BX43: 4 | BY43: 4 | BZ43: Pass | CA43: Maintain following distance | CB43: Passed | CC43: Enrolled | CD43: Query Completed | CE43: 46037 | CF43: 46218 | CH43: Compliant | CJ43: Marcus | CK43: Chen | CL43: TX0000164 | CM43: TX | CN43: CDL Holder | CO43: Marcus Chen | CP43: 45664 | CQ43: 46394 | CR43: (512) 555-0100 | CS43: Dr. Monica Steele | CT43: 45664 | CU43: TX-ME-991196 | CV43: ME100006 | CW43: Physician Assistant | CX43: TX | CY43: Federal Motor Carrier Safety Regulations | DA43: No | DB43: No | DC43: No | DD43: No | DE43: No | DF43: No | DG43: Jane Doe | DH43: Sister | DI43: 555-555-5555 | DJ43: No | DK43: No | DL43: No | DM43: No | DN43: Yes - Appendectomy (2005) | DO43: 20/20 | DP43: 20/20 | DQ43: Pass | DR43: 118 | DS43: 78 | DT43: 72 | DU43: Normal | DV43: 45392 | DW43: 45394 | DX43: Negative | DY43: 45397 | DZ43: BOF Fleet Safety & Compliance Policy 2024 | EA43: Complete | EB43: 45413
A44: DRV-007 | B44: Sofia Gomez | C44: 1020 Demo Street, Cleveland, OH 44115 | D44: 896-555-0100 | E44: ***-**-0109 | F44: Bank of America | G44: 110 | H44: 999900212 | I44: CDL Summary | J44: VALID | K44: OH0000112 | L44: 46530 | M44: 45739 | N44: 46456 | P44: Blonde | Q44: Blue | R44: 5'-4" | S44: 122 | T44: F | U44: 36161 | V44: DRV-007.png | W44: Hispanic | X44: sofiagomez@example.com | Y44: 1020 Demo Street | Z44: Cleveland | AA44: OH | AB44: 44115 | AC44: OH | AD44: Class A | AE44: 44708 | AF44: N | AH44: 45009 | AI44: MC-0071214 | AJ44: Dr. James Carter | AK44: ME100007 | AM44: Qualified | AN44: 46426 | AO44: 0 | AP44: 0 | AR44: Clear | AS44: 45566 | AT44: Authorized to Work | AU44: U.S. Passport | AX44: 45566 | AY44: BOF Onboarding Team | AZ44: Complete | BB44: Individual/Sole Proprietor | BC44: SSN | BD44: ***-**-0109 | BF44: 45566 | BG44: Received | BH44: Checking | BI44: Direct Deposit | BJ44: 45566 | BK44: Verified | BL44: 45559 | BM44: N. Brooks | BN44: Box truck | BO44: 26 ft box | BP44: Cleveland, OH | BQ44: 5 | BR44: 5 | BS44: 4 | BT44: 5 | BU44: 5 | BV44: 5 | BX44: 5 | BY44: 5 | BZ44: Pass | CB44: Passed | CC44: Enrolled | CD44: Query Completed | CE44: 46037 | CF44: 46218 | CH44: Compliant | CJ44: Sofia | CK44: Gomez | CL44: OH0000112 | CM44: OH | CN44: CDL Holder | CO44: Sofia Gomez | CP44: 45009 | CQ44: 45739 | CR44: (614) 555-0105 | CS44: Dr. James Carter | CT44: 45009 | CU44: OH-ME-801071 | CV44: ME100007 | CW44: DO | CX44: OH | CY44: Federal Motor Carrier Safety Regulations | DA44: No | DB44: No | DC44: No | DD44: No | DE44: No | DF44: No | DG44: Jane Doe | DH44: Sister | DI44: 555-555-5555 | DJ44: No | DK44: No | DL44: No | DM44: No | DN44: Yes - Appendectomy (2005) | DO44: 20/20 | DP44: 20/20 | DQ44: Pass | DR44: 118 | DS44: 78 | DT44: 72 | DU44: Normal | DV44: 45392 | DW44: 45394 | DX44: Negative | DY44: 45397 | DZ44: BOF Fleet Safety & Compliance Policy 2024 | EA44: Complete | EB44: 45413
A45: DRV-007 | B45: Sofia Gomez | C45: 1020 Demo Street, Cleveland, OH 44115 | D45: 896-555-0100 | E45: ***-**-0109 | F45: Bank of America | G45: 110 | H45: 999900212 | I45: Medical Certification | J45: VALID | K45: OH0000103 | L45: 46530 | M45: 45739 | N45: 46456 | P45: Blonde | Q45: Blue | R45: 5'-4" | S45: 122 | T45: F | U45: 36161 | V45: DRV-007.png | W45: Hispanic | X45: sofiagomez@example.com | Y45: 1020 Demo Street | Z45: Cleveland | AA45: OH | AB45: 44115 | AC45: OH | AD45: Class A | AE45: 44708 | AF45: N | AH45: 45009 | AI45: MC-0071214 | AJ45: Dr. James Carter | AK45: ME100007 | AM45: Qualified | AN45: 46426 | AO45: 0 | AP45: 0 | AR45: Clear | AS45: 45566 | AT45: Authorized to Work | AU45: U.S. Passport | AX45: 45566 | AY45: BOF Onboarding Team | AZ45: Complete | BB45: Individual/Sole Proprietor | BC45: SSN | BD45: ***-**-0109 | BF45: 45566 | BG45: Received | BH45: Checking | BI45: Direct Deposit | BJ45: 45566 | BK45: Verified | BL45: 45559 | BM45: N. Brooks | BN45: Box truck | BO45: 26 ft box | BP45: Cleveland, OH | BQ45: 5 | BR45: 5 | BS45: 4 | BT45: 5 | BU45: 5 | BV45: 5 | BX45: 5 | BY45: 5 | BZ45: Pass | CB45: Passed | CC45: Enrolled | CD45: Query Completed | CE45: 46037 | CF45: 46218 | CH45: Compliant | CJ45: Sofia | CK45: Gomez | CL45: OH0000113 | CM45: OH | CN45: CDL Holder | CO45: Sofia Gomez | CP45: 45009 | CQ45: 45739 | CR45: (614) 555-0105 | CS45: Dr. James Carter | CT45: 45009 | CU45: OH-ME-801071 | CV45: ME100007 | CW45: DO | CX45: OH | CY45: Federal Motor Carrier Safety Regulations | DA45: No | DB45: No | DC45: No | DD45: No | DE45: No | DF45: No | DG45: Jane Doe | DH45: Sister | DI45: 555-555-5555 | DJ45: No | DK45: No | DL45: No | DM45: No | DN45: Yes - Appendectomy (2005) | DO45: 20/20 | DP45: 20/20 | DQ45: Pass | DR45: 118 | DS45: 78 | DT45: 72 | DU45: Normal | DV45: 45392 | DW45: 45394 | DX45: Negative | DY45: 45397 | DZ45: BOF Fleet Safety & Compliance Policy 2024 | EA45: Complete | EB45: 45413
A46: DRV-007 | B46: Sofia Gomez | C46: 1020 Demo Street, Cleveland, OH 44115 | D46: 896-555-0100 | E46: ***-**-0109 | F46: Bank of America | G46: 110 | H46: 999900212 | I46: MVR Background Report | J46: VALID | K46: OH0000101 | L46: 46530 | M46: 45739 | N46: 46456 | P46: Blonde | Q46: Blue | R46: 5'-4" | S46: 122 | T46: F | U46: 36161 | V46: DRV-007.png | W46: Hispanic | X46: sofiagomez@example.com | Y46: 1020 Demo Street | Z46: Cleveland | AA46: OH | AB46: 44115 | AC46: OH | AD46: Class A | AE46: 44708 | AF46: N | AH46: 45009 | AI46: MC-0071214 | AJ46: Dr. James Carter | AK46: ME100007 | AM46: Qualified | AN46: 46426 | AO46: 0 | AP46: 0 | AR46: Clear | AS46: 45566 | AT46: Authorized to Work | AU46: U.S. Passport | AX46: 45566 | AY46: BOF Onboarding Team | AZ46: Complete | BB46: Individual/Sole Proprietor | BC46: SSN | BD46: ***-**-0109 | BF46: 45566 | BG46: Received | BH46: Checking | BI46: Direct Deposit | BJ46: 45566 | BK46: Verified | BL46: 45559 | BM46: N. Brooks | BN46: Box truck | BO46: 26 ft box | BP46: Cleveland, OH | BQ46: 5 | BR46: 5 | BS46: 4 | BT46: 5 | BU46: 5 | BV46: 5 | BX46: 5 | BY46: 5 | BZ46: Pass | CB46: Passed | CC46: Enrolled | CD46: Query Completed | CE46: 46037 | CF46: 46218 | CH46: Compliant | CJ46: Sofia | CK46: Gomez | CL46: OH0000114 | CM46: OH | CN46: CDL Holder | CO46: Sofia Gomez | CP46: 45009 | CQ46: 45739 | CR46: (614) 555-0105 | CS46: Dr. James Carter | CT46: 45009 | CU46: OH-ME-801071 | CV46: ME100007 | CW46: DO | CX46: OH | CY46: Federal Motor Carrier Safety Regulations | DA46: No | DB46: No | DC46: No | DD46: No | DE46: No | DF46: No | DG46: Jane Doe | DH46: Sister | DI46: 555-555-5555 | DJ46: No | DK46: No | DL46: No | DM46: No | DN46: Yes - Appendectomy (2005) | DO46: 20/20 | DP46: 20/20 | DQ46: Pass | DR46: 118 | DS46: 78 | DT46: 72 | DU46: Normal | DV46: 45392 | DW46: 45394 | DX46: Negative | DY46: 45397 | DZ46: BOF Fleet Safety & Compliance Policy 2024 | EA46: Complete | EB46: 45413
A47: DRV-007 | B47: Sofia Gomez | C47: 1020 Demo Street, Cleveland, OH 44115 | D47: 896-555-0100 | E47: ***-**-0109 | F47: Bank of America | G47: 110 | H47: 999900212 | I47: Driver Application | J47: VALID | K47: OH0000129 | L47: 46530 | M47: 45739 | N47: 46456 | P47: Blonde | Q47: Blue | R47: 5'-4" | S47: 122 | T47: F | U47: 36161 | V47: DRV-007.png | W47: Hispanic | X47: sofiagomez@example.com | Y47: 1020 Demo Street | Z47: Cleveland | AA47: OH | AB47: 44115 | AC47: OH | AD47: Class A | AE47: 44708 | AF47: N | AH47: 45009 | AI47: MC-0071214 | AJ47: Dr. James Carter | AK47: ME100007 | AM47: Qualified | AN47: 46426 | AO47: 0 | AP47: 0 | AR47: Clear | AS47: 45566 | AT47: Authorized to Work | AU47: U.S. Passport | AX47: 45566 | AY47: BOF Onboarding Team | AZ47: Complete | BB47: Individual/Sole Proprietor | BC47: SSN | BD47: ***-**-0109 | BF47: 45566 | BG47: Received | BH47: Checking | BI47: Direct Deposit | BJ47: 45566 | BK47: Verified | BL47: 45559 | BM47: N. Brooks | BN47: Box truck | BO47: 26 ft box | BP47: Cleveland, OH | BQ47: 5 | BR47: 5 | BS47: 4 | BT47: 5 | BU47: 5 | BV47: 5 | BX47: 5 | BY47: 5 | BZ47: Pass | CB47: Passed | CC47: Enrolled | CD47: Query Completed | CE47: 46037 | CF47: 46218 | CH47: Compliant | CJ47: Sofia | CK47: Gomez | CL47: OH0000115 | CM47: OH | CN47: CDL Holder | CO47: Sofia Gomez | CP47: 45009 | CQ47: 45739 | CR47: (614) 555-0105 | CS47: Dr. James Carter | CT47: 45009 | CU47: OH-ME-801071 | CV47: ME100007 | CW47: DO | CX47: OH | CY47: Federal Motor Carrier Safety Regulations | DA47: No | DB47: No | DC47: No | DD47: No | DE47: No | DF47: No | DG47: Jane Doe | DH47: Sister | DI47: 555-555-5555 | DJ47: No | DK47: No | DL47: No | DM47: No | DN47: Yes - Appendectomy (2005) | DO47: 20/20 | DP47: 20/20 | DQ47: Pass | DR47: 118 | DS47: 78 | DT47: 72 | DU47: Normal | DV47: 45392 | DW47: 45394 | DX47: Negative | DY47: 45397 | DZ47: BOF Fleet Safety & Compliance Policy 2024 | EA47: Complete | EB47: 45413
A48: DRV-007 | B48: Sofia Gomez | C48: 1020 Demo Street, Cleveland, OH 44115 | D48: 896-555-0100 | E48: ***-**-0109 | F48: Bank of America | G48: 110 | H48: 999900212 | I48: Road Test Certificate | J48: VALID | K48: OH0000120 | L48: 46530 | M48: 45739 | N48: 46456 | P48: Blonde | Q48: Blue | R48: 5'-4" | S48: 122 | T48: F | U48: 36161 | V48: DRV-007.png | W48: Hispanic | X48: sofiagomez@example.com | Y48: 1020 Demo Street | Z48: Cleveland | AA48: OH | AB48: 44115 | AC48: OH | AD48: Class A | AE48: 44708 | AF48: N | AH48: 45009 | AI48: MC-0071214 | AJ48: Dr. James Carter | AK48: ME100007 | AM48: Qualified | AN48: 46426 | AO48: 0 | AP48: 0 | AR48: Clear | AS48: 45566 | AT48: Authorized to Work | AU48: U.S. Passport | AX48: 45566 | AY48: BOF Onboarding Team | AZ48: Complete | BB48: Individual/Sole Proprietor | BC48: SSN | BD48: ***-**-0109 | BF48: 45566 | BG48: Received | BH48: Checking | BI48: Direct Deposit | BJ48: 45566 | BK48: Verified | BL48: 45559 | BM48: N. Brooks | BN48: Box truck | BO48: 26 ft box | BP48: Cleveland, OH | BQ48: 5 | BR48: 5 | BS48: 4 | BT48: 5 | BU48: 5 | BV48: 5 | BX48: 5 | BY48: 5 | BZ48: Pass | CB48: Passed | CC48: Enrolled | CD48: Query Completed | CE48: 46037 | CF48: 46218 | CH48: Compliant | CJ48: Sofia | CK48: Gomez | CL48: OH0000116 | CM48: OH | CN48: CDL Holder | CO48: Sofia Gomez | CP48: 45009 | CQ48: 45739 | CR48: (614) 555-0105 | CS48: Dr. James Carter | CT48: 45009 | CU48: OH-ME-801071 | CV48: ME100007 | CW48: DO | CX48: OH | CY48: Federal Motor Carrier Safety Regulations | DA48: No | DB48: No | DC48: No | DD48: No | DE48: No | DF48: No | DG48: Jane Doe | DH48: Sister | DI48: 555-555-5555 | DJ48: No | DK48: No | DL48: No | DM48: No | DN48: Yes - Appendectomy (2005) | DO48: 20/20 | DP48: 20/20 | DQ48: Pass | DR48: 118 | DS48: 78 | DT48: 72 | DU48: Normal | DV48: 45392 | DW48: 45394 | DX48: Negative | DY48: 45397 | DZ48: BOF Fleet Safety & Compliance Policy 2024 | EA48: Complete | EB48: 45413
A49: DRV-007 | B49: Sofia Gomez | C49: 1020 Demo Street, Cleveland, OH 44115 | D49: 896-555-0100 | E49: ***-**-0109 | F49: Bank of America | G49: 110 | H49: 999900212 | I49: Incident/Accident Report | J49: VALID | K49: OH0000121 | L49: 46530 | M49: 45739 | N49: 46456 | O49: Load L-507: Seal mismatch detected. Pickup: SEAL-73005 Delivery: SEAL-73099. | P49: Blonde | Q49: Blue | R49: 5'-4" | S49: 122 | T49: F | U49: 36161 | V49: DRV-007.png | W49: Hispanic | X49: sofiagomez@example.com | Y49: 1020 Demo Street | Z49: Cleveland | AA49: OH | AB49: 44115 | AC49: OH | AD49: Class A | AE49: 44708 | AF49: N | AH49: 45009 | AI49: MC-0071214 | AJ49: Dr. James Carter | AK49: ME100007 | AM49: Qualified | AN49: 46426 | AO49: 0 | AP49: 0 | AR49: Clear | AS49: 45566 | AT49: Authorized to Work | AU49: U.S. Passport | AX49: 45566 | AY49: BOF Onboarding Team | AZ49: Complete | BB49: Individual/Sole Proprietor | BC49: SSN | BD49: ***-**-0109 | BF49: 45566 | BG49: Received | BH49: Checking | BI49: Direct Deposit | BJ49: 45566 | BK49: Verified | BL49: 45559 | BM49: N. Brooks | BN49: Box truck | BO49: 26 ft box | BP49: Cleveland, OH | BQ49: 5 | BR49: 5 | BS49: 4 | BT49: 5 | BU49: 5 | BV49: 5 | BX49: 5 | BY49: 5 | BZ49: Pass | CB49: Passed | CC49: Enrolled | CD49: Query Completed | CE49: 46037 | CF49: 46218 | CH49: Compliant | CJ49: Sofia | CK49: Gomez | CL49: OH0000117 | CM49: OH | CN49: CDL Holder | CO49: Sofia Gomez | CP49: 45009 | CQ49: 45739 | CR49: (614) 555-0105 | CS49: Dr. James Carter | CT49: 45009 | CU49: OH-ME-801071 | CV49: ME100007 | CW49: DO | CX49: OH | CY49: Federal Motor Carrier Safety Regulations | DA49: No | DB49: No | DC49: No | DD49: No | DE49: No | DF49: No | DG49: Jane Doe | DH49: Sister | DI49: 555-555-5555 | DJ49: No | DK49: No | DL49: No | DM49: No | DN49: Yes - Appendectomy (2005) | DO49: 20/20 | DP49: 20/20 | DQ49: Pass | DR49: 118 | DS49: 78 | DT49: 72 | DU49: Normal | DV49: 45392 | DW49: 45394 | DX49: Negative | DY49: 45397 | DZ49: BOF Fleet Safety & Compliance Policy 2024 | EA49: Complete | EB49: 45413
A50: DRV-007 | B50: Sofia Gomez | C50: 1020 Demo Street, Cleveland, OH 44115 | D50: 896-555-0100 | E50: ***-**-0109 | F50: Bank of America | G50: 110 | H50: 999900212 | I50: Direct Deposit Form | J50: VALID | K50: OH0000073 | L50: 46530 | M50: 45739 | N50: 46456 | P50: Blonde | Q50: Blue | R50: 5'-4" | S50: 122 | T50: F | U50: 36161 | V50: DRV-007.png | W50: Hispanic | X50: sofiagomez@example.com | Y50: 1020 Demo Street | Z50: Cleveland | AA50: OH | AB50: 44115 | AC50: OH | AD50: Class A | AE50: 44708 | AF50: N | AH50: 45009 | AI50: MC-0071214 | AJ50: Dr. James Carter | AK50: ME100007 | AM50: Qualified | AN50: 46426 | AO50: 0 | AP50: 0 | AR50: Clear | AS50: 45566 | AT50: Authorized to Work | AU50: U.S. Passport | AX50: 45566 | AY50: BOF Onboarding Team | AZ50: Complete | BB50: Individual/Sole Proprietor | BC50: SSN | BD50: ***-**-0109 | BF50: 45566 | BG50: Received | BH50: Checking | BI50: Direct Deposit | BJ50: 45566 | BK50: Verified | BL50: 45559 | BM50: N. Brooks | BN50: Box truck | BO50: 26 ft box | BP50: Cleveland, OH | BQ50: 5 | BR50: 5 | BS50: 4 | BT50: 5 | BU50: 5 | BV50: 5 | BX50: 5 | BY50: 5 | BZ50: Pass | CB50: Passed | CC50: Enrolled | CD50: Query Completed | CE50: 46037 | CF50: 46218 | CH50: Compliant | CJ50: Sofia | CK50: Gomez | CL50: OH0000118 | CM50: OH | CN50: CDL Holder | CO50: Sofia Gomez | CP50: 45009 | CQ50: 45739 | CR50: (614) 555-0105 | CS50: Dr. James Carter | CT50: 45009 | CU50: OH-ME-801071 | CV50: ME100007 | CW50: DO | CX50: OH | CY50: Federal Motor Carrier Safety Regulations | DA50: No | DB50: No | DC50: No | DD50: No | DE50: No | DF50: No | DG50: Jane Doe | DH50: Sister | DI50: 555-555-5555 | DJ50: No | DK50: No | DL50: No | DM50: No | DN50: Yes - Appendectomy (2005) | DO50: 20/20 | DP50: 20/20 | DQ50: Pass | DR50: 118 | DS50: 78 | DT50: 72 | DU50: Normal | DV50: 45392 | DW50: 45394 | DX50: Negative | DY50: 45397 | DZ50: BOF Fleet Safety & Compliance Policy 2024 | EA50: Complete | EB50: 45413
A51: DRV-008 | B51: Liam Smith | C51: 530 Demo Street, Toledo, OH 43604 | D51: 820-555-0100 | E51: ***-**-0108 | F51: PNC | G51: 108 | H51: 999900204 | I51: CDL Summary | J51: VALID | K51: OH0000141 | L51: 46620 | M51: 46670 | N51: 46452 | P51: Blonde | Q51: Blue | R51: 6'-2" | S51: 194 | T51: M | U51: 23377 | V51: DRV-008.png | W51: Caucasian | X51: liamsmith@example.com | Y51: 530 Demo Street | Z51: Toledo | AA51: OH | AB51: 43604 | AC51: OH | AD51: Class A | AE51: 44798 | AF51: T | AG51: Air brake restriction | AH51: 45940 | AI51: MC-0080823 | AJ51: Dr. Alicia Brooks | AK51: ME100008 | AL51: Air brake restriction | AM51: Qualified | AN51: 46422 | AO51: 1 | AP51: 0 | AQ51: Air brake restriction | AR51: Clear | AS51: 45467 | AT51: Authorized to Work | AU51: U.S. Passport | AX51: 45467 | AY51: BOF Onboarding Team | AZ51: Complete | BB51: Individual/Sole Proprietor | BC51: SSN | BD51: ***-**-0108 | BF51: 45467 | BG51: Received | BH51: Checking | BI51: Direct Deposit | BJ51: 45467 | BK51: Verified | BL51: 45460 | BM51: L. Harper | BN51: Day cab tractor | BO51: Flatbed | BP51: Toledo, OH | BQ51: 4 | BR51: 5 | BS51: 4 | BT51: 4 | BU51: 4 | BV51: 5 | BW51: 4 | BX51: 4 | BY51: 4 | BZ51: Pass | CA51: Air brake restriction applies | CB51: Passed | CC51: Enrolled | CD51: Query Completed | CE51: 46037 | CF51: 46218 | CH51: Compliant | CJ51: Liam | CK51: Smith | CL51: OH0000141 | CM51: OH | CN51: CDL Holder | CO51: Liam Smith | CP51: 45940 | CQ51: 46670 | CR51: (614) 555-0114 | CS51: Dr. Alicia Brooks | CT51: 45940 | CU51: OH-ME-134036 | CV51: ME100008 | CW51: Advanced Practice Nurse | CX51: OH | CY51: Federal Motor Carrier Safety Regulations with applicable State variances | DA51: No | DB51: No | DC51: No | DD51: Yes | DE51: No | DF51: No | DG51: Jane Doe | DH51: Sister | DI51: 555-555-5555 | DJ51: No | DK51: No | DL51: No | DM51: No | DN51: Yes - Appendectomy (2005) | DO51: 20/20 | DP51: 20/20 | DQ51: Pass | DR51: 118 | DS51: 78 | DT51: 72 | DU51: Normal | DV51: 45392 | DW51: 45394 | DX51: Negative | DY51: 45397 | DZ51: BOF Fleet Safety & Compliance Policy 2024 | EA51: Complete | EB51: 45413
A52: DRV-008 | B52: Liam Smith | C52: 530 Demo Street, Toledo, OH 43604 | D52: 820-555-0100 | E52: ***-**-0108 | F52: PNC | G52: 108 | H52: 999900204 | I52: Medical Certification | J52: VALID | K52: OH0000139 | L52: 46620 | M52: 46670 | N52: 46452 | P52: Blonde | Q52: Blue | R52: 6'-2" | S52: 194 | T52: M | U52: 23377 | V52: DRV-008.png | W52: Caucasian | X52: liamsmith@example.com | Y52: 530 Demo Street | Z52: Toledo | AA52: OH | AB52: 43604 | AC52: OH | AD52: Class A | AE52: 44798 | AF52: T | AG52: Air brake restriction | AH52: 45940 | AI52: MC-0080823 | AJ52: Dr. Alicia Brooks | AK52: ME100008 | AL52: Air brake restriction | AM52: Qualified | AN52: 46422 | AO52: 1 | AP52: 0 | AQ52: Air brake restriction | AR52: Clear | AS52: 45467 | AT52: Authorized to Work | AU52: U.S. Passport | AX52: 45467 | AY52: BOF Onboarding Team | AZ52: Complete | BB52: Individual/Sole Proprietor | BC52: SSN | BD52: ***-**-0108 | BF52: 45467 | BG52: Received | BH52: Checking | BI52: Direct Deposit | BJ52: 45467 | BK52: Verified | BL52: 45460 | BM52: L. Harper | BN52: Day cab tractor | BO52: Flatbed | BP52: Toledo, OH | BQ52: 4 | BR52: 5 | BS52: 4 | BT52: 4 | BU52: 4 | BV52: 5 | BW52: 4 | BX52: 4 | BY52: 4 | BZ52: Pass | CA52: Air brake restriction applies | CB52: Passed | CC52: Enrolled | CD52: Query Completed | CE52: 46037 | CF52: 46218 | CH52: Compliant | CJ52: Liam | CK52: Smith | CL52: OH0000142 | CM52: OH | CN52: CDL Holder | CO52: Liam Smith | CP52: 45940 | CQ52: 46670 | CR52: (614) 555-0114 | CS52: Dr. Alicia Brooks | CT52: 45940 | CU52: OH-ME-134036 | CV52: ME100008 | CW52: Advanced Practice Nurse | CX52: OH | CY52: Federal Motor Carrier Safety Regulations with applicable State variances | DA52: No | DB52: No | DC52: No | DD52: Yes | DE52: No | DF52: No | DG52: Jane Doe | DH52: Sister | DI52: 555-555-5555 | DJ52: No | DK52: No | DL52: No | DM52: No | DN52: Yes - Appendectomy (2005) | DO52: 20/20 | DP52: 20/20 | DQ52: Pass | DR52: 118 | DS52: 78 | DT52: 72 | DU52: Normal | DV52: 45392 | DW52: 45394 | DX52: Negative | DY52: 45397 | DZ52: BOF Fleet Safety & Compliance Policy 2024 | EA52: Complete | EB52: 45413
A53: DRV-008 | B53: Liam Smith | C53: 530 Demo Street, Toledo, OH 43604 | D53: 820-555-0100 | E53: ***-**-0108 | F53: PNC | G53: 108 | H53: 999900204 | I53: MVR Background Report | J53: VALID | K53: OH0000091 | L53: 46620 | M53: 46670 | N53: 46452 | P53: Blonde | Q53: Blue | R53: 6'-2" | S53: 194 | T53: M | U53: 23377 | V53: DRV-008.png | W53: Caucasian | X53: liamsmith@example.com | Y53: 530 Demo Street | Z53: Toledo | AA53: OH | AB53: 43604 | AC53: OH | AD53: Class A | AE53: 44798 | AF53: T | AG53: Air brake restriction | AH53: 45940 | AI53: MC-0080823 | AJ53: Dr. Alicia Brooks | AK53: ME100008 | AL53: Air brake restriction | AM53: Qualified | AN53: 46422 | AO53: 1 | AP53: 0 | AQ53: Air brake restriction | AR53: Clear | AS53: 45467 | AT53: Authorized to Work | AU53: U.S. Passport | AX53: 45467 | AY53: BOF Onboarding Team | AZ53: Complete | BB53: Individual/Sole Proprietor | BC53: SSN | BD53: ***-**-0108 | BF53: 45467 | BG53: Received | BH53: Checking | BI53: Direct Deposit | BJ53: 45467 | BK53: Verified | BL53: 45460 | BM53: L. Harper | BN53: Day cab tractor | BO53: Flatbed | BP53: Toledo, OH | BQ53: 4 | BR53: 5 | BS53: 4 | BT53: 4 | BU53: 4 | BV53: 5 | BW53: 4 | BX53: 4 | BY53: 4 | BZ53: Pass | CA53: Air brake restriction applies | CB53: Passed | CC53: Enrolled | CD53: Query Completed | CE53: 46037 | CF53: 46218 | CH53: Compliant | CJ53: Liam | CK53: Smith | CL53: OH0000143 | CM53: OH | CN53: CDL Holder | CO53: Liam Smith | CP53: 45940 | CQ53: 46670 | CR53: (614) 555-0114 | CS53: Dr. Alicia Brooks | CT53: 45940 | CU53: OH-ME-134036 | CV53: ME100008 | CW53: Advanced Practice Nurse | CX53: OH | CY53: Federal Motor Carrier Safety Regulations with applicable State variances | DA53: No | DB53: No | DC53: No | DD53: Yes | DE53: No | DF53: No | DG53: Jane Doe | DH53: Sister | DI53: 555-555-5555 | DJ53: No | DK53: No | DL53: No | DM53: No | DN53: Yes - Appendectomy (2005) | DO53: 20/20 | DP53: 20/20 | DQ53: Pass | DR53: 118 | DS53: 78 | DT53: 72 | DU53: Normal | DV53: 45392 | DW53: 45394 | DX53: Negative | DY53: 45397 | DZ53: BOF Fleet Safety & Compliance Policy 2024 | EA53: Complete | EB53: 45413
A54: DRV-008 | B54: Liam Smith | C54: 530 Demo Street, Toledo, OH 43604 | D54: 820-555-0100 | E54: ***-**-0108 | F54: PNC | G54: 108 | H54: 999900204 | I54: Driver Application | J54: VALID | K54: OH0000128 | L54: 46620 | M54: 46670 | N54: 46452 | P54: Blonde | Q54: Blue | R54: 6'-2" | S54: 194 | T54: M | U54: 23377 | V54: DRV-008.png | W54: Caucasian | X54: liamsmith@example.com | Y54: 530 Demo Street | Z54: Toledo | AA54: OH | AB54: 43604 | AC54: OH | AD54: Class A | AE54: 44798 | AF54: T | AG54: Air brake restriction | AH54: 45940 | AI54: MC-0080823 | AJ54: Dr. Alicia Brooks | AK54: ME100008 | AL54: Air brake restriction | AM54: Qualified | AN54: 46422 | AO54: 1 | AP54: 0 | AQ54: Air brake restriction | AR54: Clear | AS54: 45467 | AT54: Authorized to Work | AU54: U.S. Passport | AX54: 45467 | AY54: BOF Onboarding Team | AZ54: Complete | BB54: Individual/Sole Proprietor | BC54: SSN | BD54: ***-**-0108 | BF54: 45467 | BG54: Received | BH54: Checking | BI54: Direct Deposit | BJ54: 45467 | BK54: Verified | BL54: 45460 | BM54: L. Harper | BN54: Day cab tractor | BO54: Flatbed | BP54: Toledo, OH | BQ54: 4 | BR54: 5 | BS54: 4 | BT54: 4 | BU54: 4 | BV54: 5 | BW54: 4 | BX54: 4 | BY54: 4 | BZ54: Pass | CA54: Air brake restriction applies | CB54: Passed | CC54: Enrolled | CD54: Query Completed | CE54: 46037 | CF54: 46218 | CH54: Compliant | CJ54: Liam | CK54: Smith | CL54: OH0000144 | CM54: OH | CN54: CDL Holder | CO54: Liam Smith | CP54: 45940 | CQ54: 46670 | CR54: (614) 555-0114 | CS54: Dr. Alicia Brooks | CT54: 45940 | CU54: OH-ME-134036 | CV54: ME100008 | CW54: Advanced Practice Nurse | CX54: OH | CY54: Federal Motor Carrier Safety Regulations with applicable State variances | DA54: No | DB54: No | DC54: No | DD54: Yes | DE54: No | DF54: No | DG54: Jane Doe | DH54: Sister | DI54: 555-555-5555 | DJ54: No | DK54: No | DL54: No | DM54: No | DN54: Yes - Appendectomy (2005) | DO54: 20/20 | DP54: 20/20 | DQ54: Pass | DR54: 118 | DS54: 78 | DT54: 72 | DU54: Normal | DV54: 45392 | DW54: 45394 | DX54: Negative | DY54: 45397 | DZ54: BOF Fleet Safety & Compliance Policy 2024 | EA54: Complete | EB54: 45413
A55: DRV-008 | B55: Liam Smith | C55: 530 Demo Street, Toledo, OH 43604 | D55: 820-555-0100 | E55: ***-**-0108 | F55: PNC | G55: 108 | H55: 999900204 | I55: Road Test Certificate | J55: VALID | K55: OH0000094 | L55: 46620 | M55: 46670 | N55: 46452 | P55: Blonde | Q55: Blue | R55: 6'-2" | S55: 194 | T55: M | U55: 23377 | V55: DRV-008.png | W55: Caucasian | X55: liamsmith@example.com | Y55: 530 Demo Street | Z55: Toledo | AA55: OH | AB55: 43604 | AC55: OH | AD55: Class A | AE55: 44798 | AF55: T | AG55: Air brake restriction | AH55: 45940 | AI55: MC-0080823 | AJ55: Dr. Alicia Brooks | AK55: ME100008 | AL55: Air brake restriction | AM55: Qualified | AN55: 46422 | AO55: 1 | AP55: 0 | AQ55: Air brake restriction | AR55: Clear | AS55: 45467 | AT55: Authorized to Work | AU55: U.S. Passport | AX55: 45467 | AY55: BOF Onboarding Team | AZ55: Complete | BB55: Individual/Sole Proprietor | BC55: SSN | BD55: ***-**-0108 | BF55: 45467 | BG55: Received | BH55: Checking | BI55: Direct Deposit | BJ55: 45467 | BK55: Verified | BL55: 45460 | BM55: L. Harper | BN55: Day cab tractor | BO55: Flatbed | BP55: Toledo, OH | BQ55: 4 | BR55: 5 | BS55: 4 | BT55: 4 | BU55: 4 | BV55: 5 | BW55: 4 | BX55: 4 | BY55: 4 | BZ55: Pass | CA55: Air brake restriction applies | CB55: Passed | CC55: Enrolled | CD55: Query Completed | CE55: 46037 | CF55: 46218 | CH55: Compliant | CJ55: Liam | CK55: Smith | CL55: OH0000145 | CM55: OH | CN55: CDL Holder | CO55: Liam Smith | CP55: 45940 | CQ55: 46670 | CR55: (614) 555-0114 | CS55: Dr. Alicia Brooks | CT55: 45940 | CU55: OH-ME-134036 | CV55: ME100008 | CW55: Advanced Practice Nurse | CX55: OH | CY55: Federal Motor Carrier Safety Regulations with applicable State variances | DA55: No | DB55: No | DC55: No | DD55: Yes | DE55: No | DF55: No | DG55: Jane Doe | DH55: Sister | DI55: 555-555-5555 | DJ55: No | DK55: No | DL55: No | DM55: No | DN55: Yes - Appendectomy (2005) | DO55: 20/20 | DP55: 20/20 | DQ55: Pass | DR55: 118 | DS55: 78 | DT55: 72 | DU55: Normal | DV55: 45392 | DW55: 45394 | DX55: Negative | DY55: 45397 | DZ55: BOF Fleet Safety & Compliance Policy 2024 | EA55: Complete | EB55: 45413
A56: DRV-008 | B56: Liam Smith | C56: 530 Demo Street, Toledo, OH 43604 | D56: 820-555-0100 | E56: ***-**-0108 | F56: PNC | G56: 108 | H56: 999900204 | I56: Incident/Accident Report | J56: VALID | K56: OH0000098 | L56: 46620 | M56: 46670 | N56: 46452 | O56: No major incidents recorded in last 90 days. | P56: Blonde | Q56: Blue | R56: 6'-2" | S56: 194 | T56: M | U56: 23377 | V56: DRV-008.png | W56: Caucasian | X56: liamsmith@example.com | Y56: 530 Demo Street | Z56: Toledo | AA56: OH | AB56: 43604 | AC56: OH | AD56: Class A | AE56: 44798 | AF56: T | AG56: Air brake restriction | AH56: 45940 | AI56: MC-0080823 | AJ56: Dr. Alicia Brooks | AK56: ME100008 | AL56: Air brake restriction | AM56: Qualified | AN56: 46422 | AO56: 1 | AP56: 0 | AQ56: Air brake restriction | AR56: Clear | AS56: 45467 | AT56: Authorized to Work | AU56: U.S. Passport | AX56: 45467 | AY56: BOF Onboarding Team | AZ56: Complete | BB56: Individual/Sole Proprietor | BC56: SSN | BD56: ***-**-0108 | BF56: 45467 | BG56: Received | BH56: Checking | BI56: Direct Deposit | BJ56: 45467 | BK56: Verified | BL56: 45460 | BM56: L. Harper | BN56: Day cab tractor | BO56: Flatbed | BP56: Toledo, OH | BQ56: 4 | BR56: 5 | BS56: 4 | BT56: 4 | BU56: 4 | BV56: 5 | BW56: 4 | BX56: 4 | BY56: 4 | BZ56: Pass | CA56: Air brake restriction applies | CB56: Passed | CC56: Enrolled | CD56: Query Completed | CE56: 46037 | CF56: 46218 | CH56: Compliant | CJ56: Liam | CK56: Smith | CL56: OH0000146 | CM56: OH | CN56: CDL Holder | CO56: Liam Smith | CP56: 45940 | CQ56: 46670 | CR56: (614) 555-0114 | CS56: Dr. Alicia Brooks | CT56: 45940 | CU56: OH-ME-134036 | CV56: ME100008 | CW56: Advanced Practice Nurse | CX56: OH | CY56: Federal Motor Carrier Safety Regulations with applicable State variances | DA56: No | DB56: No | DC56: No | DD56: Yes | DE56: No | DF56: No | DG56: Jane Doe | DH56: Sister | DI56: 555-555-5555 | DJ56: No | DK56: No | DL56: No | DM56: No | DN56: Yes - Appendectomy (2005) | DO56: 20/20 | DP56: 20/20 | DQ56: Pass | DR56: 118 | DS56: 78 | DT56: 72 | DU56: Normal | DV56: 45392 | DW56: 45394 | DX56: Negative | DY56: 45397 | DZ56: BOF Fleet Safety & Compliance Policy 2024 | EA56: Complete | EB56: 45413
A57: DRV-008 | B57: Liam Smith | C57: 530 Demo Street, Toledo, OH 43604 | D57: 820-555-0100 | E57: ***-**-0108 | F57: PNC | G57: 108 | H57: 999900204 | I57: Direct Deposit Form | J57: VALID | K57: OH0000150 | L57: 46620 | M57: 46670 | N57: 46452 | P57: Blonde | Q57: Blue | R57: 6'-2" | S57: 194 | T57: M | U57: 23377 | V57: DRV-008.png | W57: Caucasian | X57: liamsmith@example.com | Y57: 530 Demo Street | Z57: Toledo | AA57: OH | AB57: 43604 | AC57: OH | AD57: Class A | AE57: 44798 | AF57: T | AG57: Air brake restriction | AH57: 45940 | AI57: MC-0080823 | AJ57: Dr. Alicia Brooks | AK57: ME100008 | AL57: Air brake restriction | AM57: Qualified | AN57: 46422 | AO57: 1 | AP57: 0 | AQ57: Air brake restriction | AR57: Clear | AS57: 45467 | AT57: Authorized to Work | AU57: U.S. Passport | AX57: 45467 | AY57: BOF Onboarding Team | AZ57: Complete | BB57: Individual/Sole Proprietor | BC57: SSN | BD57: ***-**-0108 | BF57: 45467 | BG57: Received | BH57: Checking | BI57: Direct Deposit | BJ57: 45467 | BK57: Verified | BL57: 45460 | BM57: L. Harper | BN57: Day cab tractor | BO57: Flatbed | BP57: Toledo, OH | BQ57: 4 | BR57: 5 | BS57: 4 | BT57: 4 | BU57: 4 | BV57: 5 | BW57: 4 | BX57: 4 | BY57: 4 | BZ57: Pass | CA57: Air brake restriction applies | CB57: Passed | CC57: Enrolled | CD57: Query Completed | CE57: 46037 | CF57: 46218 | CH57: Compliant | CJ57: Liam | CK57: Smith | CL57: OH0000147 | CM57: OH | CN57: CDL Holder | CO57: Liam Smith | CP57: 45940 | CQ57: 46670 | CR57: (614) 555-0114 | CS57: Dr. Alicia Brooks | CT57: 45940 | CU57: OH-ME-134036 | CV57: ME100008 | CW57: Advanced Practice Nurse | CX57: OH | CY57: Federal Motor Carrier Safety Regulations with applicable State variances | DA57: No | DB57: No | DC57: No | DD57: Yes | DE57: No | DF57: No | DG57: Jane Doe | DH57: Sister | DI57: 555-555-5555 | DJ57: No | DK57: No | DL57: No | DM57: No | DN57: Yes - Appendectomy (2005) | DO57: 20/20 | DP57: 20/20 | DQ57: Pass | DR57: 118 | DS57: 78 | DT57: 72 | DU57: Normal | DV57: 45392 | DW57: 45394 | DX57: Negative | DY57: 45397 | DZ57: BOF Fleet Safety & Compliance Policy 2024 | EA57: Complete | EB57: 45413
A58: DRV-009 | B58: Emma Brown | C58: 630 Demo Street, Columbus, OH 43215 | D58: 206-555-0103 | E58: ***-**-0124 | F58: Chase | G58: 103 | H58: 999900210 | I58: CDL Summary | J58: VALID | K58: OH0000104 | L58: 46424 | M58: 46645 | N58: 46451 | P58: Black | Q58: Brown | R58: 5'-4" | S58: 144 | T58: F | U58: 30682 | V58: DRV-009.png | W58: Caucasian | X58: emmabrown@example.com | Y58: 630 Demo Street | Z58: Columbus | AA58: OH | AB58: 43215 | AC58: OH | AD58: Class B | AE58: 44602 | AF58: P | AG58: Corrective lenses | AH58: 45915 | AI58: MC-0091016 | AJ58: Dr. David Yang | AK58: ME100009 | AM58: Qualified | AN58: 46421 | AO58: 0 | AP58: 0 | AQ58: Corrective lenses | AR58: Clear | AS58: 45502 | AT58: Authorized to Work | AU58: U.S. Passport | AX58: 45502 | AY58: BOF Onboarding Team | AZ58: Complete | BB58: Individual/Sole Proprietor | BC58: SSN | BD58: ***-**-0124 | BF58: 45502 | BG58: Received | BH58: Savings | BI58: Direct Deposit | BJ58: 45502 | BK58: Verified | BL58: 45495 | BM58: J. Alvarez | BN58: Straight truck | BO58: Straight truck | BP58: Columbus, OH | BQ58: 5 | BR58: 5 | BS58: 4 | BT58: 5 | BU58: 5 | BV58: 5 | BX58: 5 | BY58: 5 | BZ58: Pass | CA58: Straight truck route only | CB58: Passed | CC58: Enrolled | CD58: Query Completed | CE58: 46037 | CF58: 46218 | CH58: Compliant | CJ58: Emma | CK58: Brown | CL58: OH0000104 | CM58: OH | CN58: CDL Holder | CO58: Emma Brown | CP58: 45915 | CQ58: 46645 | CR58: (614) 555-0113 | CS58: Dr. David Yang | CT58: 45915 | CU58: OH-ME-556547 | CV58: ME100009 | CW58: Physician Assistant | CX58: OH | CY58: Federal Motor Carrier Safety Regulations | DA58: No | DB58: No | DC58: No | DD58: No | DE58: No | DF58: No | DG58: Jane Doe | DH58: Sister | DI58: 555-555-5555 | DJ58: No | DK58: No | DL58: No | DM58: No | DN58: Yes - Appendectomy (2005) | DO58: 20/20 | DP58: 20/20 | DQ58: Pass | DR58: 118 | DS58: 78 | DT58: 72 | DU58: Normal | DV58: 45392 | DW58: 45394 | DX58: Negative | DY58: 45397 | DZ58: BOF Fleet Safety & Compliance Policy 2024 | EA58: Complete | EB58: 45413
A59: DRV-009 | B59: Emma Brown | C59: 630 Demo Street, Columbus, OH 43215 | D59: 206-555-0103 | E59: ***-**-0124 | F59: Chase | G59: 103 | H59: 999900210 | I59: Medical Certification | J59: VALID | K59: OH0000083 | L59: 46424 | M59: 46645 | N59: 46451 | P59: Black | Q59: Brown | R59: 5'-4" | S59: 144 | T59: F | U59: 30682 | V59: DRV-009.png | W59: Caucasian | X59: emmabrown@example.com | Y59: 630 Demo Street | Z59: Columbus | AA59: OH | AB59: 43215 | AC59: OH | AD59: Class B | AE59: 44602 | AF59: P | AG59: Corrective lenses | AH59: 45915 | AI59: MC-0091016 | AJ59: Dr. David Yang | AK59: ME100009 | AM59: Qualified | AN59: 46421 | AO59: 0 | AP59: 0 | AQ59: Corrective lenses | AR59: Clear | AS59: 45502 | AT59: Authorized to Work | AU59: U.S. Passport | AX59: 45502 | AY59: BOF Onboarding Team | AZ59: Complete | BB59: Individual/Sole Proprietor | BC59: SSN | BD59: ***-**-0124 | BF59: 45502 | BG59: Received | BH59: Savings | BI59: Direct Deposit | BJ59: 45502 | BK59: Verified | BL59: 45495 | BM59: J. Alvarez | BN59: Straight truck | BO59: Straight truck | BP59: Columbus, OH | BQ59: 5 | BR59: 5 | BS59: 4 | BT59: 5 | BU59: 5 | BV59: 5 | BX59: 5 | BY59: 5 | BZ59: Pass | CA59: Straight truck route only | CB59: Passed | CC59: Enrolled | CD59: Query Completed | CE59: 46037 | CF59: 46218 | CH59: Compliant | CJ59: Emma | CK59: Brown | CL59: OH0000105 | CM59: OH | CN59: CDL Holder | CO59: Emma Brown | CP59: 45915 | CQ59: 46645 | CR59: (614) 555-0113 | CS59: Dr. David Yang | CT59: 45915 | CU59: OH-ME-556547 | CV59: ME100009 | CW59: Physician Assistant | CX59: OH | CY59: Federal Motor Carrier Safety Regulations | DA59: No | DB59: No | DC59: No | DD59: No | DE59: No | DF59: No | DG59: Jane Doe | DH59: Sister | DI59: 555-555-5555 | DJ59: No | DK59: No | DL59: No | DM59: No | DN59: Yes - Appendectomy (2005) | DO59: 20/20 | DP59: 20/20 | DQ59: Pass | DR59: 118 | DS59: 78 | DT59: 72 | DU59: Normal | DV59: 45392 | DW59: 45394 | DX59: Negative | DY59: 45397 | DZ59: BOF Fleet Safety & Compliance Policy 2024 | EA59: Complete | EB59: 45413
A60: DRV-009 | B60: Emma Brown | C60: 630 Demo Street, Columbus, OH 43215 | D60: 206-555-0103 | E60: ***-**-0124 | F60: Chase | G60: 103 | H60: 999900210 | I60: MVR Background Report | J60: VALID | K60: OH0000100 | L60: 46424 | M60: 46645 | N60: 46451 | P60: Black | Q60: Brown | R60: 5'-4" | S60: 144 | T60: F | U60: 30682 | V60: DRV-009.png | W60: Caucasian | X60: emmabrown@example.com | Y60: 630 Demo Street | Z60: Columbus | AA60: OH | AB60: 43215 | AC60: OH | AD60: Class B | AE60: 44602 | AF60: P | AG60: Corrective lenses | AH60: 45915 | AI60: MC-0091016 | AJ60: Dr. David Yang | AK60: ME100009 | AM60: Qualified | AN60: 46421 | AO60: 0 | AP60: 0 | AQ60: Corrective lenses | AR60: Clear | AS60: 45502 | AT60: Authorized to Work | AU60: U.S. Passport | AX60: 45502 | AY60: BOF Onboarding Team | AZ60: Complete | BB60: Individual/Sole Proprietor | BC60: SSN | BD60: ***-**-0124 | BF60: 45502 | BG60: Received | BH60: Savings | BI60: Direct Deposit | BJ60: 45502 | BK60: Verified | BL60: 45495 | BM60: J. Alvarez | BN60: Straight truck | BO60: Straight truck | BP60: Columbus, OH | BQ60: 5 | BR60: 5 | BS60: 4 | BT60: 5 | BU60: 5 | BV60: 5 | BX60: 5 | BY60: 5 | BZ60: Pass | CA60: Straight truck route only | CB60: Passed | CC60: Enrolled | CD60: Query Completed | CE60: 46037 | CF60: 46218 | CH60: Compliant | CJ60: Emma | CK60: Brown | CL60: OH0000106 | CM60: OH | CN60: CDL Holder | CO60: Emma Brown | CP60: 45915 | CQ60: 46645 | CR60: (614) 555-0113 | CS60: Dr. David Yang | CT60: 45915 | CU60: OH-ME-556547 | CV60: ME100009 | CW60: Physician Assistant | CX60: OH | CY60: Federal Motor Carrier Safety Regulations | DA60: No | DB60: No | DC60: No | DD60: No | DE60: No | DF60: No | DG60: Jane Doe | DH60: Sister | DI60: 555-555-5555 | DJ60: No | DK60: No | DL60: No | DM60: No | DN60: Yes - Appendectomy (2005) | DO60: 20/20 | DP60: 20/20 | DQ60: Pass | DR60: 118 | DS60: 78 | DT60: 72 | DU60: Normal | DV60: 45392 | DW60: 45394 | DX60: Negative | DY60: 45397 | DZ60: BOF Fleet Safety & Compliance Policy 2024 | EA60: Complete | EB60: 45413
A61: DRV-009 | B61: Emma Brown | C61: 630 Demo Street, Columbus, OH 43215 | D61: 206-555-0103 | E61: ***-**-0124 | F61: Chase | G61: 103 | H61: 999900210 | I61: Driver Application | J61: VALID | K61: OH0000148 | L61: 46424 | M61: 46645 | N61: 46451 | P61: Black | Q61: Brown | R61: 5'-4" | S61: 144 | T61: F | U61: 30682 | V61: DRV-009.png | W61: Caucasian | X61: emmabrown@example.com | Y61: 630 Demo Street | Z61: Columbus | AA61: OH | AB61: 43215 | AC61: OH | AD61: Class B | AE61: 44602 | AF61: P | AG61: Corrective lenses | AH61: 45915 | AI61: MC-0091016 | AJ61: Dr. David Yang | AK61: ME100009 | AM61: Qualified | AN61: 46421 | AO61: 0 | AP61: 0 | AQ61: Corrective lenses | AR61: Clear | AS61: 45502 | AT61: Authorized to Work | AU61: U.S. Passport | AX61: 45502 | AY61: BOF Onboarding Team | AZ61: Complete | BB61: Individual/Sole Proprietor | BC61: SSN | BD61: ***-**-0124 | BF61: 45502 | BG61: Received | BH61: Savings | BI61: Direct Deposit | BJ61: 45502 | BK61: Verified | BL61: 45495 | BM61: J. Alvarez | BN61: Straight truck | BO61: Straight truck | BP61: Columbus, OH | BQ61: 5 | BR61: 5 | BS61: 4 | BT61: 5 | BU61: 5 | BV61: 5 | BX61: 5 | BY61: 5 | BZ61: Pass | CA61: Straight truck route only | CB61: Passed | CC61: Enrolled | CD61: Query Completed | CE61: 46037 | CF61: 46218 | CH61: Compliant | CJ61: Emma | CK61: Brown | CL61: OH0000107 | CM61: OH | CN61: CDL Holder | CO61: Emma Brown | CP61: 45915 | CQ61: 46645 | CR61: (614) 555-0113 | CS61: Dr. David Yang | CT61: 45915 | CU61: OH-ME-556547 | CV61: ME100009 | CW61: Physician Assistant | CX61: OH | CY61: Federal Motor Carrier Safety Regulations | DA61: No | DB61: No | DC61: No | DD61: No | DE61: No | DF61: No | DG61: Jane Doe | DH61: Sister | DI61: 555-555-5555 | DJ61: No | DK61: No | DL61: No | DM61: No | DN61: Yes - Appendectomy (2005) | DO61: 20/20 | DP61: 20/20 | DQ61: Pass | DR61: 118 | DS61: 78 | DT61: 72 | DU61: Normal | DV61: 45392 | DW61: 45394 | DX61: Negative | DY61: 45397 | DZ61: BOF Fleet Safety & Compliance Policy 2024 | EA61: Complete | EB61: 45413
A62: DRV-009 | B62: Emma Brown | C62: 630 Demo Street, Columbus, OH 43215 | D62: 206-555-0103 | E62: ***-**-0124 | F62: Chase | G62: 103 | H62: 999900210 | I62: Road Test Certificate | J62: VALID | K62: OH0000122 | L62: 46424 | M62: 46645 | N62: 46451 | P62: Black | Q62: Brown | R62: 5'-4" | S62: 144 | T62: F | U62: 30682 | V62: DRV-009.png | W62: Caucasian | X62: emmabrown@example.com | Y62: 630 Demo Street | Z62: Columbus | AA62: OH | AB62: 43215 | AC62: OH | AD62: Class B | AE62: 44602 | AF62: P | AG62: Corrective lenses | AH62: 45915 | AI62: MC-0091016 | AJ62: Dr. David Yang | AK62: ME100009 | AM62: Qualified | AN62: 46421 | AO62: 0 | AP62: 0 | AQ62: Corrective lenses | AR62: Clear | AS62: 45502 | AT62: Authorized to Work | AU62: U.S. Passport | AX62: 45502 | AY62: BOF Onboarding Team | AZ62: Complete | BB62: Individual/Sole Proprietor | BC62: SSN | BD62: ***-**-0124 | BF62: 45502 | BG62: Received | BH62: Savings | BI62: Direct Deposit | BJ62: 45502 | BK62: Verified | BL62: 45495 | BM62: J. Alvarez | BN62: Straight truck | BO62: Straight truck | BP62: Columbus, OH | BQ62: 5 | BR62: 5 | BS62: 4 | BT62: 5 | BU62: 5 | BV62: 5 | BX62: 5 | BY62: 5 | BZ62: Pass | CA62: Straight truck route only | CB62: Passed | CC62: Enrolled | CD62: Query Completed | CE62: 46037 | CF62: 46218 | CH62: Compliant | CJ62: Emma | CK62: Brown | CL62: OH0000108 | CM62: OH | CN62: CDL Holder | CO62: Emma Brown | CP62: 45915 | CQ62: 46645 | CR62: (614) 555-0113 | CS62: Dr. David Yang | CT62: 45915 | CU62: OH-ME-556547 | CV62: ME100009 | CW62: Physician Assistant | CX62: OH | CY62: Federal Motor Carrier Safety Regulations | DA62: No | DB62: No | DC62: No | DD62: No | DE62: No | DF62: No | DG62: Jane Doe | DH62: Sister | DI62: 555-555-5555 | DJ62: No | DK62: No | DL62: No | DM62: No | DN62: Yes - Appendectomy (2005) | DO62: 20/20 | DP62: 20/20 | DQ62: Pass | DR62: 118 | DS62: 78 | DT62: 72 | DU62: Normal | DV62: 45392 | DW62: 45394 | DX62: Negative | DY62: 45397 | DZ62: BOF Fleet Safety & Compliance Policy 2024 | EA62: Complete | EB62: 45413
A63: DRV-009 | B63: Emma Brown | C63: 630 Demo Street, Columbus, OH 43215 | D63: 206-555-0103 | E63: ***-**-0124 | F63: Chase | G63: 103 | H63: 999900210 | I63: Incident/Accident Report | J63: VALID | K63: OH0000096 | L63: 46424 | M63: 46645 | N63: 46451 | O63: No major incidents recorded in last 90 days. | P63: Black | Q63: Brown | R63: 5'-4" | S63: 144 | T63: F | U63: 30682 | V63: DRV-009.png | W63: Caucasian | X63: emmabrown@example.com | Y63: 630 Demo Street | Z63: Columbus | AA63: OH | AB63: 43215 | AC63: OH | AD63: Class B | AE63: 44602 | AF63: P | AG63: Corrective lenses | AH63: 45915 | AI63: MC-0091016 | AJ63: Dr. David Yang | AK63: ME100009 | AM63: Qualified | AN63: 46421 | AO63: 0 | AP63: 0 | AQ63: Corrective lenses | AR63: Clear | AS63: 45502 | AT63: Authorized to Work | AU63: U.S. Passport | AX63: 45502 | AY63: BOF Onboarding Team | AZ63: Complete | BB63: Individual/Sole Proprietor | BC63: SSN | BD63: ***-**-0124 | BF63: 45502 | BG63: Received | BH63: Savings | BI63: Direct Deposit | BJ63: 45502 | BK63: Verified | BL63: 45495 | BM63: J. Alvarez | BN63: Straight truck | BO63: Straight truck | BP63: Columbus, OH | BQ63: 5 | BR63: 5 | BS63: 4 | BT63: 5 | BU63: 5 | BV63: 5 | BX63: 5 | BY63: 5 | BZ63: Pass | CA63: Straight truck route only | CB63: Passed | CC63: Enrolled | CD63: Query Completed | CE63: 46037 | CF63: 46218 | CH63: Compliant | CJ63: Emma | CK63: Brown | CL63: OH0000109 | CM63: OH | CN63: CDL Holder | CO63: Emma Brown | CP63: 45915 | CQ63: 46645 | CR63: (614) 555-0113 | CS63: Dr. David Yang | CT63: 45915 | CU63: OH-ME-556547 | CV63: ME100009 | CW63: Physician Assistant | CX63: OH | CY63: Federal Motor Carrier Safety Regulations | DA63: No | DB63: No | DC63: No | DD63: No | DE63: No | DF63: No | DG63: Jane Doe | DH63: Sister | DI63: 555-555-5555 | DJ63: No | DK63: No | DL63: No | DM63: No | DN63: Yes - Appendectomy (2005) | DO63: 20/20 | DP63: 20/20 | DQ63: Pass | DR63: 118 | DS63: 78 | DT63: 72 | DU63: Normal | DV63: 45392 | DW63: 45394 | DX63: Negative | DY63: 45397 | DZ63: BOF Fleet Safety & Compliance Policy 2024 | EA63: Complete | EB63: 45413
A64: DRV-009 | B64: Emma Brown | C64: 630 Demo Street, Columbus, OH 43215 | D64: 206-555-0103 | E64: ***-**-0124 | F64: Chase | G64: 103 | H64: 999900210 | I64: Direct Deposit Form | J64: VALID | K64: OH0000140 | L64: 46424 | M64: 46645 | N64: 46451 | P64: Black | Q64: Brown | R64: 5'-4" | S64: 144 | T64: F | U64: 30682 | V64: DRV-009.png | W64: Caucasian | X64: emmabrown@example.com | Y64: 630 Demo Street | Z64: Columbus | AA64: OH | AB64: 43215 | AC64: OH | AD64: Class B | AE64: 44602 | AF64: P | AG64: Corrective lenses | AH64: 45915 | AI64: MC-0091016 | AJ64: Dr. David Yang | AK64: ME100009 | AM64: Qualified | AN64: 46421 | AO64: 0 | AP64: 0 | AQ64: Corrective lenses | AR64: Clear | AS64: 45502 | AT64: Authorized to Work | AU64: U.S. Passport | AX64: 45502 | AY64: BOF Onboarding Team | AZ64: Complete | BB64: Individual/Sole Proprietor | BC64: SSN | BD64: ***-**-0124 | BF64: 45502 | BG64: Received | BH64: Savings | BI64: Direct Deposit | BJ64: 45502 | BK64: Verified | BL64: 45495 | BM64: J. Alvarez | BN64: Straight truck | BO64: Straight truck | BP64: Columbus, OH | BQ64: 5 | BR64: 5 | BS64: 4 | BT64: 5 | BU64: 5 | BV64: 5 | BX64: 5 | BY64: 5 | BZ64: Pass | CA64: Straight truck route only | CB64: Passed | CC64: Enrolled | CD64: Query Completed | CE64: 46037 | CF64: 46218 | CH64: Compliant | CJ64: Emma | CK64: Brown | CL64: OH0000110 | CM64: OH | CN64: CDL Holder | CO64: Emma Brown | CP64: 45915 | CQ64: 46645 | CR64: (614) 555-0113 | CS64: Dr. David Yang | CT64: 45915 | CU64: OH-ME-556547 | CV64: ME100009 | CW64: Physician Assistant | CX64: OH | CY64: Federal Motor Carrier Safety Regulations | DA64: No | DB64: No | DC64: No | DD64: No | DE64: No | DF64: No | DG64: Jane Doe | DH64: Sister | DI64: 555-555-5555 | DJ64: No | DK64: No | DL64: No | DM64: No | DN64: Yes - Appendectomy (2005) | DO64: 20/20 | DP64: 20/20 | DQ64: Pass | DR64: 118 | DS64: 78 | DT64: 72 | DU64: Normal | DV64: 45392 | DW64: 45394 | DX64: Negative | DY64: 45397 | DZ64: BOF Fleet Safety & Compliance Policy 2024 | EA64: Complete | EB64: 45413
A65: DRV-010 | B65: Noah Wilson | C65: 130 Demo Street, Chicago, IL 60603 | D65: 582-555-0100 | E65: ***-**-0112 | F65: Chase | G65: 106 | H65: 999900208 | I65: CDL Summary | J65: VALID | K65: IL0000049 | L65: 46647 | M65: 46752 | N65: 46481 | P65: Black | Q65: Hazel | R65: 6'-3" | S65: 219 | T65: M | U65: 24108 | V65: DRV-010.png | W65: Black | X65: nwilson@example.com | Y65: 130 Demo Street | Z65: Chicago | AA65: IL | AB65: 60603 | AC65: IL | AD65: Class A | AE65: 44825 | AF65: H,N | AH65: 46022 | AI65: MC-0100911 | AJ65: Dr. Shannon Cole | AK65: ME100010 | AM65: Qualified | AN65: 46451 | AO65: 1 | AP65: 0 | AR65: Clear | AS65: 45523 | AT65: Authorized to Work | AU65: U.S. Passport | AX65: 45523 | AY65: BOF Onboarding Team | AZ65: Complete | BB65: Individual/Sole Proprietor | BC65: SSN | BD65: ***-**-0112 | BF65: 45523 | BG65: Received | BH65: Checking | BI65: Direct Deposit | BJ65: 45523 | BK65: Verified | BL65: 45516 | BM65: P. Mitchell | BN65: Sleeper tractor | BO65: 53 ft reefer | BP65: Chicago, IL | BQ65: 4 | BR65: 5 | BS65: 4 | BT65: 4 | BU65: 5 | BV65: 5 | BW65: 4 | BX65: 5 | BY65: 4 | BZ65: Pass | CB65: Passed | CC65: Enrolled | CD65: Query Completed | CE65: 46037 | CF65: 46218 | CH65: Compliant | CJ65: Noah | CK65: Wilson | CL65: IL0000049 | CM65: IL | CN65: CDL Holder | CO65: Noah Wilson | CP65: 46022 | CQ65: 46752 | CR65: (312) 555-0109 | CS65: Dr. Shannon Cole | CT65: 46022 | CU65: IL-ME-366300 | CV65: ME100010 | CW65: DO | CX65: IL | CY65: Federal Motor Carrier Safety Regulations | DA65: No | DB65: No | DC65: No | DD65: No | DE65: No | DF65: No | DG65: Jane Doe | DH65: Sister | DI65: 555-555-5555 | DJ65: No | DK65: No | DL65: No | DM65: No | DN65: Yes - Appendectomy (2005) | DO65: 20/20 | DP65: 20/20 | DQ65: Pass | DR65: 118 | DS65: 78 | DT65: 72 | DU65: Normal | DV65: 45392 | DW65: 45394 | DX65: Negative | DY65: 45397 | DZ65: BOF Fleet Safety & Compliance Policy 2024 | EA65: Complete | EB65: 45413
A66: DRV-010 | B66: Noah Wilson | C66: 130 Demo Street, Chicago, IL 60603 | D66: 582-555-0100 | E66: ***-**-0112 | F66: Chase | G66: 106 | H66: 999900208 | I66: Medical Certification | J66: VALID | K66: IL0000037 | L66: 46647 | M66: 46752 | N66: 46481 | P66: Black | Q66: Hazel | R66: 6'-3" | S66: 219 | T66: M | U66: 24108 | V66: DRV-010.png | W66: Black | X66: nwilson@example.com | Y66: 130 Demo Street | Z66: Chicago | AA66: IL | AB66: 60603 | AC66: IL | AD66: Class A | AE66: 44825 | AF66: H,N | AH66: 46022 | AI66: MC-0100911 | AJ66: Dr. Shannon Cole | AK66: ME100010 | AM66: Qualified | AN66: 46451 | AO66: 1 | AP66: 0 | AR66: Clear | AS66: 45523 | AT66: Authorized to Work | AU66: U.S. Passport | AX66: 45523 | AY66: BOF Onboarding Team | AZ66: Complete | BB66: Individual/Sole Proprietor | BC66: SSN | BD66: ***-**-0112 | BF66: 45523 | BG66: Received | BH66: Checking | BI66: Direct Deposit | BJ66: 45523 | BK66: Verified | BL66: 45516 | BM66: P. Mitchell | BN66: Sleeper tractor | BO66: 53 ft reefer | BP66: Chicago, IL | BQ66: 4 | BR66: 5 | BS66: 4 | BT66: 4 | BU66: 5 | BV66: 5 | BW66: 4 | BX66: 5 | BY66: 4 | BZ66: Pass | CB66: Passed | CC66: Enrolled | CD66: Query Completed | CE66: 46037 | CF66: 46218 | CH66: Compliant | CJ66: Noah | CK66: Wilson | CL66: IL0000050 | CM66: IL | CN66: CDL Holder | CO66: Noah Wilson | CP66: 46022 | CQ66: 46752 | CR66: (312) 555-0109 | CS66: Dr. Shannon Cole | CT66: 46022 | CU66: IL-ME-366300 | CV66: ME100010 | CW66: DO | CX66: IL | CY66: Federal Motor Carrier Safety Regulations | DA66: No | DB66: No | DC66: No | DD66: No | DE66: No | DF66: No | DG66: Jane Doe | DH66: Sister | DI66: 555-555-5555 | DJ66: No | DK66: No | DL66: No | DM66: No | DN66: Yes - Appendectomy (2005) | DO66: 20/20 | DP66: 20/20 | DQ66: Pass | DR66: 118 | DS66: 78 | DT66: 72 | DU66: Normal | DV66: 45392 | DW66: 45394 | DX66: Negative | DY66: 45397 | DZ66: BOF Fleet Safety & Compliance Policy 2024 | EA66: Complete | EB66: 45413
A67: DRV-010 | B67: Noah Wilson | C67: 130 Demo Street, Chicago, IL 60603 | D67: 582-555-0100 | E67: ***-**-0112 | F67: Chase | G67: 106 | H67: 999900208 | I67: MVR Background Report | J67: VALID | K67: IL0000060 | L67: 46647 | M67: 46752 | N67: 46481 | P67: Black | Q67: Hazel | R67: 6'-3" | S67: 219 | T67: M | U67: 24108 | V67: DRV-010.png | W67: Black | X67: nwilson@example.com | Y67: 130 Demo Street | Z67: Chicago | AA67: IL | AB67: 60603 | AC67: IL | AD67: Class A | AE67: 44825 | AF67: H,N | AH67: 46022 | AI67: MC-0100911 | AJ67: Dr. Shannon Cole | AK67: ME100010 | AM67: Qualified | AN67: 46451 | AO67: 1 | AP67: 0 | AR67: Clear | AS67: 45523 | AT67: Authorized to Work | AU67: U.S. Passport | AX67: 45523 | AY67: BOF Onboarding Team | AZ67: Complete | BB67: Individual/Sole Proprietor | BC67: SSN | BD67: ***-**-0112 | BF67: 45523 | BG67: Received | BH67: Checking | BI67: Direct Deposit | BJ67: 45523 | BK67: Verified | BL67: 45516 | BM67: P. Mitchell | BN67: Sleeper tractor | BO67: 53 ft reefer | BP67: Chicago, IL | BQ67: 4 | BR67: 5 | BS67: 4 | BT67: 4 | BU67: 5 | BV67: 5 | BW67: 4 | BX67: 5 | BY67: 4 | BZ67: Pass | CB67: Passed | CC67: Enrolled | CD67: Query Completed | CE67: 46037 | CF67: 46218 | CH67: Compliant | CJ67: Noah | CK67: Wilson | CL67: IL0000051 | CM67: IL | CN67: CDL Holder | CO67: Noah Wilson | CP67: 46022 | CQ67: 46752 | CR67: (312) 555-0109 | CS67: Dr. Shannon Cole | CT67: 46022 | CU67: IL-ME-366300 | CV67: ME100010 | CW67: DO | CX67: IL | CY67: Federal Motor Carrier Safety Regulations | DA67: No | DB67: No | DC67: No | DD67: No | DE67: No | DF67: No | DG67: Jane Doe | DH67: Sister | DI67: 555-555-5555 | DJ67: No | DK67: No | DL67: No | DM67: No | DN67: Yes - Appendectomy (2005) | DO67: 20/20 | DP67: 20/20 | DQ67: Pass | DR67: 118 | DS67: 78 | DT67: 72 | DU67: Normal | DV67: 45392 | DW67: 45394 | DX67: Negative | DY67: 45397 | DZ67: BOF Fleet Safety & Compliance Policy 2024 | EA67: Complete | EB67: 45413
A68: DRV-010 | B68: Noah Wilson | C68: 130 Demo Street, Chicago, IL 60603 | D68: 582-555-0100 | E68: ***-**-0112 | F68: Chase | G68: 106 | H68: 999900208 | I68: Driver Application | J68: VALID | K68: IL0000059 | L68: 46647 | M68: 46752 | N68: 46481 | P68: Black | Q68: Hazel | R68: 6'-3" | S68: 219 | T68: M | U68: 24108 | V68: DRV-010.png | W68: Black | X68: nwilson@example.com | Y68: 130 Demo Street | Z68: Chicago | AA68: IL | AB68: 60603 | AC68: IL | AD68: Class A | AE68: 44825 | AF68: H,N | AH68: 46022 | AI68: MC-0100911 | AJ68: Dr. Shannon Cole | AK68: ME100010 | AM68: Qualified | AN68: 46451 | AO68: 1 | AP68: 0 | AR68: Clear | AS68: 45523 | AT68: Authorized to Work | AU68: U.S. Passport | AX68: 45523 | AY68: BOF Onboarding Team | AZ68: Complete | BB68: Individual/Sole Proprietor | BC68: SSN | BD68: ***-**-0112 | BF68: 45523 | BG68: Received | BH68: Checking | BI68: Direct Deposit | BJ68: 45523 | BK68: Verified | BL68: 45516 | BM68: P. Mitchell | BN68: Sleeper tractor | BO68: 53 ft reefer | BP68: Chicago, IL | BQ68: 4 | BR68: 5 | BS68: 4 | BT68: 4 | BU68: 5 | BV68: 5 | BW68: 4 | BX68: 5 | BY68: 4 | BZ68: Pass | CB68: Passed | CC68: Enrolled | CD68: Query Completed | CE68: 46037 | CF68: 46218 | CH68: Compliant | CJ68: Noah | CK68: Wilson | CL68: IL0000052 | CM68: IL | CN68: CDL Holder | CO68: Noah Wilson | CP68: 46022 | CQ68: 46752 | CR68: (312) 555-0109 | CS68: Dr. Shannon Cole | CT68: 46022 | CU68: IL-ME-366300 | CV68: ME100010 | CW68: DO | CX68: IL | CY68: Federal Motor Carrier Safety Regulations | DA68: No | DB68: No | DC68: No | DD68: No | DE68: No | DF68: No | DG68: Jane Doe | DH68: Sister | DI68: 555-555-5555 | DJ68: No | DK68: No | DL68: No | DM68: No | DN68: Yes - Appendectomy (2005) | DO68: 20/20 | DP68: 20/20 | DQ68: Pass | DR68: 118 | DS68: 78 | DT68: 72 | DU68: Normal | DV68: 45392 | DW68: 45394 | DX68: Negative | DY68: 45397 | DZ68: BOF Fleet Safety & Compliance Policy 2024 | EA68: Complete | EB68: 45413
A69: DRV-010 | B69: Noah Wilson | C69: 130 Demo Street, Chicago, IL 60603 | D69: 582-555-0100 | E69: ***-**-0112 | F69: Chase | G69: 106 | H69: 999900208 | I69: Road Test Certificate | J69: VALID | K69: IL0000064 | L69: 46647 | M69: 46752 | N69: 46481 | P69: Black | Q69: Hazel | R69: 6'-3" | S69: 219 | T69: M | U69: 24108 | V69: DRV-010.png | W69: Black | X69: nwilson@example.com | Y69: 130 Demo Street | Z69: Chicago | AA69: IL | AB69: 60603 | AC69: IL | AD69: Class A | AE69: 44825 | AF69: H,N | AH69: 46022 | AI69: MC-0100911 | AJ69: Dr. Shannon Cole | AK69: ME100010 | AM69: Qualified | AN69: 46451 | AO69: 1 | AP69: 0 | AR69: Clear | AS69: 45523 | AT69: Authorized to Work | AU69: U.S. Passport | AX69: 45523 | AY69: BOF Onboarding Team | AZ69: Complete | BB69: Individual/Sole Proprietor | BC69: SSN | BD69: ***-**-0112 | BF69: 45523 | BG69: Received | BH69: Checking | BI69: Direct Deposit | BJ69: 45523 | BK69: Verified | BL69: 45516 | BM69: P. Mitchell | BN69: Sleeper tractor | BO69: 53 ft reefer | BP69: Chicago, IL | BQ69: 4 | BR69: 5 | BS69: 4 | BT69: 4 | BU69: 5 | BV69: 5 | BW69: 4 | BX69: 5 | BY69: 4 | BZ69: Pass | CB69: Passed | CC69: Enrolled | CD69: Query Completed | CE69: 46037 | CF69: 46218 | CH69: Compliant | CJ69: Noah | CK69: Wilson | CL69: IL0000053 | CM69: IL | CN69: CDL Holder | CO69: Noah Wilson | CP69: 46022 | CQ69: 46752 | CR69: (312) 555-0109 | CS69: Dr. Shannon Cole | CT69: 46022 | CU69: IL-ME-366300 | CV69: ME100010 | CW69: DO | CX69: IL | CY69: Federal Motor Carrier Safety Regulations | DA69: No | DB69: No | DC69: No | DD69: No | DE69: No | DF69: No | DG69: Jane Doe | DH69: Sister | DI69: 555-555-5555 | DJ69: No | DK69: No | DL69: No | DM69: No | DN69: Yes - Appendectomy (2005) | DO69: 20/20 | DP69: 20/20 | DQ69: Pass | DR69: 118 | DS69: 78 | DT69: 72 | DU69: Normal | DV69: 45392 | DW69: 45394 | DX69: Negative | DY69: 45397 | DZ69: BOF Fleet Safety & Compliance Policy 2024 | EA69: Complete | EB69: 45413
A70: DRV-010 | B70: Noah Wilson | C70: 130 Demo Street, Chicago, IL 60603 | D70: 582-555-0100 | E70: ***-**-0112 | F70: Chase | G70: 106 | H70: 999900208 | I70: Incident/Accident Report | J70: VALID | K70: IL0000063 | L70: 46647 | M70: 46752 | N70: 46481 | O70: No major incidents recorded in last 90 days. | P70: Black | Q70: Hazel | R70: 6'-3" | S70: 219 | T70: M | U70: 24108 | V70: DRV-010.png | W70: Black | X70: nwilson@example.com | Y70: 130 Demo Street | Z70: Chicago | AA70: IL | AB70: 60603 | AC70: IL | AD70: Class A | AE70: 44825 | AF70: H,N | AH70: 46022 | AI70: MC-0100911 | AJ70: Dr. Shannon Cole | AK70: ME100010 | AM70: Qualified | AN70: 46451 | AO70: 1 | AP70: 0 | AR70: Clear | AS70: 45523 | AT70: Authorized to Work | AU70: U.S. Passport | AX70: 45523 | AY70: BOF Onboarding Team | AZ70: Complete | BB70: Individual/Sole Proprietor | BC70: SSN | BD70: ***-**-0112 | BF70: 45523 | BG70: Received | BH70: Checking | BI70: Direct Deposit | BJ70: 45523 | BK70: Verified | BL70: 45516 | BM70: P. Mitchell | BN70: Sleeper tractor | BO70: 53 ft reefer | BP70: Chicago, IL | BQ70: 4 | BR70: 5 | BS70: 4 | BT70: 4 | BU70: 5 | BV70: 5 | BW70: 4 | BX70: 5 | BY70: 4 | BZ70: Pass | CB70: Passed | CC70: Enrolled | CD70: Query Completed | CE70: 46037 | CF70: 46218 | CH70: Compliant | CJ70: Noah | CK70: Wilson | CL70: IL0000054 | CM70: IL | CN70: CDL Holder | CO70: Noah Wilson | CP70: 46022 | CQ70: 46752 | CR70: (312) 555-0109 | CS70: Dr. Shannon Cole | CT70: 46022 | CU70: IL-ME-366300 | CV70: ME100010 | CW70: DO | CX70: IL | CY70: Federal Motor Carrier Safety Regulations | DA70: No | DB70: No | DC70: No | DD70: No | DE70: No | DF70: No | DG70: Jane Doe | DH70: Sister | DI70: 555-555-5555 | DJ70: No | DK70: No | DL70: No | DM70: No | DN70: Yes - Appendectomy (2005) | DO70: 20/20 | DP70: 20/20 | DQ70: Pass | DR70: 118 | DS70: 78 | DT70: 72 | DU70: Normal | DV70: 45392 | DW70: 45394 | DX70: Negative | DY70: 45397 | DZ70: BOF Fleet Safety & Compliance Policy 2024 | EA70: Complete | EB70: 45413
A71: DRV-010 | B71: Noah Wilson | C71: 130 Demo Street, Chicago, IL 60603 | D71: 582-555-0100 | E71: ***-**-0112 | F71: Chase | G71: 106 | H71: 999900208 | I71: Direct Deposit Form | J71: VALID | K71: IL0000038 | L71: 46647 | M71: 46752 | N71: 46481 | P71: Black | Q71: Hazel | R71: 6'-3" | S71: 219 | T71: M | U71: 24108 | V71: DRV-010.png | W71: Black | X71: nwilson@example.com | Y71: 130 Demo Street | Z71: Chicago | AA71: IL | AB71: 60603 | AC71: IL | AD71: Class A | AE71: 44825 | AF71: H,N | AH71: 46022 | AI71: MC-0100911 | AJ71: Dr. Shannon Cole | AK71: ME100010 | AM71: Qualified | AN71: 46451 | AO71: 1 | AP71: 0 | AR71: Clear | AS71: 45523 | AT71: Authorized to Work | AU71: U.S. Passport | AX71: 45523 | AY71: BOF Onboarding Team | AZ71: Complete | BB71: Individual/Sole Proprietor | BC71: SSN | BD71: ***-**-0112 | BF71: 45523 | BG71: Received | BH71: Checking | BI71: Direct Deposit | BJ71: 45523 | BK71: Verified | BL71: 45516 | BM71: P. Mitchell | BN71: Sleeper tractor | BO71: 53 ft reefer | BP71: Chicago, IL | BQ71: 4 | BR71: 5 | BS71: 4 | BT71: 4 | BU71: 5 | BV71: 5 | BW71: 4 | BX71: 5 | BY71: 4 | BZ71: Pass | CB71: Passed | CC71: Enrolled | CD71: Query Completed | CE71: 46037 | CF71: 46218 | CH71: Compliant | CJ71: Noah | CK71: Wilson | CL71: IL0000055 | CM71: IL | CN71: CDL Holder | CO71: Noah Wilson | CP71: 46022 | CQ71: 46752 | CR71: (312) 555-0109 | CS71: Dr. Shannon Cole | CT71: 46022 | CU71: IL-ME-366300 | CV71: ME100010 | CW71: DO | CX71: IL | CY71: Federal Motor Carrier Safety Regulations | DA71: No | DB71: No | DC71: No | DD71: No | DE71: No | DF71: No | DG71: Jane Doe | DH71: Sister | DI71: 555-555-5555 | DJ71: No | DK71: No | DL71: No | DM71: No | DN71: Yes - Appendectomy (2005) | DO71: 20/20 | DP71: 20/20 | DQ71: Pass | DR71: 118 | DS71: 78 | DT71: 72 | DU71: Normal | DV71: 45392 | DW71: 45394 | DX71: Negative | DY71: 45397 | DZ71: BOF Fleet Safety & Compliance Policy 2024 | EA71: Complete | EB71: 45413
A72: DRV-011 | B72: Olivia Lee | C72: 900 Demo Street, Atlanta, GA 30308 | D72: 337-555-0100 | E72: ***-**-0111 | F72: Bank of America | G72: 102 | H72: 999900209 | I72: CDL Summary | J72: VALID | K72: GA0000020 | L72: 46566 | M72: 46499 | N72: 46484 | P72: Brown | Q72: Hazel | R72: 5'-5" | S72: 148 | T72: F | U72: 24838 | V72: DRV-011.png | W72: South Asian | X72: olee@example.com | Y72: 900 Demo Street | Z72: Atlanta | AA72: GA | AB72: 30308 | AC72: GA | AD72: Class A | AE72: 44744 | AF72: N,T | AH72: 45769 | AI72: MC-0110314 | AJ72: Dr. Melissa Tran | AK72: ME100011 | AM72: Qualified | AN72: 46454 | AO72: 0 | AP72: 0 | AR72: Clear | AS72: 45551 | AT72: Authorized to Work | AU72: U.S. Passport | AX72: 45551 | AY72: BOF Onboarding Team | AZ72: Complete | BB72: Individual/Sole Proprietor | BC72: SSN | BD72: ***-**-0111 | BF72: 45551 | BG72: Received | BH72: Savings | BI72: Direct Deposit | BJ72: 45551 | BK72: Verified | BL72: 45544 | BM72: C. Nguyen | BN72: Day cab tractor | BO72: 53 ft dry van | BP72: Atlanta, GA | BQ72: 5 | BR72: 5 | BS72: 4 | BT72: 5 | BU72: 5 | BV72: 5 | BW72: 4 | BX72: 5 | BY72: 5 | BZ72: Pass | CB72: Passed | CC72: Enrolled | CD72: Query Completed | CE72: 46037 | CF72: 46218 | CH72: Compliant | CJ72: Olivia | CK72: Lee | CL72: GA0000020 | CM72: GA | CN72: CDL Holder | CO72: Olivia Lee | CP72: 45769 | CQ72: 46499 | CR72: (404) 555-0100 | CS72: Dr. Melissa Tran | CT72: 45769 | CU72: GA-ME-601747 | CV72: ME100011 | CW72: Advanced Practice Nurse | CX72: GA | CY72: Federal Motor Carrier Safety Regulations | DA72: No | DB72: No | DC72: No | DD72: No | DE72: No | DF72: No | DG72: Jane Doe | DH72: Sister | DI72: 555-555-5555 | DJ72: No | DK72: No | DL72: No | DM72: No | DN72: Yes - Appendectomy (2005) | DO72: 20/20 | DP72: 20/20 | DQ72: Pass | DR72: 118 | DS72: 78 | DT72: 72 | DU72: Normal | DV72: 45392 | DW72: 45394 | DX72: Negative | DY72: 45397 | DZ72: BOF Fleet Safety & Compliance Policy 2024 | EA72: Complete | EB72: 45413
A73: DRV-011 | B73: Olivia Lee | C73: 900 Demo Street, Atlanta, GA 30308 | D73: 337-555-0100 | E73: ***-**-0111 | F73: Bank of America | G73: 102 | H73: 999900209 | I73: Medical Certification | J73: VALID | K73: GA0000007 | L73: 46566 | M73: 46499 | N73: 46484 | P73: Brown | Q73: Hazel | R73: 5'-5" | S73: 148 | T73: F | U73: 24838 | V73: DRV-011.png | W73: South Asian | X73: olee@example.com | Y73: 900 Demo Street | Z73: Atlanta | AA73: GA | AB73: 30308 | AC73: GA | AD73: Class A | AE73: 44744 | AF73: N,T | AH73: 45769 | AI73: MC-0110314 | AJ73: Dr. Melissa Tran | AK73: ME100011 | AM73: Qualified | AN73: 46454 | AO73: 0 | AP73: 0 | AR73: Clear | AS73: 45551 | AT73: Authorized to Work | AU73: U.S. Passport | AX73: 45551 | AY73: BOF Onboarding Team | AZ73: Complete | BB73: Individual/Sole Proprietor | BC73: SSN | BD73: ***-**-0111 | BF73: 45551 | BG73: Received | BH73: Savings | BI73: Direct Deposit | BJ73: 45551 | BK73: Verified | BL73: 45544 | BM73: C. Nguyen | BN73: Day cab tractor | BO73: 53 ft dry van | BP73: Atlanta, GA | BQ73: 5 | BR73: 5 | BS73: 4 | BT73: 5 | BU73: 5 | BV73: 5 | BW73: 4 | BX73: 5 | BY73: 5 | BZ73: Pass | CB73: Passed | CC73: Enrolled | CD73: Query Completed | CE73: 46037 | CF73: 46218 | CH73: Compliant | CJ73: Olivia | CK73: Lee | CL73: GA0000021 | CM73: GA | CN73: CDL Holder | CO73: Olivia Lee | CP73: 45769 | CQ73: 46499 | CR73: (404) 555-0100 | CS73: Dr. Melissa Tran | CT73: 45769 | CU73: GA-ME-601747 | CV73: ME100011 | CW73: Advanced Practice Nurse | CX73: GA | CY73: Federal Motor Carrier Safety Regulations | DA73: No | DB73: No | DC73: No | DD73: No | DE73: No | DF73: No | DG73: Jane Doe | DH73: Sister | DI73: 555-555-5555 | DJ73: No | DK73: No | DL73: No | DM73: No | DN73: Yes - Appendectomy (2005) | DO73: 20/20 | DP73: 20/20 | DQ73: Pass | DR73: 118 | DS73: 78 | DT73: 72 | DU73: Normal | DV73: 45392 | DW73: 45394 | DX73: Negative | DY73: 45397 | DZ73: BOF Fleet Safety & Compliance Policy 2024 | EA73: Complete | EB73: 45413
A74: DRV-011 | B74: Olivia Lee | C74: 900 Demo Street, Atlanta, GA 30308 | D74: 337-555-0100 | E74: ***-**-0111 | F74: Bank of America | G74: 102 | H74: 999900209 | I74: MVR Background Report | J74: VALID | K74: GA0000009 | L74: 46566 | M74: 46499 | N74: 46484 | P74: Brown | Q74: Hazel | R74: 5'-5" | S74: 148 | T74: F | U74: 24838 | V74: DRV-011.png | W74: South Asian | X74: olee@example.com | Y74: 900 Demo Street | Z74: Atlanta | AA74: GA | AB74: 30308 | AC74: GA | AD74: Class A | AE74: 44744 | AF74: N,T | AH74: 45769 | AI74: MC-0110314 | AJ74: Dr. Melissa Tran | AK74: ME100011 | AM74: Qualified | AN74: 46454 | AO74: 0 | AP74: 0 | AR74: Clear | AS74: 45551 | AT74: Authorized to Work | AU74: U.S. Passport | AX74: 45551 | AY74: BOF Onboarding Team | AZ74: Complete | BB74: Individual/Sole Proprietor | BC74: SSN | BD74: ***-**-0111 | BF74: 45551 | BG74: Received | BH74: Savings | BI74: Direct Deposit | BJ74: 45551 | BK74: Verified | BL74: 45544 | BM74: C. Nguyen | BN74: Day cab tractor | BO74: 53 ft dry van | BP74: Atlanta, GA | BQ74: 5 | BR74: 5 | BS74: 4 | BT74: 5 | BU74: 5 | BV74: 5 | BW74: 4 | BX74: 5 | BY74: 5 | BZ74: Pass | CB74: Passed | CC74: Enrolled | CD74: Query Completed | CE74: 46037 | CF74: 46218 | CH74: Compliant | CJ74: Olivia | CK74: Lee | CL74: GA0000022 | CM74: GA | CN74: CDL Holder | CO74: Olivia Lee | CP74: 45769 | CQ74: 46499 | CR74: (404) 555-0100 | CS74: Dr. Melissa Tran | CT74: 45769 | CU74: GA-ME-601747 | CV74: ME100011 | CW74: Advanced Practice Nurse | CX74: GA | CY74: Federal Motor Carrier Safety Regulations | DA74: No | DB74: No | DC74: No | DD74: No | DE74: No | DF74: No | DG74: Jane Doe | DH74: Sister | DI74: 555-555-5555 | DJ74: No | DK74: No | DL74: No | DM74: No | DN74: Yes - Appendectomy (2005) | DO74: 20/20 | DP74: 20/20 | DQ74: Pass | DR74: 118 | DS74: 78 | DT74: 72 | DU74: Normal | DV74: 45392 | DW74: 45394 | DX74: Negative | DY74: 45397 | DZ74: BOF Fleet Safety & Compliance Policy 2024 | EA74: Complete | EB74: 45413
A75: DRV-011 | B75: Olivia Lee | C75: 900 Demo Street, Atlanta, GA 30308 | D75: 337-555-0100 | E75: ***-**-0111 | F75: Bank of America | G75: 102 | H75: 999900209 | I75: Driver Application | J75: VALID | K75: GA0000010 | L75: 46566 | M75: 46499 | N75: 46484 | P75: Brown | Q75: Hazel | R75: 5'-5" | S75: 148 | T75: F | U75: 24838 | V75: DRV-011.png | W75: South Asian | X75: olee@example.com | Y75: 900 Demo Street | Z75: Atlanta | AA75: GA | AB75: 30308 | AC75: GA | AD75: Class A | AE75: 44744 | AF75: N,T | AH75: 45769 | AI75: MC-0110314 | AJ75: Dr. Melissa Tran | AK75: ME100011 | AM75: Qualified | AN75: 46454 | AO75: 0 | AP75: 0 | AR75: Clear | AS75: 45551 | AT75: Authorized to Work | AU75: U.S. Passport | AX75: 45551 | AY75: BOF Onboarding Team | AZ75: Complete | BB75: Individual/Sole Proprietor | BC75: SSN | BD75: ***-**-0111 | BF75: 45551 | BG75: Received | BH75: Savings | BI75: Direct Deposit | BJ75: 45551 | BK75: Verified | BL75: 45544 | BM75: C. Nguyen | BN75: Day cab tractor | BO75: 53 ft dry van | BP75: Atlanta, GA | BQ75: 5 | BR75: 5 | BS75: 4 | BT75: 5 | BU75: 5 | BV75: 5 | BW75: 4 | BX75: 5 | BY75: 5 | BZ75: Pass | CB75: Passed | CC75: Enrolled | CD75: Query Completed | CE75: 46037 | CF75: 46218 | CH75: Compliant | CJ75: Olivia | CK75: Lee | CL75: GA0000023 | CM75: GA | CN75: CDL Holder | CO75: Olivia Lee | CP75: 45769 | CQ75: 46499 | CR75: (404) 555-0100 | CS75: Dr. Melissa Tran | CT75: 45769 | CU75: GA-ME-601747 | CV75: ME100011 | CW75: Advanced Practice Nurse | CX75: GA | CY75: Federal Motor Carrier Safety Regulations | DA75: No | DB75: No | DC75: No | DD75: No | DE75: No | DF75: No | DG75: Jane Doe | DH75: Sister | DI75: 555-555-5555 | DJ75: No | DK75: No | DL75: No | DM75: No | DN75: Yes - Appendectomy (2005) | DO75: 20/20 | DP75: 20/20 | DQ75: Pass | DR75: 118 | DS75: 78 | DT75: 72 | DU75: Normal | DV75: 45392 | DW75: 45394 | DX75: Negative | DY75: 45397 | DZ75: BOF Fleet Safety & Compliance Policy 2024 | EA75: Complete | EB75: 45413
A76: DRV-011 | B76: Olivia Lee | C76: 900 Demo Street, Atlanta, GA 30308 | D76: 337-555-0100 | E76: ***-**-0111 | F76: Bank of America | G76: 102 | H76: 999900209 | I76: Road Test Certificate | J76: VALID | K76: GA0000012 | L76: 46566 | M76: 46499 | N76: 46484 | P76: Brown | Q76: Hazel | R76: 5'-5" | S76: 148 | T76: F | U76: 24838 | V76: DRV-011.png | W76: South Asian | X76: olee@example.com | Y76: 900 Demo Street | Z76: Atlanta | AA76: GA | AB76: 30308 | AC76: GA | AD76: Class A | AE76: 44744 | AF76: N,T | AH76: 45769 | AI76: MC-0110314 | AJ76: Dr. Melissa Tran | AK76: ME100011 | AM76: Qualified | AN76: 46454 | AO76: 0 | AP76: 0 | AR76: Clear | AS76: 45551 | AT76: Authorized to Work | AU76: U.S. Passport | AX76: 45551 | AY76: BOF Onboarding Team | AZ76: Complete | BB76: Individual/Sole Proprietor | BC76: SSN | BD76: ***-**-0111 | BF76: 45551 | BG76: Received | BH76: Savings | BI76: Direct Deposit | BJ76: 45551 | BK76: Verified | BL76: 45544 | BM76: C. Nguyen | BN76: Day cab tractor | BO76: 53 ft dry van | BP76: Atlanta, GA | BQ76: 5 | BR76: 5 | BS76: 4 | BT76: 5 | BU76: 5 | BV76: 5 | BW76: 4 | BX76: 5 | BY76: 5 | BZ76: Pass | CB76: Passed | CC76: Enrolled | CD76: Query Completed | CE76: 46037 | CF76: 46218 | CH76: Compliant | CJ76: Olivia | CK76: Lee | CL76: GA0000024 | CM76: GA | CN76: CDL Holder | CO76: Olivia Lee | CP76: 45769 | CQ76: 46499 | CR76: (404) 555-0100 | CS76: Dr. Melissa Tran | CT76: 45769 | CU76: GA-ME-601747 | CV76: ME100011 | CW76: Advanced Practice Nurse | CX76: GA | CY76: Federal Motor Carrier Safety Regulations | DA76: No | DB76: No | DC76: No | DD76: No | DE76: No | DF76: No | DG76: Jane Doe | DH76: Sister | DI76: 555-555-5555 | DJ76: No | DK76: No | DL76: No | DM76: No | DN76: Yes - Appendectomy (2005) | DO76: 20/20 | DP76: 20/20 | DQ76: Pass | DR76: 118 | DS76: 78 | DT76: 72 | DU76: Normal | DV76: 45392 | DW76: 45394 | DX76: Negative | DY76: 45397 | DZ76: BOF Fleet Safety & Compliance Policy 2024 | EA76: Complete | EB76: 45413
A77: DRV-011 | B77: Olivia Lee | C77: 900 Demo Street, Atlanta, GA 30308 | D77: 337-555-0100 | E77: ***-**-0111 | F77: Bank of America | G77: 102 | H77: 999900209 | I77: Incident/Accident Report | J77: VALID | K77: GA0000008 | L77: 46566 | M77: 46499 | N77: 46484 | O77: No major incidents recorded in last 90 days. | P77: Brown | Q77: Hazel | R77: 5'-5" | S77: 148 | T77: F | U77: 24838 | V77: DRV-011.png | W77: South Asian | X77: olee@example.com | Y77: 900 Demo Street | Z77: Atlanta | AA77: GA | AB77: 30308 | AC77: GA | AD77: Class A | AE77: 44744 | AF77: N,T | AH77: 45769 | AI77: MC-0110314 | AJ77: Dr. Melissa Tran | AK77: ME100011 | AM77: Qualified | AN77: 46454 | AO77: 0 | AP77: 0 | AR77: Clear | AS77: 45551 | AT77: Authorized to Work | AU77: U.S. Passport | AX77: 45551 | AY77: BOF Onboarding Team | AZ77: Complete | BB77: Individual/Sole Proprietor | BC77: SSN | BD77: ***-**-0111 | BF77: 45551 | BG77: Received | BH77: Savings | BI77: Direct Deposit | BJ77: 45551 | BK77: Verified | BL77: 45544 | BM77: C. Nguyen | BN77: Day cab tractor | BO77: 53 ft dry van | BP77: Atlanta, GA | BQ77: 5 | BR77: 5 | BS77: 4 | BT77: 5 | BU77: 5 | BV77: 5 | BW77: 4 | BX77: 5 | BY77: 5 | BZ77: Pass | CB77: Passed | CC77: Enrolled | CD77: Query Completed | CE77: 46037 | CF77: 46218 | CH77: Compliant | CJ77: Olivia | CK77: Lee | CL77: GA0000025 | CM77: GA | CN77: CDL Holder | CO77: Olivia Lee | CP77: 45769 | CQ77: 46499 | CR77: (404) 555-0100 | CS77: Dr. Melissa Tran | CT77: 45769 | CU77: GA-ME-601747 | CV77: ME100011 | CW77: Advanced Practice Nurse | CX77: GA | CY77: Federal Motor Carrier Safety Regulations | DA77: No | DB77: No | DC77: No | DD77: No | DE77: No | DF77: No | DG77: Jane Doe | DH77: Sister | DI77: 555-555-5555 | DJ77: No | DK77: No | DL77: No | DM77: No | DN77: Yes - Appendectomy (2005) | DO77: 20/20 | DP77: 20/20 | DQ77: Pass | DR77: 118 | DS77: 78 | DT77: 72 | DU77: Normal | DV77: 45392 | DW77: 45394 | DX77: Negative | DY77: 45397 | DZ77: BOF Fleet Safety & Compliance Policy 2024 | EA77: Complete | EB77: 45413
A78: DRV-011 | B78: Olivia Lee | C78: 900 Demo Street, Atlanta, GA 30308 | D78: 337-555-0100 | E78: ***-**-0111 | F78: Bank of America | G78: 102 | H78: 999900209 | I78: Direct Deposit Form | J78: VALID | K78: GA0000003 | L78: 46566 | M78: 46499 | N78: 46484 | P78: Brown | Q78: Hazel | R78: 5'-5" | S78: 148 | T78: F | U78: 24838 | V78: DRV-011.png | W78: South Asian | X78: olee@example.com | Y78: 900 Demo Street | Z78: Atlanta | AA78: GA | AB78: 30308 | AC78: GA | AD78: Class A | AE78: 44744 | AF78: N,T | AH78: 45769 | AI78: MC-0110314 | AJ78: Dr. Melissa Tran | AK78: ME100011 | AM78: Qualified | AN78: 46454 | AO78: 0 | AP78: 0 | AR78: Clear | AS78: 45551 | AT78: Authorized to Work | AU78: U.S. Passport | AX78: 45551 | AY78: BOF Onboarding Team | AZ78: Complete | BB78: Individual/Sole Proprietor | BC78: SSN | BD78: ***-**-0111 | BF78: 45551 | BG78: Received | BH78: Savings | BI78: Direct Deposit | BJ78: 45551 | BK78: Verified | BL78: 45544 | BM78: C. Nguyen | BN78: Day cab tractor | BO78: 53 ft dry van | BP78: Atlanta, GA | BQ78: 5 | BR78: 5 | BS78: 4 | BT78: 5 | BU78: 5 | BV78: 5 | BW78: 4 | BX78: 5 | BY78: 5 | BZ78: Pass | CB78: Passed | CC78: Enrolled | CD78: Query Completed | CE78: 46037 | CF78: 46218 | CH78: Compliant | CJ78: Olivia | CK78: Lee | CL78: GA0000026 | CM78: GA | CN78: CDL Holder | CO78: Olivia Lee | CP78: 45769 | CQ78: 46499 | CR78: (404) 555-0100 | CS78: Dr. Melissa Tran | CT78: 45769 | CU78: GA-ME-601747 | CV78: ME100011 | CW78: Advanced Practice Nurse | CX78: GA | CY78: Federal Motor Carrier Safety Regulations | DA78: No | DB78: No | DC78: No | DD78: No | DE78: No | DF78: No | DG78: Jane Doe | DH78: Sister | DI78: 555-555-5555 | DJ78: No | DK78: No | DL78: No | DM78: No | DN78: Yes - Appendectomy (2005) | DO78: 20/20 | DP78: 20/20 | DQ78: Pass | DR78: 118 | DS78: 78 | DT78: 72 | DU78: Normal | DV78: 45392 | DW78: 45394 | DX78: Negative | DY78: 45397 | DZ78: BOF Fleet Safety & Compliance Policy 2024 | EA78: Complete | EB78: 45413
A79: DRV-012 | B79: Robert Johnson | C79: 920 Demo Street, Chicago, IL 60605 | D79: 618-555-0101 | E79: ***-**-0114 | F79: Wells Fargo | G79: 109 | H79: 999900205 | I79: CDL Summary | J79: VALID | K79: IL0000030 | L79: 46706 | M79: 46609 | N79: 46519 | P79: Blonde | Q79: Green | R79: 6'-1" | S79: 209 | T79: M | U79: 32874 | V79: DRV-012.png | W79: Caucasian | X79: robertjohnson@example.com | Y79: 920 Demo Street | Z79: Chicago | AA79: IL | AB79: 60605 | AC79: IL | AD79: Class A | AE79: 44884 | AG79: Corrective lenses | AH79: 45879 | AI79: MC-0120411 | AJ79: Dr. Victor Reed | AK79: ME100012 | AL79: Corrective lenses | AM79: Qualified | AN79: 46489 | AO79: 1 | AP79: 1 | AQ79: Corrective lenses | AR79: Reviewed - Clear to Drive | AS79: 45579 | AT79: Authorized to Work | AU79: U.S. Passport | AX79: 45579 | AY79: BOF Onboarding Team | AZ79: Complete | BB79: Individual/Sole Proprietor | BC79: SSN | BD79: ***-**-0114 | BF79: 45579 | BG79: Received | BH79: Checking | BI79: Direct Deposit | BJ79: 45579 | BK79: Verified | BL79: 45572 | BM79: E. Barnes | BN79: Sleeper tractor | BO79: 53 ft dry van | BP79: Chicago, IL | BQ79: 4 | BR79: 4 | BS79: 4 | BT79: 4 | BU79: 4 | BV79: 4 | BW79: 4 | BX79: 4 | BY79: 4 | BZ79: Pass | CA79: Corrective lenses | CB79: Passed | CC79: Enrolled | CD79: Query Completed | CE79: 46037 | CF79: 46218 | CH79: Compliant | CJ79: Robert | CK79: Johnson | CL79: IL0000030 | CM79: IL | CN79: CDL Holder | CO79: Robert Johnson | CP79: 45879 | CQ79: 46609 | CR79: (312) 555-0103 | CS79: Dr. Victor Reed | CT79: 45879 | CU79: IL-ME-120233 | CV79: ME100012 | CW79: DO | CX79: IL | CY79: Federal Motor Carrier Safety Regulations | DA79: No | DB79: No | DC79: No | DD79: No | DE79: Yes | DF79: No | DG79: Jane Doe | DH79: Sister | DI79: 555-555-5555 | DJ79: No | DK79: No | DL79: No | DM79: No | DN79: Yes - Appendectomy (2005) | DO79: 20/20 | DP79: 20/20 | DQ79: Pass | DR79: 118 | DS79: 78 | DT79: 72 | DU79: Normal | DV79: 45392 | DW79: 45394 | DX79: Negative | DY79: 45397 | DZ79: BOF Fleet Safety & Compliance Policy 2024 | EA79: Complete | EB79: 45413
A80: DRV-012 | B80: Robert Johnson | C80: 920 Demo Street, Chicago, IL 60605 | D80: 618-555-0101 | E80: ***-**-0114 | F80: Wells Fargo | G80: 109 | H80: 999900205 | I80: Medical Certification | J80: VALID | K80: IL0000062 | L80: 46706 | M80: 46609 | N80: 46519 | P80: Blonde | Q80: Green | R80: 6'-1" | S80: 209 | T80: M | U80: 32874 | V80: DRV-012.png | W80: Caucasian | X80: robertjohnson@example.com | Y80: 920 Demo Street | Z80: Chicago | AA80: IL | AB80: 60605 | AC80: IL | AD80: Class A | AE80: 44884 | AG80: Corrective lenses | AH80: 45879 | AI80: MC-0120411 | AJ80: Dr. Victor Reed | AK80: ME100012 | AL80: Corrective lenses | AM80: Qualified | AN80: 46489 | AO80: 1 | AP80: 1 | AQ80: Corrective lenses | AR80: Reviewed - Clear to Drive | AS80: 45579 | AT80: Authorized to Work | AU80: U.S. Passport | AX80: 45579 | AY80: BOF Onboarding Team | AZ80: Complete | BB80: Individual/Sole Proprietor | BC80: SSN | BD80: ***-**-0114 | BF80: 45579 | BG80: Received | BH80: Checking | BI80: Direct Deposit | BJ80: 45579 | BK80: Verified | BL80: 45572 | BM80: E. Barnes | BN80: Sleeper tractor | BO80: 53 ft dry van | BP80: Chicago, IL | BQ80: 4 | BR80: 4 | BS80: 4 | BT80: 4 | BU80: 4 | BV80: 4 | BW80: 4 | BX80: 4 | BY80: 4 | BZ80: Pass | CA80: Corrective lenses | CB80: Passed | CC80: Enrolled | CD80: Query Completed | CE80: 46037 | CF80: 46218 | CH80: Compliant | CJ80: Robert | CK80: Johnson | CL80: IL0000031 | CM80: IL | CN80: CDL Holder | CO80: Robert Johnson | CP80: 45879 | CQ80: 46609 | CR80: (312) 555-0103 | CS80: Dr. Victor Reed | CT80: 45879 | CU80: IL-ME-120233 | CV80: ME100012 | CW80: DO | CX80: IL | CY80: Federal Motor Carrier Safety Regulations | DA80: No | DB80: No | DC80: No | DD80: No | DE80: Yes | DF80: No | DG80: Jane Doe | DH80: Sister | DI80: 555-555-5555 | DJ80: No | DK80: No | DL80: No | DM80: No | DN80: Yes - Appendectomy (2005) | DO80: 20/20 | DP80: 20/20 | DQ80: Pass | DR80: 118 | DS80: 78 | DT80: 72 | DU80: Normal | DV80: 45392 | DW80: 45394 | DX80: Negative | DY80: 45397 | DZ80: BOF Fleet Safety & Compliance Policy 2024 | EA80: Complete | EB80: 45413
A81: DRV-012 | B81: Robert Johnson | C81: 920 Demo Street, Chicago, IL 60605 | D81: 618-555-0101 | E81: ***-**-0114 | F81: Wells Fargo | G81: 109 | H81: 999900205 | I81: MVR Background Report | J81: VALID | K81: IL0000040 | L81: 46706 | M81: 46609 | N81: 46519 | P81: Blonde | Q81: Green | R81: 6'-1" | S81: 209 | T81: M | U81: 32874 | V81: DRV-012.png | W81: Caucasian | X81: robertjohnson@example.com | Y81: 920 Demo Street | Z81: Chicago | AA81: IL | AB81: 60605 | AC81: IL | AD81: Class A | AE81: 44884 | AG81: Corrective lenses | AH81: 45879 | AI81: MC-0120411 | AJ81: Dr. Victor Reed | AK81: ME100012 | AL81: Corrective lenses | AM81: Qualified | AN81: 46489 | AO81: 1 | AP81: 1 | AQ81: Corrective lenses | AR81: Reviewed - Clear to Drive | AS81: 45579 | AT81: Authorized to Work | AU81: U.S. Passport | AX81: 45579 | AY81: BOF Onboarding Team | AZ81: Complete | BB81: Individual/Sole Proprietor | BC81: SSN | BD81: ***-**-0114 | BF81: 45579 | BG81: Received | BH81: Checking | BI81: Direct Deposit | BJ81: 45579 | BK81: Verified | BL81: 45572 | BM81: E. Barnes | BN81: Sleeper tractor | BO81: 53 ft dry van | BP81: Chicago, IL | BQ81: 4 | BR81: 4 | BS81: 4 | BT81: 4 | BU81: 4 | BV81: 4 | BW81: 4 | BX81: 4 | BY81: 4 | BZ81: Pass | CA81: Corrective lenses | CB81: Passed | CC81: Enrolled | CD81: Query Completed | CE81: 46037 | CF81: 46218 | CH81: Compliant | CJ81: Robert | CK81: Johnson | CL81: IL0000032 | CM81: IL | CN81: CDL Holder | CO81: Robert Johnson | CP81: 45879 | CQ81: 46609 | CR81: (312) 555-0103 | CS81: Dr. Victor Reed | CT81: 45879 | CU81: IL-ME-120233 | CV81: ME100012 | CW81: DO | CX81: IL | CY81: Federal Motor Carrier Safety Regulations | DA81: No | DB81: No | DC81: No | DD81: No | DE81: Yes | DF81: No | DG81: Jane Doe | DH81: Sister | DI81: 555-555-5555 | DJ81: No | DK81: No | DL81: No | DM81: No | DN81: Yes - Appendectomy (2005) | DO81: 20/20 | DP81: 20/20 | DQ81: Pass | DR81: 118 | DS81: 78 | DT81: 72 | DU81: Normal | DV81: 45392 | DW81: 45394 | DX81: Negative | DY81: 45397 | DZ81: BOF Fleet Safety & Compliance Policy 2024 | EA81: Complete | EB81: 45413
A82: DRV-012 | B82: Robert Johnson | C82: 920 Demo Street, Chicago, IL 60605 | D82: 618-555-0101 | E82: ***-**-0114 | F82: Wells Fargo | G82: 109 | H82: 999900205 | I82: Driver Application | J82: VALID | K82: IL0000057 | L82: 46706 | M82: 46609 | N82: 46519 | P82: Blonde | Q82: Green | R82: 6'-1" | S82: 209 | T82: M | U82: 32874 | V82: DRV-012.png | W82: Caucasian | X82: robertjohnson@example.com | Y82: 920 Demo Street | Z82: Chicago | AA82: IL | AB82: 60605 | AC82: IL | AD82: Class A | AE82: 44884 | AG82: Corrective lenses | AH82: 45879 | AI82: MC-0120411 | AJ82: Dr. Victor Reed | AK82: ME100012 | AL82: Corrective lenses | AM82: Qualified | AN82: 46489 | AO82: 1 | AP82: 1 | AQ82: Corrective lenses | AR82: Reviewed - Clear to Drive | AS82: 45579 | AT82: Authorized to Work | AU82: U.S. Passport | AX82: 45579 | AY82: BOF Onboarding Team | AZ82: Complete | BB82: Individual/Sole Proprietor | BC82: SSN | BD82: ***-**-0114 | BF82: 45579 | BG82: Received | BH82: Checking | BI82: Direct Deposit | BJ82: 45579 | BK82: Verified | BL82: 45572 | BM82: E. Barnes | BN82: Sleeper tractor | BO82: 53 ft dry van | BP82: Chicago, IL | BQ82: 4 | BR82: 4 | BS82: 4 | BT82: 4 | BU82: 4 | BV82: 4 | BW82: 4 | BX82: 4 | BY82: 4 | BZ82: Pass | CA82: Corrective lenses | CB82: Passed | CC82: Enrolled | CD82: Query Completed | CE82: 46037 | CF82: 46218 | CH82: Compliant | CJ82: Robert | CK82: Johnson | CL82: IL0000033 | CM82: IL | CN82: CDL Holder | CO82: Robert Johnson | CP82: 45879 | CQ82: 46609 | CR82: (312) 555-0103 | CS82: Dr. Victor Reed | CT82: 45879 | CU82: IL-ME-120233 | CV82: ME100012 | CW82: DO | CX82: IL | CY82: Federal Motor Carrier Safety Regulations | DA82: No | DB82: No | DC82: No | DD82: No | DE82: Yes | DF82: No | DG82: Jane Doe | DH82: Sister | DI82: 555-555-5555 | DJ82: No | DK82: No | DL82: No | DM82: No | DN82: Yes - Appendectomy (2005) | DO82: 20/20 | DP82: 20/20 | DQ82: Pass | DR82: 118 | DS82: 78 | DT82: 72 | DU82: Normal | DV82: 45392 | DW82: 45394 | DX82: Negative | DY82: 45397 | DZ82: BOF Fleet Safety & Compliance Policy 2024 | EA82: Complete | EB82: 45413
A83: DRV-012 | B83: Robert Johnson | C83: 920 Demo Street, Chicago, IL 60605 | D83: 618-555-0101 | E83: ***-**-0114 | F83: Wells Fargo | G83: 109 | H83: 999900205 | I83: Road Test Certificate | J83: VALID | K83: IL0000066 | L83: 46706 | M83: 46609 | N83: 46519 | P83: Blonde | Q83: Green | R83: 6'-1" | S83: 209 | T83: M | U83: 32874 | V83: DRV-012.png | W83: Caucasian | X83: robertjohnson@example.com | Y83: 920 Demo Street | Z83: Chicago | AA83: IL | AB83: 60605 | AC83: IL | AD83: Class A | AE83: 44884 | AG83: Corrective lenses | AH83: 45879 | AI83: MC-0120411 | AJ83: Dr. Victor Reed | AK83: ME100012 | AL83: Corrective lenses | AM83: Qualified | AN83: 46489 | AO83: 1 | AP83: 1 | AQ83: Corrective lenses | AR83: Reviewed - Clear to Drive | AS83: 45579 | AT83: Authorized to Work | AU83: U.S. Passport | AX83: 45579 | AY83: BOF Onboarding Team | AZ83: Complete | BB83: Individual/Sole Proprietor | BC83: SSN | BD83: ***-**-0114 | BF83: 45579 | BG83: Received | BH83: Checking | BI83: Direct Deposit | BJ83: 45579 | BK83: Verified | BL83: 45572 | BM83: E. Barnes | BN83: Sleeper tractor | BO83: 53 ft dry van | BP83: Chicago, IL | BQ83: 4 | BR83: 4 | BS83: 4 | BT83: 4 | BU83: 4 | BV83: 4 | BW83: 4 | BX83: 4 | BY83: 4 | BZ83: Pass | CA83: Corrective lenses | CB83: Passed | CC83: Enrolled | CD83: Query Completed | CE83: 46037 | CF83: 46218 | CH83: Compliant | CJ83: Robert | CK83: Johnson | CL83: IL0000034 | CM83: IL | CN83: CDL Holder | CO83: Robert Johnson | CP83: 45879 | CQ83: 46609 | CR83: (312) 555-0103 | CS83: Dr. Victor Reed | CT83: 45879 | CU83: IL-ME-120233 | CV83: ME100012 | CW83: DO | CX83: IL | CY83: Federal Motor Carrier Safety Regulations | DA83: No | DB83: No | DC83: No | DD83: No | DE83: Yes | DF83: No | DG83: Jane Doe | DH83: Sister | DI83: 555-555-5555 | DJ83: No | DK83: No | DL83: No | DM83: No | DN83: Yes - Appendectomy (2005) | DO83: 20/20 | DP83: 20/20 | DQ83: Pass | DR83: 118 | DS83: 78 | DT83: 72 | DU83: Normal | DV83: 45392 | DW83: 45394 | DX83: Negative | DY83: 45397 | DZ83: BOF Fleet Safety & Compliance Policy 2024 | EA83: Complete | EB83: 45413
A84: DRV-012 | B84: Robert Johnson | C84: 920 Demo Street, Chicago, IL 60605 | D84: 618-555-0101 | E84: ***-**-0114 | F84: Wells Fargo | G84: 109 | H84: 999900205 | I84: Incident/Accident Report | J84: VALID | K84: IL0000048 | L84: 46706 | M84: 46609 | N84: 46519 | O84: Load L-512: Seal broken upon arrival. Theft suspected. | P84: Blonde | Q84: Green | R84: 6'-1" | S84: 209 | T84: M | U84: 32874 | V84: DRV-012.png | W84: Caucasian | X84: robertjohnson@example.com | Y84: 920 Demo Street | Z84: Chicago | AA84: IL | AB84: 60605 | AC84: IL | AD84: Class A | AE84: 44884 | AG84: Corrective lenses | AH84: 45879 | AI84: MC-0120411 | AJ84: Dr. Victor Reed | AK84: ME100012 | AL84: Corrective lenses | AM84: Qualified | AN84: 46489 | AO84: 1 | AP84: 1 | AQ84: Corrective lenses | AR84: Reviewed - Clear to Drive | AS84: 45579 | AT84: Authorized to Work | AU84: U.S. Passport | AX84: 45579 | AY84: BOF Onboarding Team | AZ84: Complete | BB84: Individual/Sole Proprietor | BC84: SSN | BD84: ***-**-0114 | BF84: 45579 | BG84: Received | BH84: Checking | BI84: Direct Deposit | BJ84: 45579 | BK84: Verified | BL84: 45572 | BM84: E. Barnes | BN84: Sleeper tractor | BO84: 53 ft dry van | BP84: Chicago, IL | BQ84: 4 | BR84: 4 | BS84: 4 | BT84: 4 | BU84: 4 | BV84: 4 | BW84: 4 | BX84: 4 | BY84: 4 | BZ84: Pass | CA84: Corrective lenses | CB84: Passed | CC84: Enrolled | CD84: Query Completed | CE84: 46037 | CF84: 46218 | CH84: Compliant | CJ84: Robert | CK84: Johnson | CL84: IL0000035 | CM84: IL | CN84: CDL Holder | CO84: Robert Johnson | CP84: 45879 | CQ84: 46609 | CR84: (312) 555-0103 | CS84: Dr. Victor Reed | CT84: 45879 | CU84: IL-ME-120233 | CV84: ME100012 | CW84: DO | CX84: IL | CY84: Federal Motor Carrier Safety Regulations | DA84: No | DB84: No | DC84: No | DD84: No | DE84: Yes | DF84: No | DG84: Jane Doe | DH84: Sister | DI84: 555-555-5555 | DJ84: No | DK84: No | DL84: No | DM84: No | DN84: Yes - Appendectomy (2005) | DO84: 20/20 | DP84: 20/20 | DQ84: Pass | DR84: 118 | DS84: 78 | DT84: 72 | DU84: Normal | DV84: 45392 | DW84: 45394 | DX84: Negative | DY84: 45397 | DZ84: BOF Fleet Safety & Compliance Policy 2024 | EA84: Complete | EB84: 45413
A85: DRV-012 | B85: Robert Johnson | C85: 920 Demo Street, Chicago, IL 60605 | D85: 618-555-0101 | E85: ***-**-0114 | F85: Wells Fargo | G85: 109 | H85: 999900205 | I85: Direct Deposit Form | J85: VALID | K85: IL0000039 | L85: 46706 | M85: 46609 | N85: 46519 | P85: Blonde | Q85: Green | R85: 6'-1" | S85: 209 | T85: M | U85: 32874 | V85: DRV-012.png | W85: Caucasian | X85: robertjohnson@example.com | Y85: 920 Demo Street | Z85: Chicago | AA85: IL | AB85: 60605 | AC85: IL | AD85: Class A | AE85: 44884 | AG85: Corrective lenses | AH85: 45879 | AI85: MC-0120411 | AJ85: Dr. Victor Reed | AK85: ME100012 | AL85: Corrective lenses | AM85: Qualified | AN85: 46489 | AO85: 1 | AP85: 1 | AQ85: Corrective lenses | AR85: Reviewed - Clear to Drive | AS85: 45579 | AT85: Authorized to Work | AU85: U.S. Passport | AX85: 45579 | AY85: BOF Onboarding Team | AZ85: Complete | BB85: Individual/Sole Proprietor | BC85: SSN | BD85: ***-**-0114 | BF85: 45579 | BG85: Received | BH85: Checking | BI85: Direct Deposit | BJ85: 45579 | BK85: Verified | BL85: 45572 | BM85: E. Barnes | BN85: Sleeper tractor | BO85: 53 ft dry van | BP85: Chicago, IL | BQ85: 4 | BR85: 4 | BS85: 4 | BT85: 4 | BU85: 4 | BV85: 4 | BW85: 4 | BX85: 4 | BY85: 4 | BZ85: Pass | CA85: Corrective lenses | CB85: Passed | CC85: Enrolled | CD85: Query Completed | CE85: 46037 | CF85: 46218 | CH85: Compliant | CJ85: Robert | CK85: Johnson | CL85: IL0000036 | CM85: IL | CN85: CDL Holder | CO85: Robert Johnson | CP85: 45879 | CQ85: 46609 | CR85: (312) 555-0103 | CS85: Dr. Victor Reed | CT85: 45879 | CU85: IL-ME-120233 | CV85: ME100012 | CW85: DO | CX85: IL | CY85: Federal Motor Carrier Safety Regulations | DA85: No | DB85: No | DC85: No | DD85: No | DE85: Yes | DF85: No | DG85: Jane Doe | DH85: Sister | DI85: 555-555-5555 | DJ85: No | DK85: No | DL85: No | DM85: No | DN85: Yes - Appendectomy (2005) | DO85: 20/20 | DP85: 20/20 | DQ85: Pass | DR85: 118 | DS85: 78 | DT85: 72 | DU85: Normal | DV85: 45392 | DW85: 45394 | DX85: Negative | DY85: 45397 | DZ85: BOF Fleet Safety & Compliance Policy 2024 | EA85: Complete | EB85: 45413
A87: DRV-001 900-00-0123 | D87: John T. Carter
A88: DRV-002 900-00-0105 | D88: Maria E. Lopez
A89: DRV-003 900-00-0116 | D89: Alex J. Kim
A90: DRV-004 900-00-0119 | D90: Priya A. Patel
A91: DRV-005 900-00-0102 | D91: Kenji H. Tanaka
A92: DRV-006 900-00-0101 | D92: Marcus W. Chen
A93: DRV-007 900-00-0109 | D93: Sofia I. Gomez
A94: DRV-008 900-00-0108 | D94: Liam P. Smith
A95: DRV-009 900-00-0124 | D95: Emma C. Brown
A96: DRV-010 900-00-0112 | D96: Noah R. Wilson
A97: DRV-011 900-00-0111 | D97: Olivia M. Lee
A98: DRV-012 900-00-0114 | D98: Robert D. Johnson

Sheet Dispatch
A1: Load ID | B1: Driver ID | C1: Driver Name | D1: Asset ID | E1: Revenue | F1: Backhaul Pay | G1: Driver Signature? | H1: Load Status | I1: Reason for Pending Status | J1: Seal Number (Pickup) | K1: Seal Photo (Pickup) | L1: Seal Number (Delivery) | M1: Seal Photo (Delivery) | N1: Seal Status | O1: Exception Flag | P1: Override Reason | Q1: Audit Log | R1: Compliance Lock | S1: Seal Issue Type | T1: Photo Required? | U1: Review Status | V1: Legacy Driver ID | W1: Revenue Status | X1: Export Load Status | Y1: Rate Confirmation URL | Z1: BOL URL | AA1: Pickup Seal Photo URL | AB1: Delivery Seal Photo URL | AC1: Driver Photo URL | AD1: POD Image URL | AE1: Pickup Image URL | AF1: Delivery Image URL | AG1: Lumper Image URL | AH1: Dispatcher Name | AI1: Broker Name | AJ1: Broker MC Number | AK1: Shipper Name | AL1: Pickup Address | AM1: Pickup City | AN1: Pickup State | AO1: Pickup Appointment | AP1: Consignee Name | AQ1: Delivery Address | AR1: Delivery City | AS1: Delivery State | AT1: Delivery Appointment | AU1: Commodity | AV1: Weight (lbs) | AW1: Pallet Count | AX1: Piece Count | AY1: Trailer Number | AZ1: Rate Confirmation Number | BA1: BOL Number | BB1: POD Received? | BC1: POD Received Timestamp | BD1: Lumper Amount | BE1: RFID Tag ID | BF1: RFID Pickup Read Time | BG1: RFID Delivery Read Time | BH1: RFID Reader Location | BI1: RFID Scan Status | BJ1: RFID Exception | BK1: Insurance Claim ID | BL1: Claim Status | BM1: Claim Type | BN1: Date of Loss | BO1: Claim Amount | BP1: Deductible Amount | BQ1: Adjuster Name | BR1: Insurer Name | BS1: Policy Number | BT1: Origin | BU1: Destination | BV1: Pickup Date | BW1: Delivery Date | BX1: Pickup Time Window | BY1: Delivery Time Window | BZ1: Total Pay | CA1: Linehaul Rate | CB1: Fuel Surcharge | CC1: Detention Pay | CD1: Accessorial Pay | CE1: Miles | CF1: Broker Load Number | CG1: Customer PO Number | CH1: POD Status | CI1: POD URL | CJ1: POD Signed By | CK1: BOL Status | CL1: BOL Generated Date | CM1: Rate Confirmation Status | CN1: Rate Confirmation Date | CO1: RFID Trailer Tag ID | CP1: RFID Cargo Tag ID | CQ1: RFID Last Scan Time | CR1: RFID Last Scan Location | CS1: Insurance Required? | CT1: Claim Notes | CU1: Claim Reserve Amount | CV1: Estimated Claim Exposure | CW1: Insurance Coverage Type | CX1: Incident Report Linked? | CY1: Proof Bundle Complete? | CZ1: Total Revenue | DA1: Driver Pay | DB1: Settlement Hold? | DC1: Settlement Hold Reason | DD1: Proof Status | DE1: Origin State | DF1: Destination State
A2: L-501 | B2: DRV-001 | C2: John Carter | D2: T-102 | E2: 2000 | F2: 65 | G2: NO | H2: DELIVERED | J2: SEAL-83921 | K2: pickup_photo_01.jpg | L2: SEAL-83920 | M2: delivery_photo_01.jpg | N2: =IF(L2="","PENDING",IF(L2<>J2,"MISMATCH","VERIFIED")) -> MISMATCH | O2: =IF(N2="MISMATCH","SEAL_MISMATCH",IF(OR(K2="",M2=""),"PHOTO_MISSING","")) -> SEAL_MISMATCH | Q2: =IF(O2="","",_xludf.CONCAT("Pickup:",J2," | Delivery:",L2," | Override:",IF(P2="","NONE",P2))) -> #NAME? | R2: =IF(O2="","CLEAR",IF(P2="","LOCKED","OVERRIDDEN")) -> LOCKED | S2: SEAL_MISMATCH | T2: YES | U2: OPEN | V2: Driver 1 | W2: READY | X2: DELIVERED | Y2: /documents/loads/L-501_RC.pdf | Z2: /documents/loads/L-501_BOL.pdf | AA2: /documents/loads/L-501_PICKUP_SEAL.jpg | AB2: /documents/loads/L-501_DELIVERY_SEAL.jpg | AC2: /drivers/DRV-001.jpg | AD2: /images/pod/L-501_POD.jpg | AE2: /images/pickup/L-501_PICKUP.jpg | AF2: /images/delivery/L-501_DELIVERY.jpg | AG2: /images/lumper/L-501_LUMPER.jpg | AH2: Tina Brooks | AI2: BlueLine Logistics | AJ2: MC-782104 | AK2: Peachtree Foods | AL2: 1450 Industrial Pkwy | AM2: Atlanta | AN2: GA | AO2: 45839.417 | AP2: Desert Valley Grocers | AQ2: 504 Mesa Park | AR2: Phoenix | AS2: AZ | AT2: 45842.75 | AU2: Frozen foods | AV2: 26024 | AW2: 19 | AX2: 456 | AY2: TRL-2854 | AZ2: RC-501-204 | BA2: BOL-501-9935 | BB2: YES | BC2: 45842.792 | BD2: 315 | BE2: RFID-501-65302 | BF2: 45839.422 | BG2: 45842.758 | BH2: Atlanta Yard Gate 1 | BI2: VERIFIED | BL2: NO_CLAIM | BO2: 0 | BP2: 500 | BR2: Progressive Commercial | BS2: POL-660002 | BT2: Acme Distribution - Cleveland, OH | BU2: Metro Fulfillment - Dallas, TX | BV2: 46204 | BW2: 46205 | BX2: 10:00-13:00 | BY2: 09:00-13:00 | BZ2: 2065 | CA2: 1640 | CB2: 240 | CC2: 0 | CD2: 120 | CE2: 240 | CF2: BLN-100500 | CG2: PO-84000 | CH2: RECEIVED | CI2: /images/pod/L-501_POD.jpg | CJ2: Warehouse Clerk | CK2: UPLOADED | CL2: 46204 | CM2: UPLOADED | CN2: 46203 | CO2: TRAIL-2002 | CP2: CARGO-5002 | CQ2: 46205.427 | CR2: Dock Door 3 | CS2: NO | CT2: No active claim | CU2: 0 | CV2: 0 | CW2: Motor Truck Cargo | CX2: NO | CY2: YES | CZ2: 2065 | DA2: 560 | DB2: NO | DD2: COMPLETE | DE2: GA | DF2: AZ
A3: L-502 | B3: DRV-002 | C3: Maria Lopez | D3: T-101 | E3: 1800 | F3: 95 | G3: NO | H3: IN_TRANSIT | J3: SEAL-55219 | K3: pickup_photo_02.jpg | L3: SEAL-55219 | M3: delivery_photo_02.jpg | N3: =IF(L3="","PENDING",IF(L3<>J3,"MISMATCH","VERIFIED")) -> VERIFIED | O3: =IF(N3="MISMATCH","SEAL_MISMATCH",IF(OR(K3="",M3=""),"PHOTO_MISSING","")) | Q3: =IF(O3="","",_xludf.CONCAT("Pickup:",J3," | Delivery:",L3," | Override:",IF(P3="","NONE",P3))) | R3: =IF(O3="","CLEAR",IF(P3="","LOCKED","OVERRIDDEN")) -> CLEAR | S3: VERIFIED | T3: NO | U3: CLOSED | V3: Driver 2 | W3: PENDING | X3: IN_TRANSIT | Y3: /documents/loads/L-502_RC.pdf | Z3: /documents/loads/L-502_BOL.pdf | AA3: /documents/loads/L-502_PICKUP_SEAL.jpg | AB3: /documents/loads/L-502_DELIVERY_SEAL.jpg | AC3: /drivers/DRV-002.jpg | AD3: /images/pod/L-502_POD.jpg | AE3: /images/pickup/L-502_PICKUP.jpg | AF3: /images/delivery/L-502_DELIVERY.jpg | AG3: /images/lumper/L-502_LUMPER.jpg | AH3: Jamal Reeves | AI3: Summit Freight | AJ3: MC-641255 | AK3: Lakeside Plastics | AL3: 880 Harbor Dr | AM3: Cleveland | AN3: OH | AO3: 45841.5 | AP3: Great Lakes Foods | AQ3: 109 Shoreline Dr | AR3: Detroit | AS3: MI | AT3: 45845.083 | AU3: Dry groceries | AV3: 40981 | AW3: 25 | AX3: 675 | AY3: TRL-2559 | AZ3: RC-502-703 | BA3: BOL-502-5557 | BB3: PENDING | BC3: 46207.458 | BD3: 0 | BE3: RFID-502-30926 | BF3: 45841.522 | BG3: 46207.417 | BH3: Cleveland Yard Gate 3 | BI3: PENDING_DELIVERY | BL3: NO_CLAIM | BO3: 0 | BP3: 500 | BR3: Great West Casualty | BS3: POL-660003 | BT3: Midwest Foods - Chicago, IL | BU3: South Hub DC - Memphis, TN | BV3: 46206 | BW3: 46207 | BX3: 08:00-11:00 | BY3: 10:00-14:00 | BZ3: 1895 | CA3: 1476 | CB3: 216 | CC3: 50 | CD3: 58 | CE3: 297 | CF3: BLN-100501 | CG3: PO-84001 | CH3: PENDING | CI3: /images/pod/L-502_POD.jpg | CJ3: Receiver | CK3: UPLOADED | CL3: 46206 | CM3: UPLOADED | CN3: 46205 | CO3: TRAIL-2003 | CP3: CARGO-5003 | CQ3: 46207.427 | CR3: Yard Gate A | CS3: NO | CT3: No active claim | CU3: 0 | CV3: 0 | CW3: Auto Liability | CX3: NO | CY3: YES | CZ3: 1895 | DA3: 504 | DB3: NO | DD3: COMPLETE | DE3: OH | DF3: MI
A4: L-503 | B4: DRV-003 | C4: Alex Kim | D4: T-107 | E4: 2100 | F4: 45 | G4: NO | H4: DELIVERED | J4: SEAL-77102 | K4: pickup_photo_03.jpg | N4: =IF(L4="","PENDING",IF(L4<>J4,"MISMATCH","VERIFIED")) -> PENDING | O4: =IF(N4="MISMATCH","SEAL_MISMATCH",IF(OR(K4="",M4=""),"PHOTO_MISSING","")) -> PHOTO_MISSING | Q4: =IF(O4="","",_xludf.CONCAT("Pickup:",J4," | Delivery:",L4," | Override:",IF(P4="","NONE",P4))) -> #NAME? | R4: =IF(O4="","CLEAR",IF(P4="","LOCKED","OVERRIDDEN")) -> LOCKED | S4: MISSING_DELIVERY_SEAL | T4: YES | U4: OPEN | V4: Driver 3 | W4: READY | X4: DELIVERED | Y4: /documents/loads/L-503_RC.pdf | Z4: /documents/loads/L-503_BOL.pdf | AA4: /documents/loads/L-503_PICKUP_SEAL.jpg | AB4: /documents/loads/L-503_DELIVERY_SEAL.jpg | AC4: /drivers/DRV-003.jpg | AD4: /images/pod/L-503_POD.jpg | AE4: /images/pickup/L-503_PICKUP.jpg | AF4: /images/delivery/L-503_DELIVERY.jpg | AG4: /images/lumper/L-503_LUMPER.jpg | AH4: Morgan Patel | AI4: IronRoute Transport | AJ4: MC-518903 | AK4: Midwest Paper Co. | AL4: 2210 Mill Rd | AM4: Columbus | AN4: OH | AO4: 45843.625 | AP4: Capital Retail Hub | AQ4: 755 Market Loop | AR4: Indianapolis | AS4: IN | AT4: 45845.042 | AU4: Plastic resins | AV4: 21169 | AW4: 23 | AX4: 1081 | AY4: TRL-2452 | AZ4: RC-503-718 | BA4: BOL-503-5333 | BB4: YES | BC4: 45845.083 | BD4: 240 | BE4: RFID-503-80284 | BF4: 45843.633 | BG4: 45845.09 | BH4: Columbus Yard Gate 4 | BI4: VERIFIED | BJ4: MISREAD_AT_GATE | BK4: CLM-2026004 | BL4: FILED | BM4: Seal Tampering | BN4: 46209 | BO4: 2500 | BP4: 500 | BQ4: Jordan Patel | BR4: Travelers | BS4: POL-660004 | BT4: BlueLine Retail - Indianapolis, IN | BU4: Lakeside Grocery - Atlanta, GA | BV4: 46208 | BW4: 46209 | BX4: 09:00-12:00 | BY4: 11:00-15:00 | BZ4: 2145 | CA4: 1722 | CB4: 252 | CC4: 75 | CD4: 51 | CE4: 354 | CF4: BLN-100502 | CG4: PO-84002 | CH4: RECEIVED | CI4: /images/pod/L-503_POD.jpg | CJ4: Dock Supervisor | CK4: MISSING | CL4: 46208 | CM4: UPLOADED | CN4: 46207 | CO4: TRAIL-2004 | CP4: CARGO-5004 | CQ4: 46209.427 | CR4: Warehouse South | CS4: YES | CT4: No active claim | CU4: 2125 | CV4: 2500 | CW4: General Liability | CX4: YES | CY4: NO | CZ4: 2145 | DA4: 588 | DB4: YES | DC4: Missing proof bundle | DD4: INCOMPLETE | DE4: OH | DF4: IN
A5: L-504 | B5: DRV-004 | C5: Priya Patel | D5: T-108 | E5: 1950 | F5: 88 | G5: YES | H5: PENDING | I5: Awaiting POD | J5: SEAL-61044 | K5: pickup_photo_04.jpg | L5: SEAL-61043 | M5: delivery_photo_04.jpg | N5: =IF(L5="","PENDING",IF(L5<>J5,"MISMATCH","VERIFIED")) -> MISMATCH | O5: =IF(N5="MISMATCH","SEAL_MISMATCH",IF(OR(K5="",M5=""),"PHOTO_MISSING","")) -> SEAL_MISMATCH | P5: Dock supervisor approved | Q5: =IF(O5="","",_xludf.CONCAT("Pickup:",J5," | Delivery:",L5," | Override:",IF(P5="","NONE",P5))) -> #NAME? | R5: =IF(O5="","CLEAR",IF(P5="","LOCKED","OVERRIDDEN")) -> OVERRIDDEN | S5: SEAL_MISMATCH | T5: YES | U5: OPEN | V5: Driver 4 | W5: PENDING | X5: PENDING | Y5: /documents/loads/L-504_RC.pdf | Z5: /documents/loads/L-504_BOL.pdf | AA5: /documents/loads/L-504_PICKUP_SEAL.jpg | AB5: /documents/loads/L-504_DELIVERY_SEAL.jpg | AC5: /drivers/DRV-004.jpg | AD5: /images/pod/L-504_POD.jpg | AE5: /images/pickup/L-504_PICKUP.jpg | AF5: /images/delivery/L-504_DELIVERY.jpg | AG5: /images/lumper/L-504_LUMPER.jpg | AH5: Avery Collins | AI5: NorthStar 3PL | AJ5: MC-774221 | AK5: Sunbelt Beverages | AL5: 9900 Commerce Blvd | AM5: Charlotte | AN5: NC | AO5: 45845.708 | AP5: Bayport Imports | AQ5: 330 Dockside Ln | AR5: Savannah | AS5: GA | AT5: 45848.917 | AU5: Building materials | AV5: 19501 | AW5: 19 | AX5: 836 | AY5: TRL-2396 | AZ5: RC-504-181 | BA5: BOL-504-4814 | BB5: NO | BC5: 46211.458 | BD5: 0 | BE5: RFID-504-59823 | BF5: 45845.724 | BG5: 46211.417 | BH5: Charlotte Yard Gate 4 | BI5: VERIFIED | BJ5: MISREAD | BK5: CLM-504-4432 | BL5: SETTLED | BM5: Shortage | BN5: 45845 | BO5: 9110.39 | BP5: 1500 | BQ5: Kelly Moore | BR5: Travelers Inland Marine | BS5: POL-660086 | BT5: NorthStar Paper - Dallas, TX | BU5: Cleveland Receiver - St. Louis, MO | BV5: 46210 | BW5: 46211 | BX5: 10:00-13:00 | BY5: 09:00-13:00 | BZ5: 2038 | CA5: 1599 | CB5: 234 | CC5: 0 | CD5: 117 | CE5: 411 | CF5: BLN-100503 | CG5: PO-84003 | CH5: RECEIVED | CI5: /images/pod/L-504_POD.jpg | CJ5: Inventory Lead | CK5: UPLOADED | CL5: 46210 | CM5: UPLOADED | CN5: 46209 | CO5: TRAIL-2005 | CP5: CARGO-5005 | CQ5: 46211.427 | CR5: Crossdock Bay 2 | CS5: YES | CT5: Shortage under review | CU5: 7743.8315 | CV5: 7610.39 | CW5: Motor Truck Cargo | CX5: YES | CY5: YES | CZ5: 2038 | DA5: 546 | DB5: NO | DD5: COMPLETE | DE5: NC | DF5: GA
A6: L-505 | B6: DRV-005 | C6: Kenji Tanaka | D6: T-104 | E6: 2200 | F6: 45 | G6: NO | H6: DELIVERED | J6: SEAL-44018 | K6: pickup_photo_05.jpg | L6: SEAL-44018 | M6: delivery_photo_05.jpg | N6: =IF(L6="","PENDING",IF(L6<>J6,"MISMATCH","VERIFIED")) -> VERIFIED | O6: =IF(N6="MISMATCH","SEAL_MISMATCH",IF(OR(K6="",M6=""),"PHOTO_MISSING","")) | Q6: =IF(O6="","",_xludf.CONCAT("Pickup:",J6," | Delivery:",L6," | Override:",IF(P6="","NONE",P6))) | R6: =IF(O6="","CLEAR",IF(P6="","LOCKED","OVERRIDDEN")) -> CLEAR | S6: VERIFIED | T6: NO | U6: CLOSED | V6: Driver 5 | W6: READY | X6: DELIVERED | Y6: /documents/loads/L-505_RC.pdf | Z6: /documents/loads/L-505_BOL.pdf | AA6: /documents/loads/L-505_PICKUP_SEAL.jpg | AB6: /documents/loads/L-505_DELIVERY_SEAL.jpg | AC6: /drivers/DRV-005.jpg | AD6: /images/pod/L-505_POD.jpg | AE6: /images/pickup/L-505_PICKUP.jpg | AF6: /images/delivery/L-505_DELIVERY.jpg | AG6: /images/lumper/L-505_LUMPER.jpg | AH6: Nina Harris | AI6: Pioneer Brokerage | AJ6: MC-699114 | AK6: Frontier Retail DC | AL6: 5600 Warehouse Way | AM6: Dallas | AN6: TX | AO6: 45847.583 | AP6: Metro Supply Chain | AQ6: 120 Junction Rd | AR6: Chicago | AS6: IL | AT6: 45850 | AU6: Paper products | AV6: 26845 | AW6: 19 | AX6: 779 | AY6: TRL-2432 | AZ6: RC-505-963 | BA6: BOL-505-1916 | BB6: YES | BC6: 45850.083 | BD6: 0 | BE6: RFID-505-51347 | BF6: 45847.604 | BG6: 45850.019 | BH6: Dallas Yard Gate 1 | BI6: VERIFIED | BK6: CLM-2026006 | BL6: RESOLVED | BM6: Shortage | BN6: 46213 | BO6: 750 | BP6: 500 | BQ6: Alex Rivera | BR6: Zurich | BS6: POL-660006 | BT6: Rapid Parts - Memphis, TN | BU6: Delta Retail DC - Nashville, TN | BV6: 46212 | BW6: 46213 | BX6: 08:00-11:00 | BY6: 10:00-14:00 | BZ6: 2245 | CA6: 1804 | CB6: 264 | CC6: 25 | CD6: 107 | CE6: 468 | CF6: BLN-100504 | CG6: PO-84004 | CH6: PENDING | CI6: /images/pod/L-505_POD.jpg | CJ6: Warehouse Clerk | CK6: UPLOADED | CL6: 46212 | CM6: UPLOADED | CN6: 46211 | CO6: TRAIL-2006 | CP6: CARGO-5006 | CQ6: 46213.427 | CR6: Receiver Gate 1 | CS6: YES | CT6: Cargo shift photos attached | CU6: 637.5 | CV6: 750 | CW6: Auto Liability | CX6: YES | CY6: YES | CZ6: 2245 | DA6: 616 | DB6: NO | DD6: COMPLETE | DE6: TX | DF6: IL
A7: L-506 | B7: DRV-006 | C7: Marcus Chen | D7: T-103 | E7: 2050 | F7: 72 | G7: YES | H7: DELIVERED | J7: SEAL-99871 | K7: pickup_photo_06.jpg | N7: =IF(L7="","PENDING",IF(L7<>J7,"MISMATCH","VERIFIED")) -> PENDING | O7: =IF(N7="MISMATCH","SEAL_MISMATCH",IF(OR(K7="",M7=""),"PHOTO_MISSING","")) -> PHOTO_MISSING | Q7: =IF(O7="","",_xludf.CONCAT("Pickup:",J7," | Delivery:",L7," | Override:",IF(P7="","NONE",P7))) -> #NAME? | R7: =IF(O7="","CLEAR",IF(P7="","LOCKED","OVERRIDDEN")) -> LOCKED | S7: MISSING_DELIVERY_SEAL | T7: YES | U7: OPEN | V7: Driver 6 | W7: READY | X7: DELIVERED | Y7: /documents/loads/L-506_RC.pdf | Z7: /documents/loads/L-506_BOL.pdf | AA7: /documents/loads/L-506_PICKUP_SEAL.jpg | AB7: /documents/loads/L-506_DELIVERY_SEAL.jpg | AC7: /drivers/DRV-006.jpg | AD7: /images/pod/L-506_POD.jpg | AE7: /images/pickup/L-506_PICKUP.jpg | AF7: /images/delivery/L-506_DELIVERY.jpg | AG7: /images/lumper/L-506_LUMPER.jpg | AH7: Tina Brooks | AI7: BlueLine Logistics | AJ7: MC-782104 | AK7: Ozark Building Supply | AL7: 710 Quarry Rd | AM7: Springfield | AN7: MO | AO7: 45849.708 | AP7: River City Distribution | AQ7: 2100 Depot Ave | AR7: Nashville | AS7: TN | AT7: 45853.167 | AU7: Consumer packaged goods | AV7: 30964 | AW7: 26 | AX7: 624 | AY7: TRL-2371 | AZ7: RC-506-242 | BA7: BOL-506-5040 | BB7: YES | BC7: 45853.417 | BD7: 315 | BE7: RFID-506-80644 | BF7: 45849.723 | BG7: 45853.206 | BH7: Springfield Yard Gate 4 | BI7: VERIFIED | BJ7: NO_FINAL_SCAN | BK7: CLM-506-3266 | BL7: SETTLED | BM7: Late Delivery | BN7: 45853 | BO7: 2268.19 | BP7: 500 | BQ7: Kelly Moore | BR7: Travelers Inland Marine | BS7: POL-757924 | BT7: Prime Consumer - Atlanta, GA | BU7: Union Crossdock - Cleveland, OH | BV7: 46214 | BW7: 46215 | BX7: 09:00-12:00 | BY7: 11:00-15:00 | BZ7: 2122 | CA7: 1681 | CB7: 246 | CC7: 0 | CD7: 123 | CE7: 525 | CF7: BLN-100505 | CG7: PO-84005 | CH7: RECEIVED | CI7: /images/pod/L-506_POD.jpg | CJ7: Receiver | CK7: UPLOADED | CL7: 46214 | CM7: UPLOADED | CN7: 46213 | CO7: TRAIL-2007 | CP7: CARGO-5007 | CQ7: 46215.427 | CR7: Dock Door 3 | CS7: YES | CT7: Minor dock scrape | CU7: 1927.9615 | CV7: 1768.19 | CW7: General Liability | CX7: YES | CY7: YES | CZ7: 2122 | DA7: 574 | DB7: NO | DD7: COMPLETE | DE7: MO | DF7: TN
A8: L-507 | B8: DRV-007 | C8: Sofia Gomez | D8: T-109 | E8: 2300 | F8: 58 | G8: NO | H8: IN_TRANSIT | J8: SEAL-73005 | K8: pickup_photo_07.jpg | L8: SEAL-73099 | M8: delivery_photo_07.jpg | N8: =IF(L8="","PENDING",IF(L8<>J8,"MISMATCH","VERIFIED")) -> MISMATCH | O8: =IF(N8="MISMATCH","SEAL_MISMATCH",IF(OR(K8="",M8=""),"PHOTO_MISSING","")) -> SEAL_MISMATCH | Q8: =IF(O8="","",_xludf.CONCAT("Pickup:",J8," | Delivery:",L8," | Override:",IF(P8="","NONE",P8))) -> #NAME? | R8: =IF(O8="","CLEAR",IF(P8="","LOCKED","OVERRIDDEN")) -> LOCKED | S8: SEAL_MISMATCH | T8: YES | U8: OPEN | V8: Driver 7 | W8: PENDING | X8: IN_TRANSIT | Y8: /documents/loads/L-507_RC.pdf | Z8: /documents/loads/L-507_BOL.pdf | AA8: /documents/loads/L-507_PICKUP_SEAL.jpg | AB8: /documents/loads/L-507_DELIVERY_SEAL.jpg | AC8: /drivers/DRV-007.jpg | AD8: /images/pod/L-507_POD.jpg | AE8: /images/pickup/L-507_PICKUP.jpg | AF8: /images/delivery/L-507_DELIVERY.jpg | AG8: /images/lumper/L-507_LUMPER.jpg | AH8: Jamal Reeves | AI8: Summit Freight | AJ8: MC-641255 | AK8: Prairie Grain Co. | AL8: 443 County Line Rd | AM8: Omaha | AN8: NE | AO8: 45851.708 | AP8: Keystone Wholesale | AQ8: 88 Liberty St | AR8: Pittsburgh | AS8: PA | AT8: 45854.917 | AU8: Beverages | AV8: 30608 | AW8: 24 | AX8: 936 | AY8: TRL-2579 | AZ8: RC-507-641 | BA8: BOL-507-5119 | BB8: PENDING | BC8: 46217.458 | BD8: 315 | BE8: RFID-507-11504 | BF8: 45851.717 | BG8: 46217.417 | BH8: Omaha Yard Gate 3 | BI8: VERIFIED | BJ8: MISREAD_AT_GATE | BL8: NO_CLAIM | BO8: 0 | BP8: 500 | BR8: Great West Casualty | BS8: POL-660008 | BT8: Acme Distribution - St. Louis, MO | BU8: Metro Fulfillment - Chicago, IL | BV8: 46216 | BW8: 46217 | BX8: 10:00-13:00 | BY8: 09:00-13:00 | BZ8: 2358 | CA8: 1886 | CB8: 276 | CC8: 50 | CD8: 88 | CE8: 582 | CF8: BLN-100506 | CG8: PO-84006 | CH8: RECEIVED | CI8: /images/pod/L-507_POD.jpg | CJ8: Dock Supervisor | CK8: MISSING | CL8: 46216 | CM8: UPLOADED | CN8: 46215 | CO8: TRAIL-2008 | CP8: CARGO-5008 | CQ8: 46217.427 | CR8: Yard Gate A | CS8: NO | CT8: No active claim | CU8: 0 | CV8: 0 | CW8: Motor Truck Cargo | CX8: NO | CY8: NO | CZ8: 2358 | DA8: 644 | DB8: YES | DC8: Missing proof bundle | DD8: INCOMPLETE | DE8: NE | DF8: PA
A9: L-508 | B9: DRV-008 | C9: Liam Smith | D9: T-110 | E9: 1750 | F9: 81 | G9: YES | H9: DELIVERED | J9: SEAL-18542 | K9: pickup_photo_08.jpg | L9: SEAL-18542 | M9: delivery_photo_08.jpg | N9: =IF(L9="","PENDING",IF(L9<>J9,"MISMATCH","VERIFIED")) -> VERIFIED | O9: =IF(N9="MISMATCH","SEAL_MISMATCH",IF(OR(K9="",M9=""),"PHOTO_MISSING","")) | Q9: =IF(O9="","",_xludf.CONCAT("Pickup:",J9," | Delivery:",L9," | Override:",IF(P9="","NONE",P9))) | R9: =IF(O9="","CLEAR",IF(P9="","LOCKED","OVERRIDDEN")) -> CLEAR | S9: VERIFIED | T9: NO | U9: CLOSED | V9: Driver 8 | W9: READY | X9: DELIVERED | Y9: /documents/loads/L-508_RC.pdf | Z9: /documents/loads/L-508_BOL.pdf | AA9: /documents/loads/L-508_PICKUP_SEAL.jpg | AB9: /documents/loads/L-508_DELIVERY_SEAL.jpg | AC9: /drivers/DRV-008.jpg | AD9: /images/pod/L-508_POD.jpg | AE9: /images/pickup/L-508_PICKUP.jpg | AF9: /images/delivery/L-508_DELIVERY.jpg | AG9: /images/lumper/L-508_LUMPER.jpg | AH9: Morgan Patel | AI9: IronRoute Transport | AJ9: MC-518903 | AK9: Peachtree Foods | AL9: 1450 Industrial Pkwy | AM9: Atlanta | AN9: GA | AO9: 45853.75 | AP9: Desert Valley Grocers | AQ9: 504 Mesa Park | AR9: Phoenix | AS9: AZ | AT9: 45855.083 | AU9: Auto parts | AV9: 34403 | AW9: 17 | AX9: 612 | AY9: TRL-2208 | AZ9: RC-508-991 | BA9: BOL-508-5889 | BB9: YES | BC9: 45855.333 | BD9: 315 | BE9: RFID-508-89818 | BF9: 45853.762 | BG9: 45855.097 | BH9: Atlanta Yard Gate 3 | BI9: VERIFIED | BJ9: DUPLICATE_SCAN | BK9: CLM-508-9689 | BL9: OPEN | BM9: Shortage | BN9: 45855 | BO9: 6722.38 | BP9: 500 | BQ9: Alicia Gomez | BR9: Great West Casualty | BS9: POL-351083 | BT9: Midwest Foods - Nashville, TN | BU9: South Hub DC - Indianapolis, IN | BV9: 46218 | BW9: 46219 | BX9: 08:00-11:00 | BY9: 10:00-14:00 | BZ9: 1831 | CA9: 1435 | CB9: 210 | CC9: 75 | CD9: 30 | CE9: 639 | CF9: BLN-100507 | CG9: PO-84007 | CH9: PENDING | CI9: /images/pod/L-508_POD.jpg | CJ9: Inventory Lead | CK9: UPLOADED | CL9: 46218 | CM9: UPLOADED | CN9: 46217 | CO9: TRAIL-2009 | CP9: CARGO-5009 | CQ9: 46219.427 | CR9: Warehouse South | CS9: YES | CT9: No active claim | CU9: 5714.023 | CV9: 6222.38 | CW9: Auto Liability | CX9: YES | CY9: YES | CZ9: 1831 | DA9: 490 | DB9: NO | DD9: COMPLETE | DE9: GA | DF9: AZ
A10: L-509 | B10: DRV-009 | C10: Emma Brown | D10: T-111 | E10: 2400 | F10: 49 | G10: NO | H10: PENDING | I10: Customer hold | J10: SEAL-26790 | K10: pickup_photo_09.jpg | L10: SEAL-26791 | M10: delivery_photo_09.jpg | N10: =IF(L10="","PENDING",IF(L10<>J10,"MISMATCH","VERIFIED")) -> MISMATCH | O10: =IF(N10="MISMATCH","SEAL_MISMATCH",IF(OR(K10="",M10=""),"PHOTO_MISSING","")) -> SEAL_MISMATCH | P10: Carrier note logged | Q10: =IF(O10="","",_xludf.CONCAT("Pickup:",J10," | Delivery:",L10," | Override:",IF(P10="","NONE",P10))) -> #NAME? | R10: =IF(O10="","CLEAR",IF(P10="","LOCKED","OVERRIDDEN")) -> OVERRIDDEN | S10: SEAL_MISMATCH | T10: YES | U10: OPEN | V10: Driver 9 | W10: PENDING | X10: PENDING | Y10: /documents/loads/L-509_RC.pdf | Z10: /documents/loads/L-509_BOL.pdf | AA10: /documents/loads/L-509_PICKUP_SEAL.jpg | AB10: /documents/loads/L-509_DELIVERY_SEAL.jpg | AC10: /drivers/DRV-009.jpg | AD10: /images/pod/L-509_POD.jpg | AE10: /images/pickup/L-509_PICKUP.jpg | AF10: /images/delivery/L-509_DELIVERY.jpg | AG10: /images/lumper/L-509_LUMPER.jpg | AH10: Avery Collins | AI10: NorthStar 3PL | AJ10: MC-774221 | AK10: Lakeside Plastics | AL10: 880 Harbor Dr | AM10: Cleveland | AN10: OH | AO10: 45855.5 | AP10: Great Lakes Foods | AQ10: 109 Shoreline Dr | AR10: Detroit | AS10: MI | AT10: 45858.708 | AU10: Frozen foods | AV10: 20806 | AW10: 27 | AX10: 1242 | AY10: TRL-2170 | AZ10: RC-509-878 | BA10: BOL-509-9727 | BB10: NO | BC10: 46221.458 | BD10: 125 | BE10: RFID-509-26828 | BF10: 45855.524 | BG10: 46221.417 | BH10: Cleveland Yard Gate 2 | BI10: PENDING_DELIVERY | BL10: NO_CLAIM | BO10: 0 | BP10: 500 | BR10: Nationwide | BS10: POL-660010 | BT10: BlueLine Retail - Cleveland, OH | BU10: Lakeside Grocery - Dallas, TX | BV10: 46220 | BW10: 46221 | BX10: 09:00-12:00 | BY10: 11:00-15:00 | BZ10: 2449 | CA10: 1967 | CB10: 288 | CC10: 0 | CD10: 145 | CE10: 696 | CF10: BLN-100508 | CG10: PO-84008 | CH10: RECEIVED | CI10: /images/pod/L-509_POD.jpg | CJ10: Warehouse Clerk | CK10: UPLOADED | CL10: 46220 | CM10: UPLOADED | CN10: 46219 | CO10: TRAIL-2010 | CP10: CARGO-5010 | CQ10: 46221.427 | CR10: Crossdock Bay 2 | CS10: NO | CT10: No active claim | CU10: 0 | CV10: 0 | CW10: General Liability | CX10: NO | CY10: YES | CZ10: 2449 | DA10: 672 | DB10: NO | DD10: COMPLETE | DE10: OH | DF10: MI
A11: L-510 | B11: DRV-010 | C11: Noah Wilson | D11: T-105 | E11: 1900 | F11: 77 | G11: YES | H11: DELIVERED | J11: SEAL-48113 | K11: pickup_photo_10.jpg | N11: =IF(L11="","PENDING",IF(L11<>J11,"MISMATCH","VERIFIED")) -> PENDING | O11: =IF(N11="MISMATCH","SEAL_MISMATCH",IF(OR(K11="",M11=""),"PHOTO_MISSING","")) -> PHOTO_MISSING | Q11: =IF(O11="","",_xludf.CONCAT("Pickup:",J11," | Delivery:",L11," | Override:",IF(P11="","NONE",P11))) -> #NAME? | R11: =IF(O11="","CLEAR",IF(P11="","LOCKED","OVERRIDDEN")) -> LOCKED | S11: MISSING_DELIVERY_SEAL | T11: YES | U11: OPEN | V11: Driver 10 | W11: READY | X11: DELIVERED | Y11: /documents/loads/L-510_RC.pdf | Z11: /documents/loads/L-510_BOL.pdf | AA11: /documents/loads/L-510_PICKUP_SEAL.jpg | AB11: /documents/loads/L-510_DELIVERY_SEAL.jpg | AC11: /drivers/DRV-010.jpg | AD11: /images/pod/L-510_POD.jpg | AE11: /images/pickup/L-510_PICKUP.jpg | AF11: /images/delivery/L-510_DELIVERY.jpg | AG11: /images/lumper/L-510_LUMPER.jpg | AH11: Nina Harris | AI11: Pioneer Brokerage | AJ11: MC-699114 | AK11: Midwest Paper Co. | AL11: 2210 Mill Rd | AM11: Columbus | AN11: OH | AO11: 45857.625 | AP11: Capital Retail Hub | AQ11: 755 Market Loop | AR11: Indianapolis | AS11: IN | AT11: 45860.958 | AU11: Dry groceries | AV11: 31074 | AW11: 23 | AX11: 782 | AY11: TRL-2629 | AZ11: RC-510-562 | BA11: BOL-510-2982 | BB11: YES | BC11: 45861.042 | BD11: 125 | BE11: RFID-510-18392 | BF11: 45857.643 | BG11: 45860.966 | BH11: Columbus Yard Gate 2 | BI11: VERIFIED | BK11: CLM-510-1964 | BL11: OPEN | BM11: Cargo Damage | BN11: 45860 | BO11: 11390.7 | BP11: 1000 | BQ11: Kelly Moore | BR11: Travelers Inland Marine | BS11: POL-392004 | BT11: NorthStar Paper - Chicago, IL | BU11: Cleveland Receiver - Memphis, TN | BV11: 46222 | BW11: 46223 | BX11: 10:00-13:00 | BY11: 09:00-13:00 | BZ11: 1977 | CA11: 1558 | CB11: 228 | CC11: 25 | CD11: 89 | CE11: 753 | CF11: BLN-100509 | CG11: PO-84009 | CH11: RECEIVED | CI11: /images/pod/L-510_POD.jpg | CJ11: Receiver | CK11: UPLOADED | CL11: 46222 | CM11: UPLOADED | CN11: 46221 | CO11: TRAIL-2011 | CP11: CARGO-5011 | CQ11: 46223.427 | CR11: Receiver Gate 1 | CS11: YES | CT11: Cargo shift photos attached | CU11: 9682.095 | CV11: 10390.7 | CW11: Motor Truck Cargo | CX11: YES | CY11: YES | CZ11: 1977 | DA11: 532 | DB11: NO | DD11: COMPLETE | DE11: OH | DF11: IN
